Workbook

Sheet Resumo
A1: RESUMO DA COTAÇÃO — 20/10/2026 (PARCIAL)
A2: DIMEC x MEDCENTRO por EAN. Palmed (CAST/MAB) entra após correlação. Regra: não comprar com reajuste > limite (Premissas).
A3: Indicador | B3: Valor
A4: Itens na Lista de Compra | B4: =COUNTA(Cotação!$C$6:$C$5941) -> 5936
A5: Valor da lista (Qtd sugerida × preço ref.) | B5: =SUMPRODUCT(Cotação!$I$6:$I$5941,Cotação!$M$6:$M$5941) -> 464600.39
A6: Itens com ao menos 1 oferta | B6: =COUNTIF(Cotação!$AA$6:$AA$5941,"<>SEM OFERTA") -> 1096
A7: Itens SEM oferta | B7: =COUNTIF(Cotação!$AA$6:$AA$5941,"SEM OFERTA") -> 4840
A8: Itens a COMPRAR | B8: =COUNTIF(Cotação!$AA$6:$AA$5941,"COMPRAR") -> 576
A9: Itens bloqueados (reajuste > limite) | B9: =COUNTIF(Cotação!$AA$6:$AA$5941,"NÃO*") -> 504
A10: Itens p/ verificar unidade/embalagem | B10: =COUNTIF(Cotação!$AA$6:$AA$5941,"VERIFICAR*") -> 16
A11: Valor total do pedido | B11: =SUM(Cotação!$AD$6:$AD$5941) -> 35018.49
A12: Mesmos itens ao preço de referência | B12: =SUMPRODUCT((Cotação!$AA$6:$AA$5941="COMPRAR")*Cotação!$AC$6:$AC$5941*Cotação!$M$6:$M$5941) -> 35665.449
A13: Economia total vs. referência | B13: =SUM(Cotação!$AE$6:$AE$5941) -> 646.95848
A14: Economia % | B14: =IFERROR(B13/B12,0) -> 0.018139642
A15: Itens com estoque insuficiente no vencedor | B15: =COUNTIF(Cotação!$AF$6:$AF$5941,"ESTOQUE INSUFICIENTE") -> 30
A16: Itens em empate técnico (dif. < R$0,01) | B16: =COUNTIF(Cotação!$AF$6:$AF$5941,"EMPATE TÉCNICO") -> 4
A18: PEDIDO POR DISTRIBUIDOR
A19: Distribuidor | B19: Itens vencedores | C19: Itens a comprar | D19: Caixas | E19: Valor pedido | F19: Economia vs ref. | G19: % do pedido | H19: Itens bloqueados (>5%)
A20: DIMEC | B20: =COUNTIF(Cotação!$W$6:$W$5941,A20) -> 598 | C20: =COUNTIFS(Cotação!$W$6:$W$5941,A20,Cotação!$AA$6:$AA$5941,"COMPRAR") -> 292 | D20: =SUMIFS(Cotação!$AC$6:$AC$5941,Cotação!$W$6:$W$5941,A20) -> 3492 | E20: =SUMIFS(Cotação!$AD$6:$AD$5941,Cotação!$W$6:$W$5941,A20) -> 17429.269 | F20: =SUMIFS(Cotação!$AE$6:$AE$5941,Cotação!$W$6:$W$5941,A20) -> 500.75131 | G20: =IFERROR(E20/$E$24,0) -> 0.49771616 | H20: =COUNTIFS(Cotação!$W$6:$W$5941,A20,Cotação!$AA$6:$AA$5941,"NÃO*") -> 293
A21: MEDCENTRO | B21: =COUNTIF(Cotação!$W$6:$W$5941,A21) -> 498 | C21: =COUNTIFS(Cotação!$W$6:$W$5941,A21,Cotação!$AA$6:$AA$5941,"COMPRAR") -> 284 | D21: =SUMIFS(Cotação!$AC$6:$AC$5941,Cotação!$W$6:$W$5941,A21) -> 2088 | E21: =SUMIFS(Cotação!$AD$6:$AD$5941,Cotação!$W$6:$W$5941,A21) -> 17589.221 | F21: =SUMIFS(Cotação!$AE$6:$AE$5941,Cotação!$W$6:$W$5941,A21) -> 146.20716 | G21: =IFERROR(E21/$E$24,0) -> 0.50228384 | H21: =COUNTIFS(Cotação!$W$6:$W$5941,A21,Cotação!$AA$6:$AA$5941,"NÃO*") -> 211
A22: PALMED CAST | B22: =COUNTIF(Cotação!$W$6:$W$5941,A22) -> 0 | C22: =COUNTIFS(Cotação!$W$6:$W$5941,A22,Cotação!$AA$6:$AA$5941,"COMPRAR") -> 0 | D22: =SUMIFS(Cotação!$AC$6:$AC$5941,Cotação!$W$6:$W$5941,A22) -> 0 | E22: =SUMIFS(Cotação!$AD$6:$AD$5941,Cotação!$W$6:$W$5941,A22) -> 0 | F22: =SUMIFS(Cotação!$AE$6:$AE$5941,Cotação!$W$6:$W$5941,A22) -> 0 | G22: =IFERROR(E22/$E$24,0) -> 0 | H22: =COUNTIFS(Cotação!$W$6:$W$5941,A22,Cotação!$AA$6:$AA$5941,"NÃO*") -> 0
A23: PALMED MAB | B23: =COUNTIF(Cotação!$W$6:$W$5941,A23) -> 0 | C23: =COUNTIFS(Cotação!$W$6:$W$5941,A23,Cotação!$AA$6:$AA$5941,"COMPRAR") -> 0 | D23: =SUMIFS(Cotação!$AC$6:$AC$5941,Cotação!$W$6:$W$5941,A23) -> 0 | E23: =SUMIFS(Cotação!$AD$6:$AD$5941,Cotação!$W$6:$W$5941,A23) -> 0 | F23: =SUMIFS(Cotação!$AE$6:$AE$5941,Cotação!$W$6:$W$5941,A23) -> 0 | G23: =IFERROR(E23/$E$24,0) -> 0 | H23: =COUNTIFS(Cotação!$W$6:$W$5941,A23,Cotação!$AA$6:$AA$5941,"NÃO*") -> 0
A24: TOTAL | B24: =SUM(B20:B23) -> 1096 | C24: =SUM(C20:C23) -> 576 | D24: =SUM(D20:D23) -> 5580 | E24: =SUM(E20:E23) -> 35018.49 | F24: =SUM(F20:F23) -> 646.95848 | G24: =SUM(G20:G23) -> 1 | H24: =SUM(H20:H23) -> 504
A27: DIMEC x MEDCENTRO — itens ofertados pelos dois
A28: Itens com preço nos dois | B28: =SUMPRODUCT((Cotação!$N$6:$N$5941<>"")*(Cotação!$R$6:$R$5941<>"")) -> 364
A29: DIMEC mais barata | B29: =SUMPRODUCT((Cotação!$N$6:$N$5941<>"")*(Cotação!$R$6:$R$5941<>"")*(Cotação!$N$6:$N$5941<Cotação!$O$6:$O$5941)) -> 175
A30: MEDCENTRO mais barata (já c/ desconto) | B30: =SUMPRODUCT((Cotação!$N$6:$N$5941<>"")*(Cotação!$R$6:$R$5941<>"")*(Cotação!$O$6:$O$5941<Cotação!$N$6:$N$5941)) -> 189
A31: Empate | B31: =B28-B29-B30 -> 0
A34: POR CURVA ABC
A35: Curva | B35: Itens lista | C35: Itens a comprar | D35: Bloqueados >5% | E35: Valor pedido | F35: Economia
A36: A | B36: =COUNTIF(Cotação!$F$6:$F$5941,A36) -> 1448 | C36: =COUNTIFS(Cotação!$F$6:$F$5941,A36,Cotação!$AA$6:$AA$5941,"COMPRAR") -> 192 | D36: =COUNTIFS(Cotação!$F$6:$F$5941,A36,Cotação!$AA$6:$AA$5941,"NÃO*") -> 160 | E36: =SUMIFS(Cotação!$AD$6:$AD$5941,Cotação!$F$6:$F$5941,A36) -> 23312.359 | F36: =SUMIFS(Cotação!$AE$6:$AE$5941,Cotação!$F$6:$F$5941,A36) -> 401.46352
A37: B | B37: =COUNTIF(Cotação!$F$6:$F$5941,A37) -> 1241 | C37: =COUNTIFS(Cotação!$F$6:$F$5941,A37,Cotação!$AA$6:$AA$5941,"COMPRAR") -> 189 | D37: =COUNTIFS(Cotação!$F$6:$F$5941,A37,Cotação!$AA$6:$AA$5941,"NÃO*") -> 126 | E37: =SUMIFS(Cotação!$AD$6:$AD$5941,Cotação!$F$6:$F$5941,A37) -> 8242.9571 | F37: =SUMIFS(Cotação!$AE$6:$AE$5941,Cotação!$F$6:$F$5941,A37) -> 66.478426
A38: C | B38: =COUNTIF(Cotação!$F$6:$F$5941,A38) -> 3247 | C38: =COUNTIFS(Cotação!$F$6:$F$5941,A38,Cotação!$AA$6:$AA$5941,"COMPRAR") -> 195 | D38: =COUNTIFS(Cotação!$F$6:$F$5941,A38,Cotação!$AA$6:$AA$5941,"NÃO*") -> 218 | E38: =SUMIFS(Cotação!$AD$6:$AD$5941,Cotação!$F$6:$F$5941,A38) -> 3463.1737 | F38: =SUMIFS(Cotação!$AE$6:$AE$5941,Cotação!$F$6:$F$5941,A38) -> 179.01653
A44: PALMED — CAST x MAB (encarte, antes da correlação)
A45: Códigos no encarte (únicos) | B45: =COUNTA('Palmed CAST x MAB'!A4:A829) -> 826
A46: Só CAST | B46: =COUNTIFS('Palmed CAST x MAB'!E4:E829,"<>",'Palmed CAST x MAB'!H4:H829,"") -> 183
A47: Só MAB | B47: =COUNTIFS('Palmed CAST x MAB'!H4:H829,"<>",'Palmed CAST x MAB'!E4:E829,"") -> 238
A48: Nos dois setores | B48: =COUNT('Palmed CAST x MAB'!L4:L829) -> 405
A49: CAST mais barato | B49: =COUNTIF('Palmed CAST x MAB'!L4:L829,"<0") -> 87
A50: MAB mais barato | B50: =COUNTIF('Palmed CAST x MAB'!L4:L829,">0") -> 104
A51: Mesmo preço | B51: =COUNTIF('Palmed CAST x MAB'!L4:L829,0) -> 214

Sheet Cotação
A1: COTAÇÃO — Drogarias Rocha — 20/10/2026 (PARCIAL: DIMEC x MEDCENTRO; Palmed aguardando correlação)
A2: Casamento por EAN. MEDCENTRO com desconto adicional e limite de reajuste definidos na aba Premissas.
N4: DIMEC | O4: MEDCENTRO | P4: PALMED CAST | Q4: PALMED MAB
A5: Cód. interno | B5: EAN | C5: Produto | D5: Fabricante | E5: Un/Cx | F5: ABC | G5: Est. rede (un) | H5: Dem./mês (un) | I5: Qtd sugerida (cx) | J5: Últ. preço compra (un) | K5: Custo un (lista) | L5: Melhor 3m (un) | M5: Preço ref. (CAIXA) | N5: DIMEC | O5: MEDCENTRO (líq. -5%) | P5: PALMED CAST | Q5: PALMED MAB | R5: MEDC tabela | S5: DIMEC estoque | T5: DIMEC un/cx | U5: MEDC estoque | V5: Melhor preço (cx) | W5: Vencedor | X5: 2º melhor preço | Y5: Var. vs ref. | Z5: Var. vs melhor 3m | AA5: Decisão | AB5: Estoque vencedor | AC5: Qtd pedido (cx) | AD5: Valor pedido | AE5: Economia vs ref. | AF5: Alerta | AG5: Últ. fornecedor | AH5: Grupo
A6: 550941 | B6: 7894488000101 | C6: FLOCONETES SEGUROS E ABSORVENTES 75UN | D6: SPARTEX IND. | E6: 1 | F6: C | G6: 1 | H6: 0.6 | I6: 1 | J6: 1.35 | K6: 1.35 | L6: 1.35 | M6: =IF(J6>0,J6,K6)*E6 -> 1.35 | N6: 1.35 | O6: =IF(R6="","",ROUND(R6*(1-Premissas!$B$4),4)) | S6: 1677 | T6: 12 | V6: =IF(COUNT(N6:Q6)=0,"",MIN(N6:Q6)) -> 1.35 | W6: =IF(V6="","",INDEX($N$4:$Q$4,MATCH(V6,N6:Q6,0))) -> DIMEC | X6: =IF(COUNT(N6:Q6)<2,"",SMALL(N6:Q6,2)) | Y6: =IF(OR(V6="",M6=0),"",V6/M6-1) -> 0 | Z6: =IF(OR(V6="",L6=""),"",V6/(L6*E6)-1) -> 0 | AA6: =IF(V6="","SEM OFERTA",IF(OR(Y6>Premissas!$B$11,Y6<Premissas!$B$12),"VERIFICAR - UNIDADE/EMBALAGEM",IF(Y6>Premissas!$B$6,"NÃO COMPRAR - REAJUSTE >5%","COMPRAR"))) -> COMPRAR | AB6: =IF(W6="DIMEC",S6,IF(W6="MEDCENTRO",U6,"")) -> 1677 | AC6: =IF(AA6<>"COMPRAR",0,IF(AB6="",I6,MIN(I6,AB6))) -> 1 | AD6: =IF(AC6>0,AC6*V6,0) -> 1.35 | AE6: =IF(AC6>0,(M6-V6)*AC6,0) -> 0 | AF6: =IF(AA6<>"COMPRAR","",IF(AB6="",IF(X6="","",IF(X6-V6<0.01,"EMPATE TÉCNICO","")),IF(AB6<I6,"ESTOQUE INSUFICIENTE",IF(X6="","",IF(X6-V6<0.01,"EMPATE TÉCNICO",""))))) | AG6: JLCS COMERCIO E DISTRIBUICAO DE ALIMENTO LTDA | AH6: ABSORVENTES
A7: 643491 | B7: 7896699032520 | C7: 1560-01-F MAM TIP 80ML SIL R F CX C/6 - LOLLY | D7: LOLLY | E7: 1 | F7: B | G7: 1 | H7: 0.5 | I7: 1 | J7: 12.8 | K7: 12.8 | L7: 12.8 | M7: =IF(J7>0,J7,K7)*E7 -> 12.8 | O7: =IF(R7="","",ROUND(R7*(1-Premissas!$B$4),4)) -> 12.3215 | R7: 12.97 | U7: 78 | V7: =IF(COUNT(N7:Q7)=0,"",MIN(N7:Q7)) -> 12.3215 | W7: =IF(V7="","",INDEX($N$4:$Q$4,MATCH(V7,N7:Q7,0))) -> MEDCENTRO | X7: =IF(COUNT(N7:Q7)<2,"",SMALL(N7:Q7,2)) | Y7: =IF(OR(V7="",M7=0),"",V7/M7-1) -> -0.037382813 | Z7: =IF(OR(V7="",L7=""),"",V7/(L7*E7)-1) -> -0.037382813 | AA7: =IF(V7="","SEM OFERTA",IF(OR(Y7>Premissas!$B$11,Y7<Premissas!$B$12),"VERIFICAR - UNIDADE/EMBALAGEM",IF(Y7>Premissas!$B$6,"NÃO COMPRAR - REAJUSTE >5%","COMPRAR"))) -> COMPRAR | AB7: =IF(W7="DIMEC",S7,IF(W7="MEDCENTRO",U7,"")) -> 78 | AC7: =IF(AA7<>"COMPRAR",0,IF(AB7="",I7,MIN(I7,AB7))) -> 1 | AD7: =IF(AC7>0,AC7*V7,0) -> 12.3215 | AE7: =IF(AC7>0,(M7-V7)*AC7,0) -> 0.4785 | AF7: =IF(AA7<>"COMPRAR","",IF(AB7="",IF(X7="","",IF(X7-V7<0.01,"EMPATE TÉCNICO","")),IF(AB7<I7,"ESTOQUE INSUFICIENTE",IF(X7="","",IF(X7-V7<0.01,"EMPATE TÉCNICO",""))))) | AG7: BATEL COMERCIO DE ALIMENTOS LTDA | AH7: BABY/KIDS
A8: 643501 | B8: 7896699032537 | C8: 1560-01-M MAM TIP 80ML SIL R M LOLLY | D8: LOLLY | E8: 1 | F8: C | G8: 2 | H8: 0.8 | I8: 1 | J8: 12.8 | K8: 12.8 | L8: 12.26 | M8: =IF(J8>0,J8,K8)*E8 -> 12.8 | O8: =IF(R8="","",ROUND(R8*(1-Premissas!$B$4),4)) -> 12.3215 | R8: 12.97 | U8: 29 | V8: =IF(COUNT(N8:Q8)=0,"",MIN(N8:Q8)) -> 12.3215 | W8: =IF(V8="","",INDEX($N$4:$Q$4,MATCH(V8,N8:Q8,0))) -> MEDCENTRO | X8: =IF(COUNT(N8:Q8)<2,"",SMALL(N8:Q8,2)) | Y8: =IF(OR(V8="",M8=0),"",V8/M8-1) -> -0.037382813 | Z8: =IF(OR(V8="",L8=""),"",V8/(L8*E8)-1) -> 0.0050163132 | AA8: =IF(V8="","SEM OFERTA",IF(OR(Y8>Premissas!$B$11,Y8<Premissas!$B$12),"VERIFICAR - UNIDADE/EMBALAGEM",IF(Y8>Premissas!$B$6,"NÃO COMPRAR - REAJUSTE >5%","COMPRAR"))) -> COMPRAR | AB8: =IF(W8="DIMEC",S8,IF(W8="MEDCENTRO",U8,"")) -> 29 | AC8: =IF(AA8<>"COMPRAR",0,IF(AB8="",I8,MIN(I8,AB8))) -> 1 | AD8: =IF(AC8>0,AC8*V8,0) -> 12.3215 | AE8: =IF(AC8>0,(M8-V8)*AC8,0) -> 0.4785 | AF8: =IF(AA8<>"COMPRAR","",IF(AB8="",IF(X8="","",IF(X8-V8<0.01,"EMPATE TÉCNICO","")),IF(AB8<I8,"ESTOQUE INSUFICIENTE",IF(X8="","",IF(X8-V8<0.01,"EMPATE TÉCNICO",""))))) | AG8: BATEL COMERCIO DE ALIMENTOS LTDA | AH8: BABY/KIDS
A9: 643511 | B9: 7896699015479 | C9: 1970-01-F MINI MAM CLEAN 50ML F - LOLLY | D9: LOLLY | E9: 1 | F9: B | G9: 1 | H9: 4.3 | I9: 11 | J9: 9.07 | K9: 9.07 | L9: 9.07 | M9: =IF(J9>0,J9,K9)*E9 -> 9.07 | O9: =IF(R9="","",ROUND(R9*(1-Premissas!$B$4),4)) -> 9.12 | R9: 9.6 | U9: 333 | V9: =IF(COUNT(N9:Q9)=0,"",MIN(N9:Q9)) -> 9.12 | W9: =IF(V9="","",INDEX($N$4:$Q$4,MATCH(V9,N9:Q9,0))) -> MEDCENTRO | X9: =IF(COUNT(N9:Q9)<2,"",SMALL(N9:Q9,2)) | Y9: =IF(OR(V9="",M9=0),"",V9/M9-1) -> 0.0055126792 | Z9: =IF(OR(V9="",L9=""),"",V9/(L9*E9)-1) -> 0.0055126792 | AA9: =IF(V9="","SEM OFERTA",IF(OR(Y9>Premissas!$B$11,Y9<Premissas!$B$12),"VERIFICAR - UNIDADE/EMBALAGEM",IF(Y9>Premissas!$B$6,"NÃO COMPRAR - REAJUSTE >5%","COMPRAR"))) -> COMPRAR | AB9: =IF(W9="DIMEC",S9,IF(W9="MEDCENTRO",U9,"")) -> 333 | AC9: =IF(AA9<>"COMPRAR",0,IF(AB9="",I9,MIN(I9,AB9))) -> 11 | AD9: =IF(AC9>0,AC9*V9,0) -> 100.32 | AE9: =IF(AC9>0,(M9-V9)*AC9,0) -> -0.55 | AF9: =IF(AA9<>"COMPRAR","",IF(AB9="",IF(X9="","",IF(X9-V9<0.01,"EMPATE TÉCNICO","")),IF(AB9<I9,"ESTOQUE INSUFICIENTE",IF(X9="","",IF(X9-V9<0.01,"EMPATE TÉCNICO",""))))) | AG9: BATEL COMERCIO DE ALIMENTOS LTDA | AH9: BABY/KIDS
A10: 643521 | B10: 7896699015455 | C10: 1970-01-M MINI MAM CLEAN 50ML M CX C/6 - LOLLY | D10: LOLLY | E10: 1 | F10: B | G10: 0 | H10: 2.1 | I10: 6 | J10: 9.07 | K10: 9.07 | L10: 9.07 | M10: =IF(J10>0,J10,K10)*E10 -> 9.07 | O10: =IF(R10="","",ROUND(R10*(1-Premissas!$B$4),4)) -> 9.12 | R10: 9.6 | U10: 250 | V10: =IF(COUNT(N10:Q10)=0,"",MIN(N10:Q10)) -> 9.12 | W10: =IF(V10="","",INDEX($N$4:$Q$4,MATCH(V10,N10:Q10,0))) -> MEDCENTRO | X10: =IF(COUNT(N10:Q10)<2,"",SMALL(N10:Q10,2)) | Y10: =IF(OR(V10="",M10=0),"",V10/M10-1) -> 0.0055126792 | Z10: =IF(OR(V10="",L10=""),"",V10/(L10*E10)-1) -> 0.0055126792 | AA10: =IF(V10="","SEM OFERTA",IF(OR(Y10>Premissas!$B$11,Y10<Premissas!$B$12),"VERIFICAR - UNIDADE/EMBALAGEM",IF(Y10>Premissas!$B$6,"NÃO COMPRAR - REAJUSTE >5%","COMPRAR"))) -> COMPRAR | AB10: =IF(W10="DIMEC",S10,IF(W10="MEDCENTRO",U10,"")) -> 250 | AC10: =IF(AA10<>"COMPRAR",0,IF(AB10="",I10,MIN(I10,AB10))) -> 6 | AD10: =IF(AC10>0,AC10*V10,0) -> 54.72 | AE10: =IF(AC10>0,(M10-V10)*AC10,0) -> -0.3 | AF10: =IF(AA10<>"COMPRAR","",IF(AB10="",IF(X10="","",IF(X10-V10<0.01,"EMPATE TÉCNICO","")),IF(AB10<I10,"ESTOQUE INSUFICIENTE",IF(X10="","",IF(X10-V10<0.01,"EMPATE TÉCNICO",""))))) | AG10: BATEL COMERCIO DE ALIMENTOS LTDA | AH10: BABY/KIDS
A11: 643541 | B11: 7896699019217 | C11: 3262-01-F MAM TRICOLOR 250ML SIL O F CX/6 - LOLLY | D11: LOLLY | E11: 1 | F11: B | G11: 1 | H11: 0.5 | I11: 1 | J11: 13.71 | K11: 13.71 | L11: 13.71 | M11: =IF(J11>0,J11,K11)*E11 -> 13.71 | O11: =IF(R11="","",ROUND(R11*(1-Premissas!$B$4),4)) -> 19.7695 | R11: 20.81 | U11: 6 | V11: =IF(COUNT(N11:Q11)=0,"",MIN(N11:Q11)) -> 19.7695 | W11: =IF(V11="","",INDEX($N$4:$Q$4,MATCH(V11,N11:Q11,0))) -> MEDCENTRO | X11: =IF(COUNT(N11:Q11)<2,"",SMALL(N11:Q11,2)) | Y11: =IF(OR(V11="",M11=0),"",V11/M11-1) -> 0.44197666 | Z11: =IF(OR(V11="",L11=""),"",V11/(L11*E11)-1) -> 0.44197666 | AA11: =IF(V11="","SEM OFERTA",IF(OR(Y11>Premissas!$B$11,Y11<Premissas!$B$12),"VERIFICAR - UNIDADE/EMBALAGEM",IF(Y11>Premissas!$B$6,"NÃO COMPRAR - REAJUSTE >5%","COMPRAR"))) -> NÃO COMPRAR - REAJUSTE >5% | AB11: =IF(W11="DIMEC",S11,IF(W11="MEDCENTRO",U11,"")) -> 6 | AC11: =IF(AA11<>"COMPRAR",0,IF(AB11="",I11,MIN(I11,AB11))) -> 0 | AD11: =IF(AC11>0,AC11*V11,0) -> 0 | AE11: =IF(AC11>0,(M11-V11)*AC11,0) -> 0 | AF11: =IF(AA11<>"COMPRAR","",IF(AB11="",IF(X11="","",IF(X11-V11<0.01,"EMPATE TÉCNICO","")),IF(AB11<I11,"ESTOQUE INSUFICIENTE",IF(X11="","",IF(X11-V11<0.01,"EMPATE TÉCNICO",""))))) | AG11: BATEL COMERCIO DE ALIMENTOS LTDA | AH11: BABY/KIDS
A12: 643571 | B12: 7896699022330 | C12: 4512-01-N CH BORBOLETA SIL R T2 N - LOLLY | D12: LOLLY | E12: 1 | F12: C | G12: 1 | H12: 1.2 | I12: 2 | J12: 6.8 | K12: 6.8 | L12: 6.8 | M12: =IF(J12>0,J12,K12)*E12 -> 6.8 | O12: =IF(R12="","",ROUND(R12*(1-Premissas!$B$4),4)) -> 8.056 | R12: 8.48 | U12: 28 | V12: =IF(COUNT(N12:Q12)=0,"",MIN(N12:Q12)) -> 8.056 | W12: =IF(V12="","",INDEX($N$4:$Q$4,MATCH(V12,N12:Q12,0))) -> MEDCENTRO | X12: =IF(COUNT(N12:Q12)<2,"",SMALL(N12:Q12,2)) | Y12: =IF(OR(V12="",M12=0),"",V12/M12-1) -> 0.18470588 | Z12: =IF(OR(V12="",L12=""),"",V12/(L12*E12)-1) -> 0.18470588 | AA12: =IF(V12="","SEM OFERTA",IF(OR(Y12>Premissas!$B$11,Y12<Premissas!$B$12),"VERIFICAR - UNIDADE/EMBALAGEM",IF(Y12>Premissas!$B$6,"NÃO COMPRAR - REAJUSTE >5%","COMPRAR"))) -> NÃO COMPRAR - REAJUSTE >5% | AB12: =IF(W12="DIMEC",S12,IF(W12="MEDCENTRO",U12,"")) -> 28 | AC12: =IF(AA12<>"COMPRAR",0,IF(AB12="",I12,MIN(I12,AB12))) -> 0 | AD12: =IF(AC12>0,AC12*V12,0) -> 0 | AE12: =IF(AC12>0,(M12-V12)*AC12,0) -> 0 | AF12: =IF(AA12<>"COMPRAR","",IF(AB12="",IF(X12="","",IF(X12-V12<0.01,"EMPATE TÉCNICO","")),IF(AB12<I12,"ESTOQUE INSUFICIENTE",IF(X12="","",IF(X12-V12<0.01,"EMPATE TÉCNICO",""))))) | AG12: BATEL COMERCIO DE ALIMENTOS LTDA | AH12: BABY/KIDS
A13: 643581 | B13: 7896699022484 | C13: 4515-01-F CH TIP BORBOLETA SIL O T2 F CX/6 - LOLLY | D13: LOLLY | E13: 1 | F13: C | G13: 1 | H13: 1.4 | I13: 3 | J13: 7.25 | K13: 7.25 | L13: 7.25 | M13: =IF(J13>0,J13,K13)*E13 -> 7.25 | O13: =IF(R13="","",ROUND(R13*(1-Premissas!$B$4),4)) -> 8.056 | R13: 8.48 | U13: 140 | V13: =IF(COUNT(N13:Q13)=0,"",MIN(N13:Q13)) -> 8.056 | W13: =IF(V13="","",INDEX($N$4:$Q$4,MATCH(V13,N13:Q13,0))) -> MEDCENTRO | X13: =IF(COUNT(N13:Q13)<2,"",SMALL(N13:Q13,2)) | Y13: =IF(OR(V13="",M13=0),"",V13/M13-1) -> 0.11117241 | Z13: =IF(OR(V13="",L13=""),"",V13/(L13*E13)-1) -> 0.11117241 | AA13: =IF(V13="","SEM OFERTA",IF(OR(Y13>Premissas!$B$11,Y13<Premissas!$B$12),"VERIFICAR - UNIDADE/EMBALAGEM",IF(Y13>Premissas!$B$6,"NÃO COMPRAR - REAJUSTE >5%","COMPRAR"))) -> NÃO COMPRAR - REAJUSTE >5% | AB13: =IF(W13="DIMEC",S13,IF(W13="MEDCENTRO",U13,"")) -> 140 | AC13: =IF(AA13<>"COMPRAR",0,IF(AB13="",I13,MIN(I13,AB13))) -> 0 | AD13: =IF(AC13>0,AC13*V13,0) -> 0 | AE13: =IF(AC13>0,(M13-V13)*AC13,0) -> 0 | AF13: =IF(AA13<>"COMPRAR","",IF(AB13="",IF(X13="","",IF(X13-V13<0.01,"EMPATE TÉCNICO","")),IF(AB13<I13,"ESTOQUE INSUFICIENTE",IF(X13="","",IF(X13-V13<0.01,"EMPATE TÉCNICO",""))))) | AG13: BATEL COMERCIO DE ALIMENTOS LTDA | AH13: BABY/KIDS
A14: 657171 | B14: 7896699021982 | C14: 4814-01-AZ CH ZOO BONA SIL O T1 AZUL CX/6 - LOLLY | D14: LOLLY | E14: 1 | F14: C | G14: 3 | H14: 2.1 | I14: 3 | J14: 6.35 | K14: 6.35 | L14: 6.35 | M14: =IF(J14>0,J14,K14)*E14 -> 6.35 | O14: =IF(R14="","",ROUND(R14*(1-Premissas!$B$4),4)) -> 7.6 | R14: 8 | U14: 88 | V14: =IF(COUNT(N14:Q14)=0,"",MIN(N14:Q14)) -> 7.6 | W14: =IF(V14="","",INDEX($N$4:$Q$4,MATCH(V14,N14:Q14,0))) -> MEDCENTRO | X14: =IF(COUNT(N14:Q14)<2,"",SMALL(N14:Q14,2)) | Y14: =IF(OR(V14="",M14=0),"",V14/M14-1) -> 0.19685039 | Z14: =IF(OR(V14="",L14=""),"",V14/(L14*E14)-1) -> 0.19685039 | AA14: =IF(V14="","SEM OFERTA",IF(OR(Y14>Premissas!$B$11,Y14<Premissas!$B$12),"VERIFICAR - UNIDADE/EMBALAGEM",IF(Y14>Premissas!$B$6,"NÃO COMPRAR - REAJUSTE >5%","COMPRAR"))) -> NÃO COMPRAR - REAJUSTE >5% | AB14: =IF(W14="DIMEC",S14,IF(W14="MEDCENTRO",U14,"")) -> 88 | AC14: =IF(AA14<>"COMPRAR",0,IF(AB14="",I14,MIN(I14,AB14))) -> 0 | AD14: =IF(AC14>0,AC14*V14,0) -> 0 | AE14: =IF(AC14>0,(M14-V14)*AC14,0) -> 0 | AF14: =IF(AA14<>"COMPRAR","",IF(AB14="",IF(X14="","",IF(X14-V14<0.01,"EMPATE TÉCNICO","")),IF(AB14<I14,"ESTOQUE INSUFICIENTE",IF(X14="","",IF(X14-V14<0.01,"EMPATE TÉCNICO",""))))) | AG14: BATEL COMERCIO DE ALIMENTOS LTDA | AH14: BABY/KIDS
A15: 653461 | B15: 7896699033244 | C15: 4915-01-F CH VIVA SIL O T2 F LOLLY | D15: LOLLY | E15: 1 | F15: C | G15: 0 | H15: 0.1 | I15: 1 | J15: 8.76 | K15: 8.76 | L15: 8.76 | M15: =IF(J15>0,J15,K15)*E15 -> 8.76 | O15: =IF(R15="","",ROUND(R15*(1-Premissas!$B$4),4)) -> 8.8065 | R15: 9.27 | U15: 36 | V15: =IF(COUNT(N15:Q15)=0,"",MIN(N15:Q15)) -> 8.8065 | W15: =IF(V15="","",INDEX($N$4:$Q$4,MATCH(V15,N15:Q15,0))) -> MEDCENTRO | X15: =IF(COUNT(N15:Q15)<2,"",SMALL(N15:Q15,2)) | Y15: =IF(OR(V15="",M15=0),"",V15/M15-1) -> 0.0053082192 | Z15: =IF(OR(V15="",L15=""),"",V15/(L15*E15)-1) -> 0.0053082192 | AA15: =IF(V15="","SEM OFERTA",IF(OR(Y15>Premissas!$B$11,Y15<Premissas!$B$12),"VERIFICAR - UNIDADE/EMBALAGEM",IF(Y15>Premissas!$B$6,"NÃO COMPRAR - REAJUSTE >5%","COMPRAR"))) -> COMPRAR | AB15: =IF(W15="DIMEC",S15,IF(W15="MEDCENTRO",U15,"")) -> 36 | AC15: =IF(AA15<>"COMPRAR",0,IF(AB15="",I15,MIN(I15,AB15))) -> 1 | AD15: =IF(AC15>0,AC15*V15,0) -> 8.8065 | AE15: =IF(AC15>0,(M15-V15)*AC15,0) -> -0.0465 | AF15: =IF(AA15<>"COMPRAR","",IF(AB15="",IF(X15="","",IF(X15-V15<0.01,"EMPATE TÉCNICO","")),IF(AB15<I15,"ESTOQUE INSUFICIENTE",IF(X15="","",IF(X15-V15<0.01,"EMPATE TÉCNICO",""))))) | AG15: BATEL COMERCIO DE ALIMENTOS LTDA | AH15: BABY/KIDS
A16: 653581 | B16: 7896699025195 | C16: 5214-01-F CH OCEANO SIL O T1 ROSA CX/6 - LOLLY | D16: LOLLY | E16: 1 | F16: B | G16: 1 | H16: 1.6 | I16: 4 | J16: 8.46 | K16: 8.46 | L16: 8.46 | M16: =IF(J16>0,J16,K16)*E16 -> 8.46 | O16: =IF(R16="","",ROUND(R16*(1-Premissas!$B$4),4)) -> 10.051 | R16: 10.58 | U16: 152 | V16: =IF(COUNT(N16:Q16)=0,"",MIN(N16:Q16)) -> 10.051 | W16: =IF(V16="","",INDEX($N$4:$Q$4,MATCH(V16,N16:Q16,0))) -> MEDCENTRO | X16: =IF(COUNT(N16:Q16)<2,"",SMALL(N16:Q16,2)) | Y16: =IF(OR(V16="",M16=0),"",V16/M16-1) -> 0.18806147 | Z16: =IF(OR(V16="",L16=""),"",V16/(L16*E16)-1) -> 0.18806147 | AA16: =IF(V16="","SEM OFERTA",IF(OR(Y16>Premissas!$B$11,Y16<Premissas!$B$12),"VERIFICAR - UNIDADE/EMBALAGEM",IF(Y16>Premissas!$B$6,"NÃO COMPRAR - REAJUSTE >5%","COMPRAR"))) -> NÃO COMPRAR - REAJUSTE >5% | AB16: =IF(W16="DIMEC",S16,IF(W16="MEDCENTRO",U16,"")) -> 152 | AC16: =IF(AA16<>"COMPRAR",0,IF(AB16="",I16,MIN(I16,AB16))) -> 0 | AD16: =IF(AC16>0,AC16*V16,0) -> 0 | AE16: =IF(AC16>0,(M16-V16)*AC16,0) -> 0 | AF16: =IF(AA16<>"COMPRAR","",IF(AB16="",IF(X16="","",IF(X16-V16<0.01,"EMPATE TÉCNICO","")),IF(AB16<I16,"ESTOQUE INSUFICIENTE",IF(X16="","",IF(X16-V16<0.01,"EMPATE TÉCNICO",""))))) | AG16: BATEL COMERCIO DE ALIMENTOS LTDA | AH16: BABY/KIDS
A17: 643591 | B17: 7896699032230 | C17: 6014-01-F CH 100% SILICONE OT1 F LOLLY | D17: LOLLY | E17: 1 | F17: B | G17: 0 | H17: 0.7 | I17: 2 | J17: 15.13 | K17: 15.13 | L17: 15.13 | M17: =IF(J17>0,J17,K17)*E17 -> 15.13 | O17: =IF(R17="","",ROUND(R17*(1-Premissas!$B$4),4)) -> 15.2095 | R17: 16.01 | U17: 472 | V17: =IF(COUNT(N17:Q17)=0,"",MIN(N17:Q17)) -> 15.2095 | W17: =IF(V17="","",INDEX($N$4:$Q$4,MATCH(V17,N17:Q17,0))) -> MEDCENTRO | X17: =IF(COUNT(N17:Q17)<2,"",SMALL(N17:Q17,2)) | Y17: =IF(OR(V17="",M17=0),"",V17/M17-1) -> 0.0052544613 | Z17: =IF(OR(V17="",L17=""),"",V17/(L17*E17)-1) -> 0.0052544613 | AA17: =IF(V17="","SEM OFERTA",IF(OR(Y17>Premissas!$B$11,Y17<Premissas!$B$12),"VERIFICAR - UNIDADE/EMBALAGEM",IF(Y17>Premissas!$B$6,"NÃO COMPRAR - REAJUSTE >5%","COMPRAR"))) -> COMPRAR | AB17: =IF(W17="DIMEC",S17,IF(W17="MEDCENTRO",U17,"")) -> 472 | AC17: =IF(AA17<>"COMPRAR",0,IF(AB17="",I17,MIN(I17,AB17))) -> 2 | AD17: =IF(AC17>0,AC17*V17,0) -> 30.419 | AE17: =IF(AC17>0,(M17-V17)*AC17,0) -> -0.159 | AF17: =IF(AA17<>"COMPRAR","",IF(AB17="",IF(X17="","",IF(X17-V17<0.01,"EMPATE TÉCNICO","")),IF(AB17<I17,"ESTOQUE INSUFICIENTE",IF(X17="","",IF(X17-V17<0.01,"EMPATE TÉCNICO",""))))) | AG17: BATEL COMERCIO DE ALIMENTOS LTDA | AH17: BABY/KIDS
A18: 643631 | B18: 7896699019989 | C18: 7225-01 TIRA LEITE LOLLY | D18: LOLLY | E18: 1 | F18: C | G18: 2 | H18: 0.9 | I18: 1 | J18: 26.35 | K18: 26.35 | L18: 26.35 | M18: =IF(J18>0,J18,K18)*E18 -> 26.35 | O18: =IF(R18="","",ROUND(R18*(1-Premissas!$B$4),4)) -> 32.1195 | R18: 33.81 | U18: 96 | V18: =IF(COUNT(N18:Q18)=0,"",MIN(N18:Q18)) -> 32.1195 | W18: =IF(V18="","",INDEX($N$4:$Q$4,MATCH(V18,N18:Q18,0))) -> MEDCENTRO | X18: =IF(COUNT(N18:Q18)<2,"",SMALL(N18:Q18,2)) | Y18: =IF(OR(V18="",M18=0),"",V18/M18-1) -> 0.21895636 | Z18: =IF(OR(V18="",L18=""),"",V18/(L18*E18)-1) -> 0.21895636 | AA18: =IF(V18="","SEM OFERTA",IF(OR(Y18>Premissas!$B$11,Y18<Premissas!$B$12),"VERIFICAR - UNIDADE/EMBALAGEM",IF(Y18>Premissas!$B$6,"NÃO COMPRAR - REAJUSTE >5%","COMPRAR"))) -> NÃO COMPRAR - REAJUSTE >5% | AB18: =IF(W18="DIMEC",S18,IF(W18="MEDCENTRO",U18,"")) -> 96 | AC18: =IF(AA18<>"COMPRAR",0,IF(AB18="",I18,MIN(I18,AB18))) -> 0 | AD18: =IF(AC18>0,AC18*V18,0) -> 0 | AE18: =IF(AC18>0,(M18-V18)*AC18,0) -> 0 | AF18: =IF(AA18<>"COMPRAR","",IF(AB18="",IF(X18="","",IF(X18-V18<0.01,"EMPATE TÉCNICO","")),IF(AB18<I18,"ESTOQUE INSUFICIENTE",IF(X18="","",IF(X18-V18<0.01,"EMPATE TÉCNICO",""))))) | AG18: BATEL COMERCIO DE ALIMENTOS LTDA | AH18: BABY/KIDS
... A20: 610631 | B20: 7896699011617 | C20: BICO MAMAD SIL BIG REDONDO | D20: LOLLY | E20: 1 | F20: C | G20: 2 | H20: 0.9 | I20: 1 | J20: 7.51 | K20: 7.51 | L20: 7.51 | M20: =IF(J20>0,J20,K20)*E20 -> 7.51 | O20: =IF(R20="","",ROUND(R20*(1-Premissas!$B$4),4)) -> 7.828 | R20: 8.24 | U20: 391 | V20: =IF(COUNT(N20:Q20)=0,"",MIN(N20:Q20)) -> 7.828 | W20: =IF(V20="","",INDEX($N$4:$Q$4,MATCH(V20,N20:Q20,0))) -> MEDCENTRO | X20: =IF(COUNT(N20:Q20)<2,"",SMALL(N20:Q20,2)) | Y20: =IF(OR(V20="",M20=0),"",V20/M20-1) -> 0.042343542 | Z20: =IF(OR(V20="",L20=""),"",V20/(L20*E20)-1) -> 0.042343542 | AA20: =IF(V20="","SEM OFERTA",IF(OR(Y20>Premissas!$B$11,Y20<Premissas!$B$12),"VERIFICAR - UNIDADE/EMBALAGEM",IF(Y20>Premissas!$B$6,"NÃO COMPRAR - REAJUSTE >5%","COMPRAR"))) -> COMPRAR | AB20: =IF(W20="DIMEC",S20,IF(W20="MEDCENTRO",U20,"")) -> 391 | AC20: =IF(AA20<>"COMPRAR",0,IF(AB20="",I20,MIN(I20,AB20))) -> 1 | AD20: =IF(AC20>0,AC20*V20,0) -> 7.828 | AE20: =IF(AC20>0,(M20-V20)*AC20,0) -> -0.318 | AF20: =IF(AA20<>"COMPRAR","",IF(AB20="",IF(X20="","",IF(X20-V20<0.01,"EMPATE TÉCNICO","")),IF(AB20<I20,"ESTOQUE INSUFICIENTE",IF(X20="","",IF(X20-V20<0.01,"EMPATE TÉCNICO",""))))) | AG20: M C F RODRIGUES DE ANDRADE DIST IMPORT EXP ALIMENTO EIRELI | AH20: BABY/KIDS
A21: 619101 | B21: 7898953484243 | C21: BICO P/ SERINGA DE LAVAGEN NASAL C/2 | D21: 3B | E21: 1 | F21: B | G21: 11 | H21: 5 | I21: 2 | J21: 4.3 | K21: 4.3 | L21: 4.3 | M21: =IF(J21>0,J21,K21)*E21 -> 4.3 | N21: 4.3 | O21: =IF(R21="","",ROUND(R21*(1-Premissas!$B$4),4)) -> 4.37 | R21: 4.6 | S21: 988 | T21: 100 | U21: 252 | V21: =IF(COUNT(N21:Q21)=0,"",MIN(N21:Q21)) -> 4.3 | W21: =IF(V21="","",INDEX($N$4:$Q$4,MATCH(V21,N21:Q21,0))) -> DIMEC | X21: =IF(COUNT(N21:Q21)<2,"",SMALL(N21:Q21,2)) -> 4.37 | Y21: =IF(OR(V21="",M21=0),"",V21/M21-1) -> 0 | Z21: =IF(OR(V21="",L21=""),"",V21/(L21*E21)-1) -> 0 | AA21: =IF(V21="","SEM OFERTA",IF(OR(Y21>Premissas!$B$11,Y21<Premissas!$B$12),"VERIFICAR - UNIDADE/EMBALAGEM",IF(Y21>Premissas!$B$6,"NÃO COMPRAR - REAJUSTE >5%","COMPRAR"))) -> COMPRAR | AB21: =IF(W21="DIMEC",S21,IF(W21="MEDCENTRO",U21,"")) -> 988 | AC21: =IF(AA21<>"COMPRAR",0,IF(AB21="",I21,MIN(I21,AB21))) -> 2 | AD21: =IF(AC21>0,AC21*V21,0) -> 8.6 | AE21: =IF(AC21>0,(M21-V21)*AC21,0) -> 0 | AF21: =IF(AA21<>"COMPRAR","",IF(AB21="",IF(X21="","",IF(X21-V21<0.01,"EMPATE TÉCNICO","")),IF(AB21<I21,"ESTOQUE INSUFICIENTE",IF(X21="","",IF(X21-V21<0.01,"EMPATE TÉCNICO",""))))) | AG21: CENTROFARMA DISTRIBUIDORA FARMACEUTICA LTDA | AH21: BABY/KIDS
A22: 603521 | B22: 7896033233736 | C22: CANECA LILLO AP S 150ML MENINA | D22: LILLO | E22: 1 | F22: C | G22: 0 | H22: 0.1 | I22: 1 | J22: 25.77 | K22: 25.77 | L22: 25.77 | M22: =IF(J22>0,J22,K22)*E22 -> 25.77 | O22: =IF(R22="","",ROUND(R22*(1-Premissas!$B$4),4)) -> 25.346 | R22: 26.68 | U22: 18 | V22: =IF(COUNT(N22:Q22)=0,"",MIN(N22:Q22)) -> 25.346 | W22: =IF(V22="","",INDEX($N$4:$Q$4,MATCH(V22,N22:Q22,0))) -> MEDCENTRO | X22: =IF(COUNT(N22:Q22)<2,"",SMALL(N22:Q22,2)) | Y22: =IF(OR(V22="",M22=0),"",V22/M22-1) -> -0.01645324 | Z22: =IF(OR(V22="",L22=""),"",V22/(L22*E22)-1) -> -0.01645324 | AA22: =IF(V22="","SEM OFERTA",IF(OR(Y22>Premissas!$B$11,Y22<Premissas!$B$12),"VERIFICAR - UNIDADE/EMBALAGEM",IF(Y22>Premissas!$B$6,"NÃO COMPRAR - REAJUSTE >5%","COMPRAR"))) -> COMPRAR | AB22: =IF(W22="DIMEC",S22,IF(W22="MEDCENTRO",U22,"")) -> 18 | AC22: =IF(AA22<>"COMPRAR",0,IF(AB22="",I22,MIN(I22,AB22))) -> 1 | AD22: =IF(AC22>0,AC22*V22,0) -> 25.346 | AE22: =IF(AC22>0,(M22-V22)*AC22,0) -> 0.424 | AF22: =IF(AA22<>"COMPRAR","",IF(AB22="",IF(X22="","",IF(X22-V22<0.01,"EMPATE TÉCNICO","")),IF(AB22<I22,"ESTOQUE INSUFICIENTE",IF(X22="","",IF(X22-V22<0.01,"EMPATE TÉCNICO",""))))) | AG22: CENTROFARMA DISTRIBUIDORA FARMACEUTICA LTDA | AH22: BABY/KIDS
A23: 603531 | B23: 7896033233729 | C23: CANECA LILLO AP S 150ML MENINO | D23: LILLO | E23: 1 | F23: C | G23: 0 | H23: 0.2 | I23: 1 | J23: 25.77 | K23: 25.77 | L23: 25.77 | M23: =IF(J23>0,J23,K23)*E23 -> 25.77 | O23: =IF(R23="","",ROUND(R23*(1-Premissas!$B$4),4)) -> 24.035 | R23: 25.3 | U23: 3 | V23: =IF(COUNT(N23:Q23)=0,"",MIN(N23:Q23)) -> 24.035 | W23: =IF(V23="","",INDEX($N$4:$Q$4,MATCH(V23,N23:Q23,0))) -> MEDCENTRO | X23: =IF(COUNT(N23:Q23)<2,"",SMALL(N23:Q23,2)) | Y23: =IF(OR(V23="",M23=0),"",V23/M23-1) -> -0.067326348 | Z23: =IF(OR(V23="",L23=""),"",V23/(L23*E23)-1) -> -0.067326348 | AA23: =IF(V23="","SEM OFERTA",IF(OR(Y23>Premissas!$B$11,Y23<Premissas!$B$12),"VERIFICAR - UNIDADE/EMBALAGEM",IF(Y23>Premissas!$B$6,"NÃO COMPRAR - REAJUSTE >5%","COMPRAR"))) -> COMPRAR | AB23: =IF(W23="DIMEC",S23,IF(W23="MEDCENTRO",U23,"")) -> 3 | AC23: =IF(AA23<>"COMPRAR",0,IF(AB23="",I23,MIN(I23,AB23))) -> 1 | AD23: =IF(AC23>0,AC23*V23,0) -> 24.035 | AE23: =IF(AC23>0,(M23-V23)*AC23,0) -> 1.735 | AF23: =IF(AA23<>"COMPRAR","",IF(AB23="",IF(X23="","",IF(X23-V23<0.01,"EMPATE TÉCNICO","")),IF(AB23<I23,"ESTOQUE INSUFICIENTE",IF(X23="","",IF(X23-V23<0.01,"EMPATE TÉCNICO",""))))) | AG23: CENTROFARMA DISTRIBUIDORA FARMACEUTICA LTDA | AH23: BABY/KIDS
A24: 660051 | B24: 7896699011983 | C24: CHOCALHO INFANTIL N - LOLLY | D24: LOLLY | E24: 1 | F24: C | G24: 1 | H24: 0.7 | I24: 1 | J24: 13.79 | K24: 13.79 | L24: 13.79 | M24: =IF(J24>0,J24,K24)*E24 -> 13.79 | O24: =IF(R24="","",ROUND(R24*(1-Premissas!$B$4),4)) -> 15.048 | R24: 15.84 | U24: 122 | V24: =IF(COUNT(N24:Q24)=0,"",MIN(N24:Q24)) -> 15.048 | W24: =IF(V24="","",INDEX($N$4:$Q$4,MATCH(V24,N24:Q24,0))) -> MEDCENTRO | X24: =IF(COUNT(N24:Q24)<2,"",SMALL(N24:Q24,2)) | Y24: =IF(OR(V24="",M24=0),"",V24/M24-1) -> 0.091225526 | Z24: =IF(OR(V24="",L24=""),"",V24/(L24*E24)-1) -> 0.091225526 | AA24: =IF(V24="","SEM OFERTA",IF(OR(Y24>Premissas!$B$11,Y24<Premissas!$B$12),"VERIFICAR - UNIDADE/EMBALAGEM",IF(Y24>Premissas!$B$6,"NÃO COMPRAR - REAJUSTE >5%","COMPRAR"))) -> NÃO COMPRAR - REAJUSTE >5% | AB24: =IF(W24="DIMEC",S24,IF(W24="MEDCENTRO",U24,"")) -> 122 | AC24: =IF(AA24<>"COMPRAR",0,IF(AB24="",I24,MIN(I24,AB24))) -> 0 | AD24: =IF(AC24>0,AC24*V24,0) -> 0 | AE24: =IF(AC24>0,(M24-V24)*AC24,0) -> 0 | AF24: =IF(AA24<>"COMPRAR","",IF(AB24="",IF(X24="","",IF(X24-V24<0.01,"EMPATE TÉCNICO","")),IF(AB24<I24,"ESTOQUE INSUFICIENTE",IF(X24="","",IF(X24-V24<0.01,"EMPATE TÉCNICO",""))))) | AG24: BATEL COMERCIO DE ALIMENTOS LTDA | AH24: BABY/KIDS
A25: 629761 | B25: 7896699015936 | C25: CHOCALHO LOLLY AZUL | D25: LOLLY | E25: 1 | F25: C | G25: 0 | H25: 0.1 | I25: 1 | J25: 14.97 | K25: 14.97 | L25: 14.97 | M25: =IF(J25>0,J25,K25)*E25 -> 14.97 | O25: =IF(R25="","",ROUND(R25*(1-Premissas!$B$4),4)) -> 15.048 | R25: 15.84 | U25: 340 | V25: =IF(COUNT(N25:Q25)=0,"",MIN(N25:Q25)) -> 15.048 | W25: =IF(V25="","",INDEX($N$4:$Q$4,MATCH(V25,N25:Q25,0))) -> MEDCENTRO | X25: =IF(COUNT(N25:Q25)<2,"",SMALL(N25:Q25,2)) | Y25: =IF(OR(V25="",M25=0),"",V25/M25-1) -> 0.0052104208 | Z25: =IF(OR(V25="",L25=""),"",V25/(L25*E25)-1) -> 0.0052104208 | AA25: =IF(V25="","SEM OFERTA",IF(OR(Y25>Premissas!$B$11,Y25<Premissas!$B$12),"VERIFICAR - UNIDADE/EMBALAGEM",IF(Y25>Premissas!$B$6,"NÃO COMPRAR - REAJUSTE >5%","COMPRAR"))) -> COMPRAR | AB25: =IF(W25="DIMEC",S25,IF(W25="MEDCENTRO",U25,"")) -> 340 | AC25: =IF(AA25<>"COMPRAR",0,IF(AB25="",I25,MIN(I25,AB25))) -> 1 | AD25: =IF(AC25>0,AC25*V25,0) -> 15.048 | AE25: =IF(AC25>0,(M25-V25)*AC25,0) -> -0.078 | AF25: =IF(AA25<>"COMPRAR","",IF(AB25="",IF(X25="","",IF(X25-V25<0.01,"EMPATE TÉCNICO","")),IF(AB25<I25,"ESTOQUE INSUFICIENTE",IF(X25="","",IF(X25-V25<0.01,"EMPATE TÉCNICO",""))))) | AG25: M C F RODRIGUES DE ANDRADE DIST IMPORT EXP ALIMENTO EIRELI | AH25: BABY/KIDS
A26: 629771 | B26: 7896699015950 | C26: CHOCALHO LOLLY ROSA | D26: LOLLY | E26: 1 | F26: C | G26: 0 | H26: 0 | I26: 1 | J26: 14.49 | K26: 14.49 | L26: 14.49 | M26: =IF(J26>0,J26,K26)*E26 -> 14.49 | O26: =IF(R26="","",ROUND(R26*(1-Premissas!$B$4),4)) -> 15.048 | R26: 15.84 | U26: 258 | V26: =IF(COUNT(N26:Q26)=0,"",MIN(N26:Q26)) -> 15.048 | W26: =IF(V26="","",INDEX($N$4:$Q$4,MATCH(V26,N26:Q26,0))) -> MEDCENTRO | X26: =IF(COUNT(N26:Q26)<2,"",SMALL(N26:Q26,2)) | Y26: =IF(OR(V26="",M26=0),"",V26/M26-1) -> 0.038509317 | Z26: =IF(OR(V26="",L26=""),"",V26/(L26*E26)-1) -> 0.038509317 | AA26: =IF(V26="","SEM OFERTA",IF(OR(Y26>Premissas!$B$11,Y26<Premissas!$B$12),"VERIFICAR - UNIDADE/EMBALAGEM",IF(Y26>Premissas!$B$6,"NÃO COMPRAR - REAJUSTE >5%","COMPRAR"))) -> COMPRAR | AB26: =IF(W26="DIMEC",S26,IF(W26="MEDCENTRO",U26,"")) -> 258 | AC26: =IF(AA26<>"COMPRAR",0,IF(AB26="",I26,MIN(I26,AB26))) -> 1 | AD26: =IF(AC26>0,AC26*V26,0) -> 15.048 | AE26: =IF(AC26>0,(M26-V26)*AC26,0) -> -0.558 | AF26: =IF(AA26<>"COMPRAR","",IF(AB26="",IF(X26="","",IF(X26-V26<0.01,"EMPATE TÉCNICO","")),IF(AB26<I26,"ESTOQUE INSUFICIENTE",IF(X26="","",IF(X26-V26<0.01,"EMPATE TÉCNICO",""))))) | AG26: M C F RODRIGUES DE ANDRADE DIST IMPORT EXP ALIMENTO EIRELI | AH26: BABY/KIDS
A27: 663371 | B27: 7896699021746 | C27: CHUPETA BONA SIL R T1 M - LOLLY | D27: LOLLY | E27: 1 | F27: C | G27: 2 | H27: 1.1 | I27: 1 | J27: 6.1 | K27: 6.1 | L27: 6.1 | M27: =IF(J27>0,J27,K27)*E27 -> 6.1 | O27: =IF(R27="","",ROUND(R27*(1-Premissas!$B$4),4)) -> 7.6 | R27: 8 | U27: 140 | V27: =IF(COUNT(N27:Q27)=0,"",MIN(N27:Q27)) -> 7.6 | W27: =IF(V27="","",INDEX($N$4:$Q$4,MATCH(V27,N27:Q27,0))) -> MEDCENTRO | X27: =IF(COUNT(N27:Q27)<2,"",SMALL(N27:Q27,2)) | Y27: =IF(OR(V27="",M27=0),"",V27/M27-1) -> 0.24590164 | Z27: =IF(OR(V27="",L27=""),"",V27/(L27*E27)-1) -> 0.24590164 | AA27: =IF(V27="","SEM OFERTA",IF(OR(Y27>Premissas!$B$11,Y27<Premissas!$B$12),"VERIFICAR - UNIDADE/EMBALAGEM",IF(Y27>Premissas!$B$6,"NÃO COMPRAR - REAJUSTE >5%","COMPRAR"))) -> NÃO COMPRAR - REAJUSTE >5% | AB27: =IF(W27="DIMEC",S27,IF(W27="MEDCENTRO",U27,"")) -> 140 | AC27: =IF(AA27<>"COMPRAR",0,IF(AB27="",I27,MIN(I27,AB27))) -> 0 | AD27: =IF(AC27>0,AC27*V27,0) -> 0 | AE27: =IF(AC27>0,(M27-V27)*AC27,0) -> 0 | AF27: =IF(AA27<>"COMPRAR","",IF(AB27="",IF(X27="","",IF(X27-V27<0.01,"EMPATE TÉCNICO","")),IF(AB27<I27,"ESTOQUE INSUFICIENTE",IF(X27="","",IF(X27-V27<0.01,"EMPATE TÉCNICO",""))))) | AG27: BATEL COMERCIO DE ALIMENTOS LTDA | AH27: BABY/KIDS
A28: 663421 | B28: 7896699025829 | C28: CHUPETA DREAMS CAP SIL O T1 M LOLLY | D28: LOLLY | E28: 1 | F28: C | G28: 1 | H28: 0.5 | I28: 1 | J28: 10.8 | K28: 10.8 | L28: 10.8 | M28: =IF(J28>0,J28,K28)*E28 -> 10.8 | O28: =IF(R28="","",ROUND(R28*(1-Premissas!$B$4),4)) -> 11.096 | R28: 11.68 | U28: 77 | V28: =IF(COUNT(N28:Q28)=0,"",MIN(N28:Q28)) -> 11.096 | W28: =IF(V28="","",INDEX($N$4:$Q$4,MATCH(V28,N28:Q28,0))) -> MEDCENTRO | X28: =IF(COUNT(N28:Q28)<2,"",SMALL(N28:Q28,2)) | Y28: =IF(OR(V28="",M28=0),"",V28/M28-1) -> 0.027407407 | Z28: =IF(OR(V28="",L28=""),"",V28/(L28*E28)-1) -> 0.027407407 | AA28: =IF(V28="","SEM OFERTA",IF(OR(Y28>Premissas!$B$11,Y28<Premissas!$B$12),"VERIFICAR - UNIDADE/EMBALAGEM",IF(Y28>Premissas!$B$6,"NÃO COMPRAR - REAJUSTE >5%","COMPRAR"))) -> COMPRAR | AB28: =IF(W28="DIMEC",S28,IF(W28="MEDCENTRO",U28,"")) -> 77 | AC28: =IF(AA28<>"COMPRAR",0,IF(AB28="",I28,MIN(I28,AB28))) -> 1 | AD28: =IF(AC28>0,AC28*V28,0) -> 11.096 | AE28: =IF(AC28>0,(M28-V28)*AC28,0) -> -0.296 | AF28: =IF(AA28<>"COMPRAR","",IF(AB28="",IF(X28="","",IF(X28-V28<0.01,"EMPATE TÉCNICO","")),IF(AB28<I28,"ESTOQUE INSUFICIENTE",IF(X28="","",IF(X28-V28<0.01,"EMPATE TÉCNICO",""))))) | AG28: BATEL COMERCIO DE ALIMENTOS LTDA | AH28: BABY/KIDS
A29: 660011 | B29: 7896699019538 | C29: CHUPETA DREAMS SIL O T1 LOLLY | D29: LOLLY | E29: 1 | F29: C | G29: 1 | H29: 0.9 | I29: 2 | J29: 9.46 | K29: 9.46 | L29: 9.46 | M29: =IF(J29>0,J29,K29)*E29 -> 9.46 | O29: =IF(R29="","",ROUND(R29*(1-Premissas!$B$4),4)) -> 10.051 | R29: 10.58 | U29: 64 | V29: =IF(COUNT(N29:Q29)=0,"",MIN(N29:Q29)) -> 10.051 | W29: =IF(V29="","",INDEX($N$4:$Q$4,MATCH(V29,N29:Q29,0))) -> MEDCENTRO | X29: =IF(COUNT(N29:Q29)<2,"",SMALL(N29:Q29,2)) | Y29: =IF(OR(V29="",M29=0),"",V29/M29-1) -> 0.062473573 | Z29: =IF(OR(V29="",L29=""),"",V29/(L29*E29)-1) -> 0.062473573 | AA29: =IF(V29="","SEM OFERTA",IF(OR(Y29>Premissas!$B$11,Y29<Premissas!$B$12),"VERIFICAR - UNIDADE/EMBALAGEM",IF(Y29>Premissas!$B$6,"NÃO COMPRAR - REAJUSTE >5%","COMPRAR"))) -> NÃO COMPRAR - REAJUSTE >5% | AB29: =IF(W29="DIMEC",S29,IF(W29="MEDCENTRO",U29,"")) -> 64 | AC29: =IF(AA29<>"COMPRAR",0,IF(AB29="",I29,MIN(I29,AB29))) -> 0 | AD29: =IF(AC29>0,AC29*V29,0) -> 0 | AE29: =IF(AC29>0,(M29-V29)*AC29,0) -> 0 | AF29: =IF(AA29<>"COMPRAR","",IF(AB29="",IF(X29="","",IF(X29-V29<0.01,"EMPATE TÉCNICO","")),IF(AB29<I29,"ESTOQUE INSUFICIENTE",IF(X29="","",IF(X29-V29<0.01,"EMPATE TÉCNICO",""))))) | AG29: BATEL COMERCIO DE ALIMENTOS LTDA | AH29: BABY/KIDS
A30: 663381 | B30: 7896699022002 | C30: CHUPETA ZOO BONA SIL O T1 ROSA CX/6 - LOLLY | D30: LOLLY | E30: 1 | F30: C | G30: 0 | H30: 0.8 | I30: 3 | J30: 6.35 | K30: 6.35 | L30: 6.35 | M30: =IF(J30>0,J30,K30)*E30 -> 6.35 | O30: =IF(R30="","",ROUND(R30*(1-Premissas!$B$4),4)) -> 7.6 | R30: 8 | U30: 93 | V30: =IF(COUNT(N30:Q30)=0,"",MIN(N30:Q30)) -> 7.6 | W30: =IF(V30="","",INDEX($N$4:$Q$4,MATCH(V30,N30:Q30,0))) -> MEDCENTRO | X30: =IF(COUNT(N30:Q30)<2,"",SMALL(N30:Q30,2)) | Y30: =IF(OR(V30="",M30=0),"",V30/M30-1) -> 0.19685039 | Z30: =IF(OR(V30="",L30=""),"",V30/(L30*E30)-1) -> 0.19685039 | AA30: =IF(V30="","SEM OFERTA",IF(OR(Y30>Premissas!$B$11,Y30<Premissas!$B$12),"VERIFICAR - UNIDADE/EMBALAGEM",IF(Y30>Premissas!$B$6,"NÃO COMPRAR - REAJUSTE >5%","COMPRAR"))) -> NÃO COMPRAR - REAJUSTE >5% | AB30: =IF(W30="DIMEC",S30,IF(W30="MEDCENTRO",U30,"")) -> 93 | AC30: =IF(AA30<>"COMPRAR",0,IF(AB30="",I30,MIN(I30,AB30))) -> 0 | AD30: =IF(AC30>0,AC30*V30,0) -> 0 | AE30: =IF(AC30>0,(M30-V30)*AC30,0) -> 0 | AF30: =IF(AA30<>"COMPRAR","",IF(AB30="",IF(X30="","",IF(X30-V30<0.01,"EMPATE TÉCNICO","")),IF(AB30<I30,"ESTOQUE INSUFICIENTE",IF(X30="","",IF(X30-V30<0.01,"EMPATE TÉCNICO",""))))) | AG30: BATEL COMERCIO DE ALIMENTOS LTDA | AH30: BABY/KIDS
A31: 539381 | B31: 7896699017718 | C31: CHUQUINHA LOLLY COM DESENHO SIL AZ | D31: LOLLY | E31: 1 | F31: B | G31: 1 | H31: 3.2 | I31: 8 | J31: 12.47 | K31: 12.47 | L31: 12.47 | M31: =IF(J31>0,J31,K31)*E31 -> 12.47 | O31: =IF(R31="","",ROUND(R31*(1-Premissas!$B$4),4)) -> 10.7825 | R31: 11.35 | U31: 258 | V31: =IF(COUNT(N31:Q31)=0,"",MIN(N31:Q31)) -> 10.7825 | W31: =IF(V31="","",INDEX($N$4:$Q$4,MATCH(V31,N31:Q31,0))) -> MEDCENTRO | X31: =IF(COUNT(N31:Q31)<2,"",SMALL(N31:Q31,2)) | Y31: =IF(OR(V31="",M31=0),"",V31/M31-1) -> -0.13532478 | Z31: =IF(OR(V31="",L31=""),"",V31/(L31*E31)-1) -> -0.13532478 | AA31: =IF(V31="","SEM OFERTA",IF(OR(Y31>Premissas!$B$11,Y31<Premissas!$B$12),"VERIFICAR - UNIDADE/EMBALAGEM",IF(Y31>Premissas!$B$6,"NÃO COMPRAR - REAJUSTE >5%","COMPRAR"))) -> COMPRAR | AB31: =IF(W31="DIMEC",S31,IF(W31="MEDCENTRO",U31,"")) -> 258 | AC31: =IF(AA31<>"COMPRAR",0,IF(AB31="",I31,MIN(I31,AB31))) -> 8 | AD31: =IF(AC31>0,AC31*V31,0) -> 86.26 | AE31: =IF(AC31>0,(M31-V31)*AC31,0) -> 13.5 | AF31: =IF(AA31<>"COMPRAR","",IF(AB31="",IF(X31="","",IF(X31-V31<0.01,"EMPATE TÉCNICO","")),IF(AB31<I31,"ESTOQUE INSUFICIENTE",IF(X31="","",IF(X31-V31<0.01,"EMPATE TÉCNICO",""))))) | AH31: BABY/KIDS
A32: 663521 | B32: 7896699033619 | C32: COLETOR LEITE MATERNO SILICONE CX/6 - LOLLY | D32: LOLLY | E32: 1 | F32: B | G32: 1 | H32: 0.5 | I32: 1 | J32: 46.11 | K32: 46.11 | L32: 46.11 | M32: =IF(J32>0,J32,K32)*E32 -> 46.11 | O32: =IF(R32="","",ROUND(R32*(1-Premissas!$B$4),4)) -> 54.511 | R32: 57.38 | U32: 27 | V32: =IF(COUNT(N32:Q32)=0,"",MIN(N32:Q32)) -> 54.511 | W32: =IF(V32="","",INDEX($N$4:$Q$4,MATCH(V32,N32:Q32,0))) -> MEDCENTRO | X32: =IF(COUNT(N32:Q32)<2,"",SMALL(N32:Q32,2)) | Y32: =IF(OR(V32="",M32=0),"",V32/M32-1) -> 0.18219475 | Z32: =IF(OR(V32="",L32=""),"",V32/(L32*E32)-1) -> 0.18219475 | AA32: =IF(V32="","SEM OFERTA",IF(OR(Y32>Premissas!$B$11,Y32<Premissas!$B$12),"VERIFICAR - UNIDADE/EMBALAGEM",IF(Y32>Premissas!$B$6,"NÃO COMPRAR - REAJUSTE >5%","COMPRAR"))) -> NÃO COMPRAR - REAJUSTE >5% | AB32: =IF(W32="DIMEC",S32,IF(W32="MEDCENTRO",U32,"")) -> 27 | AC32: =IF(AA32<>"COMPRAR",0,IF(AB32="",I32,MIN(I32,AB32))) -> 0 | AD32: =IF(AC32>0,AC32*V32,0) -> 0 | AE32: =IF(AC32>0,(M32-V32)*AC32,0) -> 0 | AF32: =IF(AA32<>"COMPRAR","",IF(AB32="",IF(X32="","",IF(X32-V32<0.01,"EMPATE TÉCNICO","")),IF(AB32<I32,"ESTOQUE INSUFICIENTE",IF(X32="","",IF(X32-V32<0.01,"EMPATE TÉCNICO",""))))) | AG32: BATEL COMERCIO DE ALIMENTOS LTDA | AH32: BABY/KIDS
A33: 619181 | B33: 7896699020169 | C33: COPO EDUCATIVO TIP 150ML AZUL 7100-00-M | D33: LOLLY | E33: 1 | F33: C | G33: 1 | H33: 0.9 | I33: 2 | J33: 10.6 | K33: 10.6 | L33: 10.6 | M33: =IF(J33>0,J33,K33)*E33 -> 10.6 | O33: =IF(R33="","",ROUND(R33*(1-Premissas!$B$4),4)) -> 12.1505 | R33: 12.79 | U33: 75 | V33: =IF(COUNT(N33:Q33)=0,"",MIN(N33:Q33)) -> 12.1505 | W33: =IF(V33="","",INDEX($N$4:$Q$4,MATCH(V33,N33:Q33,0))) -> MEDCENTRO | X33: =IF(COUNT(N33:Q33)<2,"",SMALL(N33:Q33,2)) | Y33: =IF(OR(V33="",M33=0),"",V33/M33-1) -> 0.14627358 | Z33: =IF(OR(V33="",L33=""),"",V33/(L33*E33)-1) -> 0.14627358 | AA33: =IF(V33="","SEM OFERTA",IF(OR(Y33>Premissas!$B$11,Y33<Premissas!$B$12),"VERIFICAR - UNIDADE/EMBALAGEM",IF(Y33>Premissas!$B$6,"NÃO COMPRAR - REAJUSTE >5%","COMPRAR"))) -> NÃO COMPRAR - REAJUSTE >5% | AB33: =IF(W33="DIMEC",S33,IF(W33="MEDCENTRO",U33,"")) -> 75 | AC33: =IF(AA33<>"COMPRAR",0,IF(AB33="",I33,MIN(I33,AB33))) -> 0 | AD33: =IF(AC33>0,AC33*V33,0) -> 0 | AE33: =IF(AC33>0,(M33-V33)*AC33,0) -> 0 | AF33: =IF(AA33<>"COMPRAR","",IF(AB33="",IF(X33="","",IF(X33-V33<0.01,"EMPATE TÉCNICO","")),IF(AB33<I33,"ESTOQUE INSUFICIENTE",IF(X33="","",IF(X33-V33<0.01,"EMPATE TÉCNICO",""))))) | AG33: BATEL COMERCIO DE ALIMENTOS LTDA | AH33: BABY/KIDS
A34: 619191 | B34: 7896699020183 | C34: COPO EDUCATIVO TIP 150ML ROSA 7100-00-F | D34: LOLLY | E34: 1 | F34: B | G34: 2 | H34: 2.1 | I34: 4 | J34: 10.6 | K34: 10.6 | L34: 10.6 | M34: =IF(J34>0,J34,K34)*E34 -> 10.6 | O34: =IF(R34="","",ROUND(R34*(1-Premissas!$B$4),4)) -> 12.1505 | R34: 12.79 | U34: 52 | V34: =IF(COUNT(N34:Q34)=0,"",MIN(N34:Q34)) -> 12.1505 | W34: =IF(V34="","",INDEX($N$4:$Q$4,MATCH(V34,N34:Q34,0))) -> MEDCENTRO | X34: =IF(COUNT(N34:Q34)<2,"",SMALL(N34:Q34,2)) | Y34: =IF(OR(V34="",M34=0),"",V34/M34-1) -> 0.14627358 | Z34: =IF(OR(V34="",L34=""),"",V34/(L34*E34)-1) -> 0.14627358 | AA34: =IF(V34="","SEM OFERTA",IF(OR(Y34>Premissas!$B$11,Y34<Premissas!$B$12),"VERIFICAR - UNIDADE/EMBALAGEM",IF(Y34>Premissas!$B$6,"NÃO COMPRAR - REAJUSTE >5%","COMPRAR"))) -> NÃO COMPRAR - REAJUSTE >5% | AB34: =IF(W34="DIMEC",S34,IF(W34="MEDCENTRO",U34,"")) -> 52 | AC34: =IF(AA34<>"COMPRAR",0,IF(AB34="",I34,MIN(I34,AB34))) -> 0 | AD34: =IF(AC34>0,AC34*V34,0) -> 0 | AE34: =IF(AC34>0,(M34-V34)*AC34,0) -> 0 | AF34: =IF(AA34<>"COMPRAR","",IF(AB34="",IF(X34="","",IF(X34-V34<0.01,"EMPATE TÉCNICO","")),IF(AB34<I34,"ESTOQUE INSUFICIENTE",IF(X34="","",IF(X34-V34<0.01,"EMPATE TÉCNICO",""))))) | AG34: BATEL COMERCIO DE ALIMENTOS LTDA | AH34: BABY/KIDS
A35: 632461 | B35: 7896647078457 | C35: CORTADOR DE UNHAS METAL - AZUL/ 7845 | D35: EMDISA | E35: 1 | F35: C | G35: 0 | H35: 0 | I35: 1 | J35: 4.32 | K35: 4.32 | L35: 4.32 | M35: =IF(J35>0,J35,K35)*E35 -> 4.32 | O35: =IF(R35="","",ROUND(R35*(1-Premissas!$B$4),4)) -> 5.5765 | R35: 5.87 | U35: 14 | V35: =IF(COUNT(N35:Q35)=0,"",MIN(N35:Q35)) -> 5.5765 | W35: =IF(V35="","",INDEX($N$4:$Q$4,MATCH(V35,N35:Q35,0))) -> MEDCENTRO | X35: =IF(COUNT(N35:Q35)<2,"",SMALL(N35:Q35,2)) | Y35: =IF(OR(V35="",M35=0),"",V35/M35-1) -> 0.29085648 | Z35: =IF(OR(V35="",L35=""),"",V35/(L35*E35)-1) -> 0.29085648 | AA35: =IF(V35="","SEM OFERTA",IF(OR(Y35>Premissas!$B$11,Y35<Premissas!$B$12),"VERIFICAR - UNIDADE/EMBALAGEM",IF(Y35>Premissas!$B$6,"NÃO COMPRAR - REAJUSTE >5%","COMPRAR"))) -> NÃO COMPRAR - REAJUSTE >5% | AB35: =IF(W35="DIMEC",S35,IF(W35="MEDCENTRO",U35,"")) -> 14 | AC35: =IF(AA35<>"COMPRAR",0,IF(AB35="",I35,MIN(I35,AB35))) -> 0 | AD35: =IF(AC35>0,AC35*V35,0) -> 0 | AE35: =IF(AC35>0,(M35-V35)*AC35,0) -> 0 | AF35: =IF(AA35<>"COMPRAR","",IF(AB35="",IF(X35="","",IF(X35-V35<0.01,"EMPATE TÉCNICO","")),IF(AB35<I35,"ESTOQUE INSUFICIENTE",IF(X35="","",IF(X35-V35<0.01,"EMPATE TÉCNICO",""))))) | AG35: EMDISA DISTRIBUIDORA LTDA | AH35: BABY/KIDS
A36: 632451 | B36: 7896647078440 | C36: CORTADOR DE UNHAS METAL - ROSA/ 7844 | D36: EMDISA | E36: 1 | F36: C | G36: 0 | H36: 0 | I36: 1 | J36: 4.32 | K36: 4.32 | L36: 4.32 | M36: =IF(J36>0,J36,K36)*E36 -> 4.32 | O36: =IF(R36="","",ROUND(R36*(1-Premissas!$B$4),4)) -> 5.548 | R36: 5.84 | U36: 20 | V36: =IF(COUNT(N36:Q36)=0,"",MIN(N36:Q36)) -> 5.548 | W36: =IF(V36="","",INDEX($N$4:$Q$4,MATCH(V36,N36:Q36,0))) -> MEDCENTRO | X36: =IF(COUNT(N36:Q36)<2,"",SMALL(N36:Q36,2)) | Y36: =IF(OR(V36="",M36=0),"",V36/M36-1) -> 0.28425926 | Z36: =IF(OR(V36="",L36=""),"",V36/(L36*E36)-1) -> 0.28425926 | AA36: =IF(V36="","SEM OFERTA",IF(OR(Y36>Premissas!$B$11,Y36<Premissas!$B$12),"VERIFICAR - UNIDADE/EMBALAGEM",IF(Y36>Premissas!$B$6,"NÃO COMPRAR - REAJUSTE >5%","COMPRAR"))) -> NÃO COMPRAR - REAJUSTE >5% | AB36: =IF(W36="DIMEC",S36,IF(W36="MEDCENTRO",U36,"")) -> 20 | AC36: =IF(AA36<>"COMPRAR",0,IF(AB36="",I36,MIN(I36,AB36))) -> 0 | AD36: =IF(AC36>0,AC36*V36,0) -> 0 | AE36: =IF(AC36>0,(M36-V36)*AC36,0) -> 0 | AF36: =IF(AA36<>"COMPRAR","",IF(AB36="",IF(X36="","",IF(X36-V36<0.01,"EMPATE TÉCNICO","")),IF(AB36<I36,"ESTOQUE INSUFICIENTE",IF(X36="","",IF(X36-V36<0.01,"EMPATE TÉCNICO",""))))) | AG36: EMDISA DISTRIBUIDORA LTDA | AH36: BABY/KIDS
A37: 610711 | B37: 7896699024112 | C37: ESCOVA MASSAGEADORA NEUTRA | D37: LOLLY | E37: 1 | F37: B | G37: 2 | H37: 1.1 | I37: 1 | J37: 8.74 | K37: 8.74 | L37: 8.74 | M37: =IF(J37>0,J37,K37)*E37 -> 8.74 | O37: =IF(R37="","",ROUND(R37*(1-Premissas!$B$4),4)) -> 9.2815 | R37: 9.77 | U37: 249 | V37: =IF(COUNT(N37:Q37)=0,"",MIN(N37:Q37)) -> 9.2815 | W37: =IF(V37="","",INDEX($N$4:$Q$4,MATCH(V37,N37:Q37,0))) -> MEDCENTRO | X37: =IF(COUNT(N37:Q37)<2,"",SMALL(N37:Q37,2)) | Y37: =IF(OR(V37="",M37=0),"",V37/M37-1) -> 0.061956522 | Z37: =IF(OR(V37="",L37=""),"",V37/(L37*E37)-1) -> 0.061956522 | AA37: =IF(V37="","SEM OFERTA",IF(OR(Y37>Premissas!$B$11,Y37<Premissas!$B$12),"VERIFICAR - UNIDADE/EMBALAGEM",IF(Y37>Premissas!$B$6,"NÃO COMPRAR - REAJUSTE >5%","COMPRAR"))) -> NÃO COMPRAR - REAJUSTE >5% | AB37: =IF(W37="DIMEC",S37,IF(W37="MEDCENTRO",U37,"")) -> 249 | AC37: =IF(AA37<>"COMPRAR",0,IF(AB37="",I37,MIN(I37,AB37))) -> 0 | AD37: =IF(AC37>0,AC37*V37,0) -> 0 | AE37: =IF(AC37>0,(M37-V37)*AC37,0) -> 0 | AF37: =IF(AA37<>"COMPRAR","",IF(AB37="",IF(X37="","",IF(X37-V37<0.01,"EMPATE TÉCNICO","")),IF(AB37<I37,"ESTOQUE INSUFICIENTE",IF(X37="","",IF(X37-V37<0.01,"EMPATE TÉCNICO",""))))) | AG37: BATEL COMERCIO DE ALIMENTOS LTDA | AH37: BABY/KIDS
A38: 671181 | B38: 7898639692856 | C38: INALADOR /NEB PORTATIL RED VIBR NEBMESH2 | D38: GTECH | E38: 1 | F38: A | G38: 0 | H38: 0.1 | I38: 1 | J38: 162.8 | K38: 162.8 | L38: 162.8 | M38: =IF(J38>0,J38,K38)*E38 -> 162.8 | N38: 135.39 | O38: =IF(R38="","",ROUND(R38*(1-Premissas!$B$4),4)) -> 137.579 | R38: 144.82 | S38: 24 | T38: 20 | U38: 186 | V38: =IF(COUNT(N38:Q38)=0,"",MIN(N38:Q38)) -> 135.39 | W38: =IF(V38="","",INDEX($N$4:$Q$4,MATCH(V38,N38:Q38,0))) -> DIMEC | X38: =IF(COUNT(N38:Q38)<2,"",SMALL(N38:Q38,2)) -> 137.579 | Y38: =IF(OR(V38="",M38=0),"",V38/M38-1) -> -0.16836609 | Z38: =IF(OR(V38="",L38=""),"",V38/(L38*E38)-1) -> -0.16836609 | AA38: =IF(V38="","SEM OFERTA",IF(OR(Y38>Premissas!$B$11,Y38<Premissas!$B$12),"VERIFICAR - UNIDADE/EMBALAGEM",IF(Y38>Premissas!$B$6,"NÃO COMPRAR - REAJUSTE >5%","COMPRAR"))) -> COMPRAR | AB38: =IF(W38="DIMEC",S38,IF(W38="MEDCENTRO",U38,"")) -> 24 | AC38: =IF(AA38<>"COMPRAR",0,IF(AB38="",I38,MIN(I38,AB38))) -> 1 | AD38: =IF(AC38>0,AC38*V38,0) -> 135.39 | AE38: =IF(AC38>0,(M38-V38)*AC38,0) -> 27.41 | AF38: =IF(AA38<>"COMPRAR","",IF(AB38="",IF(X38="","",IF(X38-V38<0.01,"EMPATE TÉCNICO","")),IF(AB38<I38,"ESTOQUE INSUFICIENTE",IF(X38="","",IF(X38-V38<0.01,"EMPATE TÉCNICO",""))))) | AG38: CENTROFARMA DISTRIBUIDORA FARMACEUTICA LTDA | AH38: BABY/KIDS
A39: 610691 | B39: 7896699022804 | C39: KIT ALIMENTACAO TIP 4PCS ROSA 7131-01 | D39: BUBA | E39: 1 | F39: C | G39: 0 | H39: 0 | I39: 1 | J39: 28.2 | K39: 28.2 | L39: 28.2 | M39: =IF(J39>0,J39,K39)*E39 -> 28.2 | O39: =IF(R39="","",ROUND(R39*(1-Premissas!$B$4),4)) -> 34.96 | R39: 36.8 | U39: 15 | V39: =IF(COUNT(N39:Q39)=0,"",MIN(N39:Q39)) -> 34.96 | W39: =IF(V39="","",INDEX($N$4:$Q$4,MATCH(V39,N39:Q39,0))) -> MEDCENTRO | X39: =IF(COUNT(N39:Q39)<2,"",SMALL(N39:Q39,2)) | Y39: =IF(OR(V39="",M39=0),"",V39/M39-1) -> 0.23971631 | Z39: =IF(OR(V39="",L39=""),"",V39/(L39*E39)-1) -> 0.23971631 | AA39: =IF(V39="","SEM OFERTA",IF(OR(Y39>Premissas!$B$11,Y39<Premissas!$B$12),"VERIFICAR - UNIDADE/EMBALAGEM",IF(Y39>Premissas!$B$6,"NÃO COMPRAR - REAJUSTE >5%","COMPRAR"))) -> NÃO COMPRAR - REAJUSTE >5% | AB39: =IF(W39="DIMEC",S39,IF(W39="MEDCENTRO",U39,"")) -> 15 | AC39: =IF(AA39<>"COMPRAR",0,IF(AB39="",I39,MIN(I39,AB39))) -> 0 | AD39: =IF(AC39>0,AC39*V39,0) -> 0 | AE39: =IF(AC39>0,(M39-V39)*AC39,0) -> 0 | AF39: =IF(AA39<>"COMPRAR","",IF(AB39="",IF(X39="","",IF(X39-V39<0.01,"EMPATE TÉCNICO","")),IF(AB39<I39,"ESTOQUE INSUFICIENTE",IF(X39="","",IF(X39-V39<0.01,"EMPATE TÉCNICO",""))))) | AG39: CENTROFARMA DISTRIBUIDORA FARMACEUTICA LTDA | AH39: BABY/KIDS
A40: 552061 | B40: 7898633380575 | C40: LENÇO UMEDECIDO SUAVE MEU BEBÊ MINHA VIDA PACOTE 40 UNIDADES | D40: NUTRIEX | E40: 1 | F40: C | G40: 0 | H40: 6.4 | I40: 17 | J40: 3.38 | K40: 3.38 | L40: 2.96 | M40: =IF(J40>0,J40,K40)*E40 -> 3.38 | N40: 2.98 | O40: =IF(R40="","",ROUND(R40*(1-Premissas!$B$4),4)) | S40: 392 | T40: 24 | V40: =IF(COUNT(N40:Q40)=0,"",MIN(N40:Q40)) -> 2.98 | W40: =IF(V40="","",INDEX($N$4:$Q$4,MATCH(V40,N40:Q40,0))) -> DIMEC | X40: =IF(COUNT(N40:Q40)<2,"",SMALL(N40:Q40,2)) | Y40: =IF(OR(V40="",M40=0),"",V40/M40-1) -> -0.1183432 | Z40: =IF(OR(V40="",L40=""),"",V40/(L40*E40)-1) -> 0.0067567568 | AA40: =IF(V40="","SEM OFERTA",IF(OR(Y40>Premissas!$B$11,Y40<Premissas!$B$12),"VERIFICAR - UNIDADE/EMBALAGEM",IF(Y40>Premissas!$B$6,"NÃO COMPRAR - REAJUSTE >5%","COMPRAR"))) -> COMPRAR | AB40: =IF(W40="DIMEC",S40,IF(W40="MEDCENTRO",U40,"")) -> 392 | AC40: =IF(AA40<>"COMPRAR",0,IF(AB40="",I40,MIN(I40,AB40))) -> 17 | AD40: =IF(AC40>0,AC40*V40,0) -> 50.66 | AE40: =IF(AC40>0,(M40-V40)*AC40,0) -> 6.8 | AF40: =IF(AA40<>"COMPRAR","",IF(AB40="",IF(X40="","",IF(X40-V40<0.01,"EMPATE TÉCNICO","")),IF(AB40<I40,"ESTOQUE INSUFICIENTE",IF(X40="","",IF(X40-V40<0.01,"EMPATE TÉCNICO",""))))) | AG40: MARTINS COM SERV DISTR SA | AH40: BABY/KIDS
A41: 629751 | B41: 7896699029179 | C41: LOLLY BIC MAM SIL B 0 T2 FL M BL 0068-01 | D41: LOLLY | E41: 1 | F41: C | G41: 0 | H41: 0.5 | I41: 2 | J41: 6.21 | K41: 6.21 | L41: 6.21 | M41: =IF(J41>0,J41,K41)*E41 -> 6.21 | O41: =IF(R41="","",ROUND(R41*(1-Premissas!$B$4),4)) -> 10.051 | R41: 10.58 | U41: 587 | V41: =IF(COUNT(N41:Q41)=0,"",MIN(N41:Q41)) -> 10.051 | W41: =IF(V41="","",INDEX($N$4:$Q$4,MATCH(V41,N41:Q41,0))) -> MEDCENTRO | X41: =IF(COUNT(N41:Q41)<2,"",SMALL(N41:Q41,2)) | Y41: =IF(OR(V41="",M41=0),"",V41/M41-1) -> 0.61851852 | Z41: =IF(OR(V41="",L41=""),"",V41/(L41*E41)-1) -> 0.61851852 | AA41: =IF(V41="","SEM OFERTA",IF(OR(Y41>Premissas!$B$11,Y41<Premissas!$B$12),"VERIFICAR - UNIDADE/EMBALAGEM",IF(Y41>Premissas!$B$6,"NÃO COMPRAR - REAJUSTE >5%","COMPRAR"))) -> NÃO COMPRAR - REAJUSTE >5% | AB41: =IF(W41="DIMEC",S41,IF(W41="MEDCENTRO",U41,"")) -> 587 | AC41: =IF(AA41<>"COMPRAR",0,IF(AB41="",I41,MIN(I41,AB41))) -> 0 | AD41: =IF(AC41>0,AC41*V41,0) -> 0 | AE41: =IF(AC41>0,(M41-V41)*AC41,0) -> 0 | AF41: =IF(AA41<>"COMPRAR","",IF(AB41="",IF(X41="","",IF(X41-V41<0.01,"EMPATE TÉCNICO","")),IF(AB41<I41,"ESTOQUE INSUFICIENTE",IF(X41="","",IF(X41-V41<0.01,"EMPATE TÉCNICO",""))))) | AG41: BATEL COMERCIO DE ALIMENTOS LTDA | AH41: BABY/KIDS
A42: 630951 | B42: 896699031547 | C42: LOLLY CHUP 100% SIL RT 1 F 6111-01-F | D42: LOLLY | E42: 1 | F42: B | G42: 4 | H42: 3.2 | I42: 5 | J42: 15.29 | K42: 15.29 | L42: 15.29 | M42: =IF(J42>0,J42,K42)*E42 -> 15.29 | O42: =IF(R42="","",ROUND(R42*(1-Premissas!$B$4),4)) -> 14.2785 | R42: 15.03 | U42: 422 | V42: =IF(COUNT(N42:Q42)=0,"",MIN(N42:Q42)) -> 14.2785 | W42: =IF(V42="","",INDEX($N$4:$Q$4,MATCH(V42,N42:Q42,0))) -> MEDCENTRO | X42: =IF(COUNT(N42:Q42)<2,"",SMALL(N42:Q42,2)) | Y42: =IF(OR(V42="",M42=0),"",V42/M42-1) -> -0.066154349 | Z42: =IF(OR(V42="",L42=""),"",V42/(L42*E42)-1) -> -0.066154349 | AA42: =IF(V42="","SEM OFERTA",IF(OR(Y42>Premissas!$B$11,Y42<Premissas!$B$12),"VERIFICAR - UNIDADE/EMBALAGEM",IF(Y42>Premissas!$B$6,"NÃO COMPRAR - REAJUSTE >5%","COMPRAR"))) -> COMPRAR | AB42: =IF(W42="DIMEC",S42,IF(W42="MEDCENTRO",U42,"")) -> 422 | AC42: =IF(AA42<>"COMPRAR",0,IF(AB42="",I42,MIN(I42,AB42))) -> 5 | AD42: =IF(AC42>0,AC42*V42,0) -> 71.3925 | AE42: =IF(AC42>0,(M42-V42)*AC42,0) -> 5.0575 | AF42: =IF(AA42<>"COMPRAR","",IF(AB42="",IF(X42="","",IF(X42-V42<0.01,"EMPATE TÉCNICO","")),IF(AB42<I42,"ESTOQUE INSUFICIENTE",IF(X42="","",IF(X42-V42<0.01,"EMPATE TÉCNICO",""))))) | AG42: BATEL COMERCIO DE ALIMENTOS LTDA | AH42: BABY/KIDS
A43: 629951 | B43: 7896699029575 | C43: LOLLY CHUP CL SIL O T2 BL 5115-01-ROSA | D43: LOLLY | E43: 1 | F43: B | G43: 0 | H43: 0.6 | I43: 2 | J43: 6.95 | K43: 6.95 | L43: 6.95 | M43: =IF(J43>0,J43,K43)*E43 -> 6.95 | O43: =IF(R43="","",ROUND(R43*(1-Premissas!$B$4),4)) -> 6.992 | R43: 7.36 | U43: 189 | V43: =IF(COUNT(N43:Q43)=0,"",MIN(N43:Q43)) -> 6.992 | W43: =IF(V43="","",INDEX($N$4:$Q$4,MATCH(V43,N43:Q43,0))) -> MEDCENTRO | X43: =IF(COUNT(N43:Q43)<2,"",SMALL(N43:Q43,2)) | Y43: =IF(OR(V43="",M43=0),"",V43/M43-1) -> 0.0060431655 | Z43: =IF(OR(V43="",L43=""),"",V43/(L43*E43)-1) -> 0.0060431655 | AA43: =IF(V43="","SEM OFERTA",IF(OR(Y43>Premissas!$B$11,Y43<Premissas!$B$12),"VERIFICAR - UNIDADE/EMBALAGEM",IF(Y43>Premissas!$B$6,"NÃO COMPRAR - REAJUSTE >5%","COMPRAR"))) -> COMPRAR | AB43: =IF(W43="DIMEC",S43,IF(W43="MEDCENTRO",U43,"")) -> 189 | AC43: =IF(AA43<>"COMPRAR",0,IF(AB43="",I43,MIN(I43,AB43))) -> 2 | AD43: =IF(AC43>0,AC43*V43,0) -> 13.984 | AE43: =IF(AC43>0,(M43-V43)*AC43,0) -> -0.084 | AF43: =IF(AA43<>"COMPRAR","",IF(AB43="",IF(X43="","",IF(X43-V43<0.01,"EMPATE TÉCNICO","")),IF(AB43<I43,"ESTOQUE INSUFICIENTE",IF(X43="","",IF(X43-V43<0.01,"EMPATE TÉCNICO",""))))) | AG43: M C F RODRIGUES DE ANDRADE DIST IMPORT EXP ALIMENTO EIRELI | AH43: BABY/KIDS
A44: 629851 | B44: 7896699015691 | C44: LOLLY KIT CAB TIP C/2UN BL 7050-01-AZUL | D44: LOLLY | E44: 1 | F44: B | G44: 3 | H44: 3.2 | I44: 6 | J44: 13.6 | K44: 13.6 | L44: 13.6 | M44: =IF(J44>0,J44,K44)*E44 -> 13.6 | O44: =IF(R44="","",ROUND(R44*(1-Premissas!$B$4),4)) -> 14.554 | R44: 15.32 | U44: 146 | V44: =IF(COUNT(N44:Q44)=0,"",MIN(N44:Q44)) -> 14.554 | W44: =IF(V44="","",INDEX($N$4:$Q$4,MATCH(V44,N44:Q44,0))) -> MEDCENTRO | X44: =IF(COUNT(N44:Q44)<2,"",SMALL(N44:Q44,2)) | Y44: =IF(OR(V44="",M44=0),"",V44/M44-1) -> 0.070147059 | Z44: =IF(OR(V44="",L44=""),"",V44/(L44*E44)-1) -> 0.070147059 | AA44: =IF(V44="","SEM OFERTA",IF(OR(Y44>Premissas!$B$11,Y44<Premissas!$B$12),"VERIFICAR - UNIDADE/EMBALAGEM",IF(Y44>Premissas!$B$6,"NÃO COMPRAR - REAJUSTE >5%","COMPRAR"))) -> NÃO COMPRAR - REAJUSTE >5% | AB44: =IF(W44="DIMEC",S44,IF(W44="MEDCENTRO",U44,"")) -> 146 | AC44: =IF(AA44<>"COMPRAR",0,IF(AB44="",I44,MIN(I44,AB44))) -> 0 | AD44: =IF(AC44>0,AC44*V44,0) -> 0 | AE44: =IF(AC44>0,(M44-V44)*AC44,0) -> 0 | AF44: =IF(AA44<>"COMPRAR","",IF(AB44="",IF(X44="","",IF(X44-V44<0.01,"EMPATE TÉCNICO","")),IF(AB44<I44,"ESTOQUE INSUFICIENTE",IF(X44="","",IF(X44-V44<0.01,"EMPATE TÉCNICO",""))))) | AG44: BATEL COMERCIO DE ALIMENTOS LTDA | AH44: BABY/KIDS
A45: 629811 | B45: 7896699025423 | C45: LOLLY MAM CLEAN 250ML R 2660-01-AZUL | D45: LOLLY | E45: 1 | F45: C | G45: 0 | H45: 1.1 | I45: 3 | J45: 9.83 | K45: 9.83 | L45: 9.83 | M45: =IF(J45>0,J45,K45)*E45 -> 9.83 | O45: =IF(R45="","",ROUND(R45*(1-Premissas!$B$4),4)) -> 9.88 | R45: 10.4 | U45: 169 | V45: =IF(COUNT(N45:Q45)=0,"",MIN(N45:Q45)) -> 9.88 | W45: =IF(V45="","",INDEX($N$4:$Q$4,MATCH(V45,N45:Q45,0))) -> MEDCENTRO | X45: =IF(COUNT(N45:Q45)<2,"",SMALL(N45:Q45,2)) | Y45: =IF(OR(V45="",M45=0),"",V45/M45-1) -> 0.00508647 | Z45: =IF(OR(V45="",L45=""),"",V45/(L45*E45)-1) -> 0.00508647 | AA45: =IF(V45="","SEM OFERTA",IF(OR(Y45>Premissas!$B$11,Y45<Premissas!$B$12),"VERIFICAR - UNIDADE/EMBALAGEM",IF(Y45>Premissas!$B$6,"NÃO COMPRAR - REAJUSTE >5%","COMPRAR"))) -> COMPRAR | AB45: =IF(W45="DIMEC",S45,IF(W45="MEDCENTRO",U45,"")) -> 169 | AC45: =IF(AA45<>"COMPRAR",0,IF(AB45="",I45,MIN(I45,AB45))) -> 3 | AD45: =IF(AC45>0,AC45*V45,0) -> 29.64 | AE45: =IF(AC45>0,(M45-V45)*AC45,0) -> -0.15 | AF45: =IF(AA45<>"COMPRAR","",IF(AB45="",IF(X45="","",IF(X45-V45<0.01,"EMPATE TÉCNICO","")),IF(AB45<I45,"ESTOQUE INSUFICIENTE",IF(X45="","",IF(X45-V45<0.01,"EMPATE TÉCNICO",""))))) | AG45: M C F RODRIGUES DE ANDRADE DIST IMPORT EXP ALIMENTO EIRELI | AH45: BABY/KIDS
A46: 629821 | B46: 7896699025447 | C46: LOLLY MAM CLEAN 250ML SIL R 2660-01ROSA | D46: LOLLY | E46: 1 | F46: B | G46: 1 | H46: 2.1 | I46: 5 | J46: 9.83 | K46: 9.83 | L46: 9.83 | M46: =IF(J46>0,J46,K46)*E46 -> 9.83 | O46: =IF(R46="","",ROUND(R46*(1-Premissas!$B$4),4)) -> 9.88 | R46: 10.4 | U46: 214 | V46: =IF(COUNT(N46:Q46)=0,"",MIN(N46:Q46)) -> 9.88 | W46: =IF(V46="","",INDEX($N$4:$Q$4,MATCH(V46,N46:Q46,0))) -> MEDCENTRO | X46: =IF(COUNT(N46:Q46)<2,"",SMALL(N46:Q46,2)) | Y46: =IF(OR(V46="",M46=0),"",V46/M46-1) -> 0.00508647 | Z46: =IF(OR(V46="",L46=""),"",V46/(L46*E46)-1) -> 0.00508647 | AA46: =IF(V46="","SEM OFERTA",IF(OR(Y46>Premissas!$B$11,Y46<Premissas!$B$12),"VERIFICAR - UNIDADE/EMBALAGEM",IF(Y46>Premissas!$B$6,"NÃO COMPRAR - REAJUSTE >5%","COMPRAR"))) -> COMPRAR | AB46: =IF(W46="DIMEC",S46,IF(W46="MEDCENTRO",U46,"")) -> 214 | AC46: =IF(AA46<>"COMPRAR",0,IF(AB46="",I46,MIN(I46,AB46))) -> 5 | AD46: =IF(AC46>0,AC46*V46,0) -> 49.4 | AE46: =IF(AC46>0,(M46-V46)*AC46,0) -> -0.25 | AF46: =IF(AA46<>"COMPRAR","",IF(AB46="",IF(X46="","",IF(X46-V46<0.01,"EMPATE TÉCNICO","")),IF(AB46<I46,"ESTOQUE INSUFICIENTE",IF(X46="","",IF(X46-V46<0.01,"EMPATE TÉCNICO",""))))) | AG46: JLCS COMERCIO E DISTRIBUICAO DE ALIMENTO LTDA | AH46: BABY/KIDS
A47: 629841 | B47: 7896699023047 | C47: LOLLY MAM Z C/AL 250ML S R 2560-01-AZUL | D47: LOLLY | E47: 1 | F47: C | G47: 1 | H47: 0.5 | I47: 1 | J47: 19.21 | K47: 19.21 | L47: 19.21 | M47: =IF(J47>0,J47,K47)*E47 -> 19.21 | O47: =IF(R47="","",ROUND(R47*(1-Premissas!$B$4),4)) -> 22.04 | R47: 23.2 | U47: 45 | V47: =IF(COUNT(N47:Q47)=0,"",MIN(N47:Q47)) -> 22.04 | W47: =IF(V47="","",INDEX($N$4:$Q$4,MATCH(V47,N47:Q47,0))) -> MEDCENTRO | X47: =IF(COUNT(N47:Q47)<2,"",SMALL(N47:Q47,2)) | Y47: =IF(OR(V47="",M47=0),"",V47/M47-1) -> 0.1473191 | Z47: =IF(OR(V47="",L47=""),"",V47/(L47*E47)-1) -> 0.1473191 | AA47: =IF(V47="","SEM OFERTA",IF(OR(Y47>Premissas!$B$11,Y47<Premissas!$B$12),"VERIFICAR - UNIDADE/EMBALAGEM",IF(Y47>Premissas!$B$6,"NÃO COMPRAR - REAJUSTE >5%","COMPRAR"))) -> NÃO COMPRAR - REAJUSTE >5% | AB47: =IF(W47="DIMEC",S47,IF(W47="MEDCENTRO",U47,"")) -> 45 | AC47: =IF(AA47<>"COMPRAR",0,IF(AB47="",I47,MIN(I47,AB47))) -> 0 | AD47: =IF(AC47>0,AC47*V47,0) -> 0 | AE47: =IF(AC47>0,(M47-V47)*AC47,0) -> 0 | AF47: =IF(AA47<>"COMPRAR","",IF(AB47="",IF(X47="","",IF(X47-V47<0.01,"EMPATE TÉCNICO","")),IF(AB47<I47,"ESTOQUE INSUFICIENTE",IF(X47="","",IF(X47-V47<0.01,"EMPATE TÉCNICO",""))))) | AG47: M C F RODRIGUES DE ANDRADE DIST IMPORT EXP ALIMENTO EIRELI | AH47: BABY/KIDS
A48: 629831 | B48: 7896699023061 | C48: LOLLY MAM Z C/AL 250ML S R 2560-01-ROSA | D48: LOLLY | E48: 1 | F48: B | G48: 4 | H48: 2.1 | I48: 2 | J48: 19.21 | K48: 19.21 | L48: 19.21 | M48: =IF(J48>0,J48,K48)*E48 -> 19.21 | O48: =IF(R48="","",ROUND(R48*(1-Premissas!$B$4),4)) -> 22.04 | R48: 23.2 | U48: 14 | V48: =IF(COUNT(N48:Q48)=0,"",MIN(N48:Q48)) -> 22.04 | W48: =IF(V48="","",INDEX($N$4:$Q$4,MATCH(V48,N48:Q48,0))) -> MEDCENTRO | X48: =IF(COUNT(N48:Q48)<2,"",SMALL(N48:Q48,2)) | Y48: =IF(OR(V48="",M48=0),"",V48/M48-1) -> 0.1473191 | Z48: =IF(OR(V48="",L48=""),"",V48/(L48*E48)-1) -> 0.1473191 | AA48: =IF(V48="","SEM OFERTA",IF(OR(Y48>Premissas!$B$11,Y48<Premissas!$B$12),"VERIFICAR - UNIDADE/EMBALAGEM",IF(Y48>Premissas!$B$6,"NÃO COMPRAR - REAJUSTE >5%","COMPRAR"))) -> NÃO COMPRAR - REAJUSTE >5% | AB48: =IF(W48="DIMEC",S48,IF(W48="MEDCENTRO",U48,"")) -> 14 | AC48: =IF(AA48<>"COMPRAR",0,IF(AB48="",I48,MIN(I48,AB48))) -> 0 | AD48: =IF(AC48>0,AC48*V48,0) -> 0 | AE48: =IF(AC48>0,(M48-V48)*AC48,0) -> 0 | AF48: =IF(AA48<>"COMPRAR","",IF(AB48="",IF(X48="","",IF(X48-V48<0.01,"EMPATE TÉCNICO","")),IF(AB48<I48,"ESTOQUE INSUFICIENTE",IF(X48="","",IF(X48-V48<0.01,"EMPATE TÉCNICO",""))))) | AG48: BATEL COMERCIO DE ALIMENTOS LTDA | AH48: BABY/KIDS
A49: 554 | B49: 7896699013147 | C49: LOLLY NENNY 3+ AZUL | D49: LOLLY | E49: 1 | F49: C | G49: 0 | H49: 0 | I49: 1 | J49: 0 | K49: 15 | M49: =IF(J49>0,J49,K49)*E49 -> 15 | O49: =IF(R49="","",ROUND(R49*(1-Premissas!$B$4),4)) -> 19.456 | R49: 20.48 | U49: 64 | V49: =IF(COUNT(N49:Q49)=0,"",MIN(N49:Q49)) -> 19.456 | W49: =IF(V49="","",INDEX($N$4:$Q$4,MATCH(V49,N49:Q49,0))) -> MEDCENTRO | X49: =IF(COUNT(N49:Q49)<2,"",SMALL(N49:Q49,2)) | Y49: =IF(OR(V49="",M49=0),"",V49/M49-1) -> 0.29706667 | Z49: =IF(OR(V49="",L49=""),"",V49/(L49*E49)-1) | AA49: =IF(V49="","SEM OFERTA",IF(OR(Y49>Premissas!$B$11,Y49<Premissas!$B$12),"VERIFICAR - UNIDADE/EMBALAGEM",IF(Y49>Premissas!$B$6,"NÃO COMPRAR - REAJUSTE >5%","COMPRAR"))) -> NÃO COMPRAR - REAJUSTE >5% | AB49: =IF(W49="DIMEC",S49,IF(W49="MEDCENTRO",U49,"")) -> 64 | AC49: =IF(AA49<>"COMPRAR",0,IF(AB49="",I49,MIN(I49,AB49))) -> 0 | AD49: =IF(AC49>0,AC49*V49,0) -> 0 | AE49: =IF(AC49>0,(M49-V49)*AC49,0) -> 0 | AF49: =IF(AA49<>"COMPRAR","",IF(AB49="",IF(X49="","",IF(X49-V49<0.01,"EMPATE TÉCNICO","")),IF(AB49<I49,"ESTOQUE INSUFICIENTE",IF(X49="","",IF(X49-V49<0.01,"EMPATE TÉCNICO",""))))) | AH49: BABY/KIDS
A50: 647581 | B50: 7896699022460 | C50: M CH TIP BORBOLETA SIL O T2 | D50: LOLLY | E50: 1 | F50: B | G50: 0 | H50: 1.8 | I50: 5 | J50: 7.25 | K50: 7.25 | L50: 7.25 | M50: =IF(J50>0,J50,K50)*E50 -> 7.25 | O50: =IF(R50="","",ROUND(R50*(1-Premissas!$B$4),4)) -> 8.056 | R50: 8.48 | U50: 67 | V50: =IF(COUNT(N50:Q50)=0,"",MIN(N50:Q50)) -> 8.056 | W50: =IF(V50="","",INDEX($N$4:$Q$4,MATCH(V50,N50:Q50,0))) -> MEDCENTRO | X50: =IF(COUNT(N50:Q50)<2,"",SMALL(N50:Q50,2)) | Y50: =IF(OR(V50="",M50=0),"",V50/M50-1) -> 0.11117241 | Z50: =IF(OR(V50="",L50=""),"",V50/(L50*E50)-1) -> 0.11117241 | AA50: =IF(V50="","SEM OFERTA",IF(OR(Y50>Premissas!$B$11,Y50<Premissas!$B$12),"VERIFICAR - UNIDADE/EMBALAGEM",IF(Y50>Premissas!$B$6,"NÃO COMPRAR - REAJUSTE >5%","COMPRAR"))) -> NÃO COMPRAR - REAJUSTE >5% | AB50: =IF(W50="DIMEC",S50,IF(W50="MEDCENTRO",U50,"")) -> 67 | AC50: =IF(AA50<>"COMPRAR",0,IF(AB50="",I50,MIN(I50,AB50))) -> 0 | AD50: =IF(AC50>0,AC50*V50,0) -> 0 | AE50: =IF(AC50>0,(M50-V50)*AC50,0) -> 0 | AF50: =IF(AA50<>"COMPRAR","",IF(AB50="",IF(X50="","",IF(X50-V50<0.01,"EMPATE TÉCNICO","")),IF(AB50<I50,"ESTOQUE INSUFICIENTE",IF(X50="","",IF(X50-V50<0.01,"EMPATE TÉCNICO",""))))) | AG50: BATEL COMERCIO DE ALIMENTOS LTDA | AH50: BABY/KIDS
A51: 653561 | B51: 7896699026574 | C51: MAM BIG TIPCOLOR 300ML R M - LOLLY | D51: LOLLY | E51: 1 | F51: C | G51: 2 | H51: 1.3 | I51: 2 | J51: 17.17 | K51: 17.17 | L51: 17.17 | M51: =IF(J51>0,J51,K51)*E51 -> 17.17 | O51: =IF(R51="","",ROUND(R51*(1-Premissas!$B$4),4)) -> 23.104 | R51: 24.32 | U51: 28 | V51: =IF(COUNT(N51:Q51)=0,"",MIN(N51:Q51)) -> 23.104 | W51: =IF(V51="","",INDEX($N$4:$Q$4,MATCH(V51,N51:Q51,0))) -> MEDCENTRO | X51: =IF(COUNT(N51:Q51)<2,"",SMALL(N51:Q51,2)) | Y51: =IF(OR(V51="",M51=0),"",V51/M51-1) -> 0.3456028 | Z51: =IF(OR(V51="",L51=""),"",V51/(L51*E51)-1) -> 0.3456028 | AA51: =IF(V51="","SEM OFERTA",IF(OR(Y51>Premissas!$B$11,Y51<Premissas!$B$12),"VERIFICAR - UNIDADE/EMBALAGEM",IF(Y51>Premissas!$B$6,"NÃO COMPRAR - REAJUSTE >5%","COMPRAR"))) -> NÃO COMPRAR - REAJUSTE >5% | AB51: =IF(W51="DIMEC",S51,IF(W51="MEDCENTRO",U51,"")) -> 28 | AC51: =IF(AA51<>"COMPRAR",0,IF(AB51="",I51,MIN(I51,AB51))) -> 0 | AD51: =IF(AC51>0,AC51*V51,0) -> 0 | AE51: =IF(AC51>0,(M51-V51)*AC51,0) -> 0 | AF51: =IF(AA51<>"COMPRAR","",IF(AB51="",IF(X51="","",IF(X51-V51<0.01,"EMPATE TÉCNICO","")),IF(AB51<I51,"ESTOQUE INSUFICIENTE",IF(X51="","",IF(X51-V51<0.01,"EMPATE TÉCNICO",""))))) | AG51: BATEL COMERCIO DE ALIMENTOS LTDA | AH51: BABY/KIDS
A52: 653541 | B52: 7896699032445 | C52: MAM TIP 240ML SIL R F - LOLLY | D52: LOLLY | E52: 1 | F52: C | G52: 0 | H52: 0.7 | I52: 2 | J52: 12.71 | K52: 12.71 | L52: 12.71 | M52: =IF(J52>0,J52,K52)*E52 -> 12.71 | O52: =IF(R52="","",ROUND(R52*(1-Premissas!$B$4),4)) -> 16.4065 | R52: 17.27 | U52: 38 | V52: =IF(COUNT(N52:Q52)=0,"",MIN(N52:Q52)) -> 16.4065 | W52: =IF(V52="","",INDEX($N$4:$Q$4,MATCH(V52,N52:Q52,0))) -> MEDCENTRO | X52: =IF(COUNT(N52:Q52)<2,"",SMALL(N52:Q52,2)) | Y52: =IF(OR(V52="",M52=0),"",V52/M52-1) -> 0.29083399 | Z52: =IF(OR(V52="",L52=""),"",V52/(L52*E52)-1) -> 0.29083399 | AA52: =IF(V52="","SEM OFERTA",IF(OR(Y52>Premissas!$B$11,Y52<Premissas!$B$12),"VERIFICAR - UNIDADE/EMBALAGEM",IF(Y52>Premissas!$B$6,"NÃO COMPRAR - REAJUSTE >5%","COMPRAR"))) -> NÃO COMPRAR - REAJUSTE >5% | AB52: =IF(W52="DIMEC",S52,IF(W52="MEDCENTRO",U52,"")) -> 38 | AC52: =IF(AA52<>"COMPRAR",0,IF(AB52="",I52,MIN(I52,AB52))) -> 0 | AD52: =IF(AC52>0,AC52*V52,0) -> 0 | AE52: =IF(AC52>0,(M52-V52)*AC52,0) -> 0 | AF52: =IF(AA52<>"COMPRAR","",IF(AB52="",IF(X52="","",IF(X52-V52<0.01,"EMPATE TÉCNICO","")),IF(AB52<I52,"ESTOQUE INSUFICIENTE",IF(X52="","",IF(X52-V52<0.01,"EMPATE TÉCNICO",""))))) | AG52: BATEL COMERCIO DE ALIMENTOS LTDA | AH52: BABY/KIDS
A53: 38003 | B53: 7896033221030 | C53: MAMAD FIONA MINI SIL 50ML AZUL 641820 | D53: FIONA | E53: 1 | F53: B | G53: 0 | H53: 0.9 | I53: 3 | J53: 7.69 | K53: 7.69 | L53: 7.69 | M53: =IF(J53>0,J53,K53)*E53 -> 7.69 | O53: =IF(R53="","",ROUND(R53*(1-Premissas!$B$4),4)) -> 8.0085 | R53: 8.43 | U53: 804 | V53: =IF(COUNT(N53:Q53)=0,"",MIN(N53:Q53)) -> 8.0085 | W53: =IF(V53="","",INDEX($N$4:$Q$4,MATCH(V53,N53:Q53,0))) -> MEDCENTRO | X53: =IF(COUNT(N53:Q53)<2,"",SMALL(N53:Q53,2)) | Y53: =IF(OR(V53="",M53=0),"",V53/M53-1) -> 0.041417425 | Z53: =IF(OR(V53="",L53=""),"",V53/(L53*E53)-1) -> 0.041417425 | AA53: =IF(V53="","SEM OFERTA",IF(OR(Y53>Premissas!$B$11,Y53<Premissas!$B$12),"VERIFICAR - UNIDADE/EMBALAGEM",IF(Y53>Premissas!$B$6,"NÃO COMPRAR - REAJUSTE >5%","COMPRAR"))) -> COMPRAR | AB53: =IF(W53="DIMEC",S53,IF(W53="MEDCENTRO",U53,"")) -> 804 | AC53: =IF(AA53<>"COMPRAR",0,IF(AB53="",I53,MIN(I53,AB53))) -> 3 | AD53: =IF(AC53>0,AC53*V53,0) -> 24.0255 | AE53: =IF(AC53>0,(M53-V53)*AC53,0) -> -0.9555 | AF53: =IF(AA53<>"COMPRAR","",IF(AB53="",IF(X53="","",IF(X53-V53<0.01,"EMPATE TÉCNICO","")),IF(AB53<I53,"ESTOQUE INSUFICIENTE",IF(X53="","",IF(X53-V53<0.01,"EMPATE TÉCNICO",""))))) | AG53: CENTROFARMA DISTRIBUIDORA FARMACEUTICA LTDA | AH53: BABY/KIDS
A54: 37903 | B54: 7896033221047 | C54: MAMAD MINI SIL 50ML ROSA 821630/641830 | D54: FIONA | E54: 1 | F54: C | G54: 2 | H54: 1 | I54: 1 | J54: 7.69 | K54: 7.69 | L54: 7.69 | M54: =IF(J54>0,J54,K54)*E54 -> 7.69 | O54: =IF(R54="","",ROUND(R54*(1-Premissas!$B$4),4)) -> 8.0275 | R54: 8.45 | U54: 644 | V54: =IF(COUNT(N54:Q54)=0,"",MIN(N54:Q54)) -> 8.0275 | W54: =IF(V54="","",INDEX($N$4:$Q$4,MATCH(V54,N54:Q54,0))) -> MEDCENTRO | X54: =IF(COUNT(N54:Q54)<2,"",SMALL(N54:Q54,2)) | Y54: =IF(OR(V54="",M54=0),"",V54/M54-1) -> 0.043888166 | Z54: =IF(OR(V54="",L54=""),"",V54/(L54*E54)-1) -> 0.043888166 | AA54: =IF(V54="","SEM OFERTA",IF(OR(Y54>Premissas!$B$11,Y54<Premissas!$B$12),"VERIFICAR - UNIDADE/EMBALAGEM",IF(Y54>Premissas!$B$6,"NÃO COMPRAR - REAJUSTE >5%","COMPRAR"))) -> COMPRAR | AB54: =IF(W54="DIMEC",S54,IF(W54="MEDCENTRO",U54,"")) -> 644 | AC54: =IF(AA54<>"COMPRAR",0,IF(AB54="",I54,MIN(I54,AB54))) -> 1 | AD54: =IF(AC54>0,AC54*V54,0) -> 8.0275 | AE54: =IF(AC54>0,(M54-V54)*AC54,0) -> -0.3375 | AF54: =IF(AA54<>"COMPRAR","",IF(AB54="",IF(X54="","",IF(X54-V54<0.01,"EMPATE TÉCNICO","")),IF(AB54<I54,"ESTOQUE INSUFICIENTE",IF(X54="","",IF(X54-V54<0.01,"EMPATE TÉCNICO",""))))) | AG54: CENTROFARMA DISTRIBUIDORA FARMACEUTICA LTDA | AH54: BABY/KIDS
A55: 660001 | B55: 7896699025508 | C55: MAMADEIRA CLEAN 120 ML SIL R M - LOLLY | D55: LOLLY | E55: 1 | F55: C | G55: 0 | H55: 0.5 | I55: 2 | J55: 8.61 | K55: 8.61 | L55: 8.61 | M55: =IF(J55>0,J55,K55)*E55 -> 8.61 | O55: =IF(R55="","",ROUND(R55*(1-Premissas!$B$4),4)) -> 11.096 | R55: 11.68 | U55: 74 | V55: =IF(COUNT(N55:Q55)=0,"",MIN(N55:Q55)) -> 11.096 | W55: =IF(V55="","",INDEX($N$4:$Q$4,MATCH(V55,N55:Q55,0))) -> MEDCENTRO | X55: =IF(COUNT(N55:Q55)<2,"",SMALL(N55:Q55,2)) | Y55: =IF(OR(V55="",M55=0),"",V55/M55-1) -> 0.28873403 | Z55: =IF(OR(V55="",L55=""),"",V55/(L55*E55)-1) -> 0.28873403 | AA55: =IF(V55="","SEM OFERTA",IF(OR(Y55>Premissas!$B$11,Y55<Premissas!$B$12),"VERIFICAR - UNIDADE/EMBALAGEM",IF(Y55>Premissas!$B$6,"NÃO COMPRAR - REAJUSTE >5%","COMPRAR"))) -> NÃO COMPRAR - REAJUSTE >5% | AB55: =IF(W55="DIMEC",S55,IF(W55="MEDCENTRO",U55,"")) -> 74 | AC55: =IF(AA55<>"COMPRAR",0,IF(AB55="",I55,MIN(I55,AB55))) -> 0 | AD55: =IF(AC55>0,AC55*V55,0) -> 0 | AE55: =IF(AC55>0,(M55-V55)*AC55,0) -> 0 | AF55: =IF(AA55<>"COMPRAR","",IF(AB55="",IF(X55="","",IF(X55-V55<0.01,"EMPATE TÉCNICO","")),IF(AB55<I55,"ESTOQUE INSUFICIENTE",IF(X55="","",IF(X55-V55<0.01,"EMPATE TÉCNICO",""))))) | AG55: BATEL COMERCIO DE ALIMENTOS LTDA | AH55: BABY/KIDS
A56: 659981 | B56: 7896699025263 | C56: MORDEDOR PEIXE M - LOLLY | D56: LOLLY | E56: 1 | F56: C | G56: 2 | H56: 0.9 | I56: 1 | J56: 6.49 | K56: 6.49 | L56: 6.49 | M56: =IF(J56>0,J56,K56)*E56 -> 6.49 | O56: =IF(R56="","",ROUND(R56*(1-Premissas!$B$4),4)) -> 6.517 | R56: 6.86 | U56: 78 | V56: =IF(COUNT(N56:Q56)=0,"",MIN(N56:Q56)) -> 6.517 | W56: =IF(V56="","",INDEX($N$4:$Q$4,MATCH(V56,N56:Q56,0))) -> MEDCENTRO | X56: =IF(COUNT(N56:Q56)<2,"",SMALL(N56:Q56,2)) | Y56: =IF(OR(V56="",M56=0),"",V56/M56-1) -> 0.0041602465 | Z56: =IF(OR(V56="",L56=""),"",V56/(L56*E56)-1) -> 0.0041602465 | AA56: =IF(V56="","SEM OFERTA",IF(OR(Y56>Premissas!$B$11,Y56<Premissas!$B$12),"VERIFICAR - UNIDADE/EMBALAGEM",IF(Y56>Premissas!$B$6,"NÃO COMPRAR - REAJUSTE >5%","COMPRAR"))) -> COMPRAR | AB56: =IF(W56="DIMEC",S56,IF(W56="MEDCENTRO",U56,"")) -> 78 | AC56: =IF(AA56<>"COMPRAR",0,IF(AB56="",I56,MIN(I56,AB56))) -> 1 | AD56: =IF(AC56>0,AC56*V56,0) -> 6.517 | AE56: =IF(AC56>0,(M56-V56)*AC56,0) -> -0.027 | AF56: =IF(AA56<>"COMPRAR","",IF(AB56="",IF(X56="","",IF(X56-V56<0.01,"EMPATE TÉCNICO","")),IF(AB56<I56,"ESTOQUE INSUFICIENTE",IF(X56="","",IF(X56-V56<0.01,"EMPATE TÉCNICO",""))))) | AG56: BATEL COMERCIO DE ALIMENTOS LTDA | AH56: BABY/KIDS
A57: 602671 | B57: 7898936661012 | C57: PENTE DE ACO - DR PENTINHO | D57: DR PENTINHO | E57: 1 | F57: A | G57: 3 | H57: 3.2 | I57: 6 | J57: 11.46 | K57: 11.46 | L57: 11.46 | M57: =IF(J57>0,J57,K57)*E57 -> 11.46 | N57: 11.46 | O57: =IF(R57="","",ROUND(R57*(1-Premissas!$B$4),4)) -> 11.172 | R57: 11.76 | S57: 4 | T57: 6 | U57: 964 | V57: =IF(COUNT(N57:Q57)=0,"",MIN(N57:Q57)) -> 11.172 | W57: =IF(V57="","",INDEX($N$4:$Q$4,MATCH(V57,N57:Q57,0))) -> MEDCENTRO | X57: =IF(COUNT(N57:Q57)<2,"",SMALL(N57:Q57,2)) -> 11.46 | Y57: =IF(OR(V57="",M57=0),"",V57/M57-1) -> -0.02513089 | Z57: =IF(OR(V57="",L57=""),"",V57/(L57*E57)-1) -> -0.02513089 | AA57: =IF(V57="","SEM OFERTA",IF(OR(Y57>Premissas!$B$11,Y57<Premissas!$B$12),"VERIFICAR - UNIDADE/EMBALAGEM",IF(Y57>Premissas!$B$6,"NÃO COMPRAR - REAJUSTE >5%","COMPRAR"))) -> COMPRAR | AB57: =IF(W57="DIMEC",S57,IF(W57="MEDCENTRO",U57,"")) -> 964 | AC57: =IF(AA57<>"COMPRAR",0,IF(AB57="",I57,MIN(I57,AB57))) -> 6 | AD57: =IF(AC57>0,AC57*V57,0) -> 67.032 | AE57: =IF(AC57>0,(M57-V57)*AC57,0) -> 1.728 | AF57: =IF(AA57<>"COMPRAR","",IF(AB57="",IF(X57="","",IF(X57-V57<0.01,"EMPATE TÉCNICO","")),IF(AB57<I57,"ESTOQUE INSUFICIENTE",IF(X57="","",IF(X57-V57<0.01,"EMPATE TÉCNICO",""))))) | AG57: BATEL COMERCIO DE ALIMENTOS LTDA | AH57: BABY/KIDS
A58: 629791 | B58: 7896699030670 | C58: PREND CHUPETA LOLLY ROSA | D58: LOLLY | E58: 1 | F58: C | G58: 0 | H58: 0 | I58: 1 | J58: 11.04 | K58: 11.04 | L58: 11.04 | M58: =IF(J58>0,J58,K58)*E58 -> 11.04 | O58: =IF(R58="","",ROUND(R58*(1-Premissas!$B$4),4)) -> 11.096 | R58: 11.68 | U58: 23 | V58: =IF(COUNT(N58:Q58)=0,"",MIN(N58:Q58)) -> 11.096 | W58: =IF(V58="","",INDEX($N$4:$Q$4,MATCH(V58,N58:Q58,0))) -> MEDCENTRO | X58: =IF(COUNT(N58:Q58)<2,"",SMALL(N58:Q58,2)) | Y58: =IF(OR(V58="",M58=0),"",V58/M58-1) -> 0.0050724638 | Z58: =IF(OR(V58="",L58=""),"",V58/(L58*E58)-1) -> 0.0050724638 | AA58: =IF(V58="","SEM OFERTA",IF(OR(Y58>Premissas!$B$11,Y58<Premissas!$B$12),"VERIFICAR - UNIDADE/EMBALAGEM",IF(Y58>Premissas!$B$6,"NÃO COMPRAR - REAJUSTE >5%","COMPRAR"))) -> COMPRAR | AB58: =IF(W58="DIMEC",S58,IF(W58="MEDCENTRO",U58,"")) -> 23 | AC58: =IF(AA58<>"COMPRAR",0,IF(AB58="",I58,MIN(I58,AB58))) -> 1 | AD58: =IF(AC58>0,AC58*V58,0) -> 11.096 | AE58: =IF(AC58>0,(M58-V58)*AC58,0) -> -0.056 | AF58: =IF(AA58<>"COMPRAR","",IF(AB58="",IF(X58="","",IF(X58-V58<0.01,"EMPATE TÉCNICO","")),IF(AB58<I58,"ESTOQUE INSUFICIENTE",IF(X58="","",IF(X58-V58<0.01,"EMPATE TÉCNICO",""))))) | AG58: M C F RODRIGUES DE ANDRADE DIST IMPORT EXP ALIMENTO EIRELI | AH58: BABY/KIDS
A59: 671101 | B59: 7896699036399 | C59: SERINGA LAVAGEM NASAL AZUL 7176-01-M | D59: LOLLY | E59: 1 | F59: C | G59: 1 | H59: 0.8 | I59: 2 | J59: 15.69 | K59: 15.69 | L59: 15.69 | M59: =IF(J59>0,J59,K59)*E59 -> 15.69 | O59: =IF(R59="","",ROUND(R59*(1-Premissas!$B$4),4)) -> 18.2305 | R59: 19.19 | U59: 430 | V59: =IF(COUNT(N59:Q59)=0,"",MIN(N59:Q59)) -> 18.2305 | W59: =IF(V59="","",INDEX($N$4:$Q$4,MATCH(V59,N59:Q59,0))) -> MEDCENTRO | X59: =IF(COUNT(N59:Q59)<2,"",SMALL(N59:Q59,2)) | Y59: =IF(OR(V59="",M59=0),"",V59/M59-1) -> 0.16191842 | Z59: =IF(OR(V59="",L59=""),"",V59/(L59*E59)-1) -> 0.16191842 | AA59: =IF(V59="","SEM OFERTA",IF(OR(Y59>Premissas!$B$11,Y59<Premissas!$B$12),"VERIFICAR - UNIDADE/EMBALAGEM",IF(Y59>Premissas!$B$6,"NÃO COMPRAR - REAJUSTE >5%","COMPRAR"))) -> NÃO COMPRAR - REAJUSTE >5% | AB59: =IF(W59="DIMEC",S59,IF(W59="MEDCENTRO",U59,"")) -> 430 | AC59: =IF(AA59<>"COMPRAR",0,IF(AB59="",I59,MIN(I59,AB59))) -> 0 | AD59: =IF(AC59>0,AC59*V59,0) -> 0 | AE59: =IF(AC59>0,(M59-V59)*AC59,0) -> 0 | AF59: =IF(AA59<>"COMPRAR","",IF(AB59="",IF(X59="","",IF(X59-V59<0.01,"EMPATE TÉCNICO","")),IF(AB59<I59,"ESTOQUE INSUFICIENTE",IF(X59="","",IF(X59-V59<0.01,"EMPATE TÉCNICO",""))))) | AG59: CENTROFARMA DISTRIBUIDORA FARMACEUTICA LTDA | AH59: BABY/KIDS
A60: 671151 | B60: 7898706400148 | C60: SERINGA P/ LAVAGEM NASAL 10ML HELO KITTY | D60: MUNILA | E60: 1 | F60: B | G60: 1 | H60: 1.6 | I60: 4 | J60: 14.82 | K60: 14.82 | L60: 14.82 | M60: =IF(J60>0,J60,K60)*E60 -> 14.82 | O60: =IF(R60="","",ROUND(R60*(1-Premissas!$B$4),4)) -> 14.9055 | R60: 15.69 | U60: 370 | V60: =IF(COUNT(N60:Q60)=0,"",MIN(N60:Q60)) -> 14.9055 | W60: =IF(V60="","",INDEX($N$4:$Q$4,MATCH(V60,N60:Q60,0))) -> MEDCENTRO | X60: =IF(COUNT(N60:Q60)<2,"",SMALL(N60:Q60,2)) | Y60: =IF(OR(V60="",M60=0),"",V60/M60-1) -> 0.0057692308 | Z60: =IF(OR(V60="",L60=""),"",V60/(L60*E60)-1) -> 0.0057692308 | AA60: =IF(V60="","SEM OFERTA",IF(OR(Y60>Premissas!$B$11,Y60<Premissas!$B$12),"VERIFICAR - UNIDADE/EMBALAGEM",IF(Y60>Premissas!$B$6,"NÃO COMPRAR - REAJUSTE >5%","COMPRAR"))) -> COMPRAR | AB60: =IF(W60="DIMEC",S60,IF(W60="MEDCENTRO",U60,"")) -> 370 | AC60: =IF(AA60<>"COMPRAR",0,IF(AB60="",I60,MIN(I60,AB60))) -> 4 | AD60: =IF(AC60>0,AC60*V60,0) -> 59.622 | AE60: =IF(AC60>0,(M60-V60)*AC60,0) -> -0.342 | AF60: =IF(AA60<>"COMPRAR","",IF(AB60="",IF(X60="","",IF(X60-V60<0.01,"EMPATE TÉCNICO","")),IF(AB60<I60,"ESTOQUE INSUFICIENTE",IF(X60="","",IF(X60-V60<0.01,"EMPATE TÉCNICO",""))))) | AG60: CENTROFARMA DISTRIBUIDORA FARMACEUTICA LTDA | AH60: BABY/KIDS
A61: 671161 | B61: 7898706400155 | C61: SERINGA P/ LAVAGEM NASAL 10ML PATATI PAT | D61: MUNILA | E61: 1 | F61: B | G61: 2 | H61: 2.1 | I61: 4 | J61: 14.82 | K61: 14.82 | L61: 14.82 | M61: =IF(J61>0,J61,K61)*E61 -> 14.82 | O61: =IF(R61="","",ROUND(R61*(1-Premissas!$B$4),4)) -> 14.9055 | R61: 15.69 | U61: 58 | V61: =IF(COUNT(N61:Q61)=0,"",MIN(N61:Q61)) -> 14.9055 | W61: =IF(V61="","",INDEX($N$4:$Q$4,MATCH(V61,N61:Q61,0))) -> MEDCENTRO | X61: =IF(COUNT(N61:Q61)<2,"",SMALL(N61:Q61,2)) | Y61: =IF(OR(V61="",M61=0),"",V61/M61-1) -> 0.0057692308 | Z61: =IF(OR(V61="",L61=""),"",V61/(L61*E61)-1) -> 0.0057692308 | AA61: =IF(V61="","SEM OFERTA",IF(OR(Y61>Premissas!$B$11,Y61<Premissas!$B$12),"VERIFICAR - UNIDADE/EMBALAGEM",IF(Y61>Premissas!$B$6,"NÃO COMPRAR - REAJUSTE >5%","COMPRAR"))) -> COMPRAR | AB61: =IF(W61="DIMEC",S61,IF(W61="MEDCENTRO",U61,"")) -> 58 | AC61: =IF(AA61<>"COMPRAR",0,IF(AB61="",I61,MIN(I61,AB61))) -> 4 | AD61: =IF(AC61>0,AC61*V61,0) -> 59.622 | AE61: =IF(AC61>0,(M61-V61)*AC61,0) -> -0.342 | AF61: =IF(AA61<>"COMPRAR","",IF(AB61="",IF(X61="","",IF(X61-V61<0.01,"EMPATE TÉCNICO","")),IF(AB61<I61,"ESTOQUE INSUFICIENTE",IF(X61="","",IF(X61-V61<0.01,"EMPATE TÉCNICO",""))))) | AG61: CENTROFARMA DISTRIBUIDORA FARMACEUTICA LTDA | AH61: BABY/KIDS
A62: 671141 | B62: 7898706401138 | C62: SERINGA P/ LAVAGEM NASAL BABY 5 ML | D62: MUNILA | E62: 1 | F62: C | G62: 0 | H62: 0.3 | I62: 1 | J62: 15.84 | K62: 15.84 | L62: 15.84 | M62: =IF(J62>0,J62,K62)*E62 -> 15.84 | O62: =IF(R62="","",ROUND(R62*(1-Premissas!$B$4),4)) -> 17.556 | R62: 18.48 | U62: 372 | V62: =IF(COUNT(N62:Q62)=0,"",MIN(N62:Q62)) -> 17.556 | W62: =IF(V62="","",INDEX($N$4:$Q$4,MATCH(V62,N62:Q62,0))) -> MEDCENTRO | X62: =IF(COUNT(N62:Q62)<2,"",SMALL(N62:Q62,2)) | Y62: =IF(OR(V62="",M62=0),"",V62/M62-1) -> 0.10833333 | Z62: =IF(OR(V62="",L62=""),"",V62/(L62*E62)-1) -> 0.10833333 | AA62: =IF(V62="","SEM OFERTA",IF(OR(Y62>Premissas!$B$11,Y62<Premissas!$B$12),"VERIFICAR - UNIDADE/EMBALAGEM",IF(Y62>Premissas!$B$6,"NÃO COMPRAR - REAJUSTE >5%","COMPRAR"))) -> NÃO COMPRAR - REAJUSTE >5% | AB62: =IF(W62="DIMEC",S62,IF(W62="MEDCENTRO",U62,"")) -> 372 | AC62: =IF(AA62<>"COMPRAR",0,IF(AB62="",I62,MIN(I62,AB62))) -> 0 | AD62: =IF(AC62>0,AC62*V62,0) -> 0 | AE62: =IF(AC62>0,(M62-V62)*AC62,0) -> 0 | AF62: =IF(AA62<>"COMPRAR","",IF(AB62="",IF(X62="","",IF(X62-V62<0.01,"EMPATE TÉCNICO","")),IF(AB62<I62,"ESTOQUE INSUFICIENTE",IF(X62="","",IF(X62-V62<0.01,"EMPATE TÉCNICO",""))))) | AG62: CENTROFARMA DISTRIBUIDORA FARMACEUTICA LTDA | AH62: BABY/KIDS
A63: 685901 | B63: 7898706401930 | C63: SERINGA P/LAVAGEM NASAL LALA JACARE 10ML | D63: MUNILA | E63: 1 | F63: A | G63: 10 | H63: 4.8 | I63: 3 | J63: 13.46 | K63: 13.46 | L63: 13.46 | M63: =IF(J63>0,J63,K63)*E63 -> 13.46 | O63: =IF(R63="","",ROUND(R63*(1-Premissas!$B$4),4)) -> 13.5375 | R63: 14.25 | U63: 468 | V63: =IF(COUNT(N63:Q63)=0,"",MIN(N63:Q63)) -> 13.5375 | W63: =IF(V63="","",INDEX($N$4:$Q$4,MATCH(V63,N63:Q63,0))) -> MEDCENTRO | X63: =IF(COUNT(N63:Q63)<2,"",SMALL(N63:Q63,2)) | Y63: =IF(OR(V63="",M63=0),"",V63/M63-1) -> 0.0057578009 | Z63: =IF(OR(V63="",L63=""),"",V63/(L63*E63)-1) -> 0.0057578009 | AA63: =IF(V63="","SEM OFERTA",IF(OR(Y63>Premissas!$B$11,Y63<Premissas!$B$12),"VERIFICAR - UNIDADE/EMBALAGEM",IF(Y63>Premissas!$B$6,"NÃO COMPRAR - REAJUSTE >5%","COMPRAR"))) -> COMPRAR | AB63: =IF(W63="DIMEC",S63,IF(W63="MEDCENTRO",U63,"")) -> 468 | AC63: =IF(AA63<>"COMPRAR",0,IF(AB63="",I63,MIN(I63,AB63))) -> 3 | AD63: =IF(AC63>0,AC63*V63,0) -> 40.6125 | AE63: =IF(AC63>0,(M63-V63)*AC63,0) -> -0.2325 | AF63: =IF(AA63<>"COMPRAR","",IF(AB63="",IF(X63="","",IF(X63-V63<0.01,"EMPATE TÉCNICO","")),IF(AB63<I63,"ESTOQUE INSUFICIENTE",IF(X63="","",IF(X63-V63<0.01,"EMPATE TÉCNICO",""))))) | AG63: CENTROFARMA DISTRIBUIDORA FARMACEUTICA LTDA | AH63: BABY/KIDS
A64: 585961 | B64: 7908371200155 | C64: T. MONICA AGUINHA CL 100ML BONS TEMP LAVA | D64: PAIXAO | E64: 1 | F64: C | G64: 0 | H64: 0.1 | I64: 1 | J64: 7.83 | K64: 7.83 | L64: 7.83 | M64: =IF(J64>0,J64,K64)*E64 -> 7.83 | O64: =IF(R64="","",ROUND(R64*(1-Premissas!$B$4),4)) -> 7.885 | R64: 8.3 | U64: 1 | V64: =IF(COUNT(N64:Q64)=0,"",MIN(N64:Q64)) -> 7.885 | W64: =IF(V64="","",INDEX($N$4:$Q$4,MATCH(V64,N64:Q64,0))) -> MEDCENTRO | X64: =IF(COUNT(N64:Q64)<2,"",SMALL(N64:Q64,2)) | Y64: =IF(OR(V64="",M64=0),"",V64/M64-1) -> 0.0070242656 | Z64: =IF(OR(V64="",L64=""),"",V64/(L64*E64)-1) -> 0.0070242656 | AA64: =IF(V64="","SEM OFERTA",IF(OR(Y64>Premissas!$B$11,Y64<Premissas!$B$12),"VERIFICAR - UNIDADE/EMBALAGEM",IF(Y64>Premissas!$B$6,"NÃO COMPRAR - REAJUSTE >5%","COMPRAR"))) -> COMPRAR | AB64: =IF(W64="DIMEC",S64,IF(W64="MEDCENTRO",U64,"")) -> 1 | AC64: =IF(AA64<>"COMPRAR",0,IF(AB64="",I64,MIN(I64,AB64))) -> 1 | AD64: =IF(AC64>0,AC64*V64,0) -> 7.885 | AE64: =IF(AC64>0,(M64-V64)*AC64,0) -> -0.055 | AF64: =IF(AA64<>"COMPRAR","",IF(AB64="",IF(X64="","",IF(X64-V64<0.01,"EMPATE TÉCNICO","")),IF(AB64<I64,"ESTOQUE INSUFICIENTE",IF(X64="","",IF(X64-V64<0.01,"EMPATE TÉCNICO",""))))) | AG64: CENTROFARMA DISTRIBUIDORA FARMACEUTICA LTDA | AH64: BABY/KIDS
A65: 586061 | B65: 7908371200223 | C65: T. MONICA TALCO VEGE 200G CHEIR MEU BEBE | D65: LANGE COSMETICOS | E65: 1 | F65: C | G65: 0 | H65: 0.1 | I65: 1 | J65: 16.84 | K65: 16.84 | L65: 16.84 | M65: =IF(J65>0,J65,K65)*E65 -> 16.84 | O65: =IF(R65="","",ROUND(R65*(1-Premissas!$B$4),4)) -> 15.6655 | R65: 16.49 | U65: 1 | V65: =IF(COUNT(N65:Q65)=0,"",MIN(N65:Q65)) -> 15.6655 | W65: =IF(V65="","",INDEX($N$4:$Q$4,MATCH(V65,N65:Q65,0))) -> MEDCENTRO | X65: =IF(COUNT(N65:Q65)<2,"",SMALL(N65:Q65,2)) | Y65: =IF(OR(V65="",M65=0),"",V65/M65-1) -> -0.069744656 | Z65: =IF(OR(V65="",L65=""),"",V65/(L65*E65)-1) -> -0.069744656 | AA65: =IF(V65="","SEM OFERTA",IF(OR(Y65>Premissas!$B$11,Y65<Premissas!$B$12),"VERIFICAR - UNIDADE/EMBALAGEM",IF(Y65>Premissas!$B$6,"NÃO COMPRAR - REAJUSTE >5%","COMPRAR"))) -> COMPRAR | AB65: =IF(W65="DIMEC",S65,IF(W65="MEDCENTRO",U65,"")) -> 1 | AC65: =IF(AA65<>"COMPRAR",0,IF(AB65="",I65,MIN(I65,AB65))) -> 1 | AD65: =IF(AC65>0,AC65*V65,0) -> 15.6655 | AE65: =IF(AC65>0,(M65-V65)*AC65,0) -> 1.1745 | AF65: =IF(AA65<>"COMPRAR","",IF(AB65="",IF(X65="","",IF(X65-V65<0.01,"EMPATE TÉCNICO","")),IF(AB65<I65,"ESTOQUE INSUFICIENTE",IF(X65="","",IF(X65-V65<0.01,"EMPATE TÉCNICO",""))))) | AG65: CENTROFARMA DISTRIBUIDORA FARMACEUTICA LTDA | AH65: BABY/KIDS
A66: 452041 | B66: 7896004709413 | C66: CETOCONAZOL+DIP BETAMETASONA+SULF NEOMICINA 20+0,5+2,5MG CREME BG 30G | D66: GERMED GENERICOS | E66: 1 | F66: B | G66: 3 | H66: 1.4 | I66: 1 | J66: 8.68875 | K66: 8.68875 | L66: 8.6888 | M66: =IF(J66>0,J66,K66)*E66 -> 8.68875 | O66: =IF(R66="","",ROUND(R66*(1-Premissas!$B$4),4)) -> 9.614 | R66: 10.12 | U66: 70 | V66: =IF(COUNT(N66:Q66)=0,"",MIN(N66:Q66)) -> 9.614 | W66: =IF(V66="","",INDEX($N$4:$Q$4,MATCH(V66,N66:Q66,0))) -> MEDCENTRO | X66: =IF(COUNT(N66:Q66)<2,"",SMALL(N66:Q66,2)) | Y66: =IF(OR(V66="",M66=0),"",V66/M66-1) -> 0.10648828 | Z66: =IF(OR(V66="",L66=""),"",V66/(L66*E66)-1) -> 0.10648191 | AA66: =IF(V66="","SEM OFERTA",IF(OR(Y66>Premissas!$B$11,Y66<Premissas!$B$12),"VERIFICAR - UNIDADE/EMBALAGEM",IF(Y66>Premissas!$B$6,"NÃO COMPRAR - REAJUSTE >5%","COMPRAR"))) -> NÃO COMPRAR - REAJUSTE >5% | AB66: =IF(W66="DIMEC",S66,IF(W66="MEDCENTRO",U66,"")) -> 70 | AC66: =IF(AA66<>"COMPRAR",0,IF(AB66="",I66,MIN(I66,AB66))) -> 0 | AD66: =IF(AC66>0,AC66*V66,0) -> 0 | AE66: =IF(AC66>0,(M66-V66)*AC66,0) -> 0 | AF66: =IF(AA66<>"COMPRAR","",IF(AB66="",IF(X66="","",IF(X66-V66<0.01,"EMPATE TÉCNICO","")),IF(AB66<I66,"ESTOQUE INSUFICIENTE",IF(X66="","",IF(X66-V66<0.01,"EMPATE TÉCNICO",""))))) | AH66: CONVENIENCIA
A67: 222121 | B67: 7898166041004 | C67: DIPIFARMA 500 MG/ML SOL INJ CX 100 AMP VD AMB X 2 ML (EMB HOSP) | D67: FARMACE INDUSTRIA QUIMICO-FARMACEUTICA CEARENSE | E67: 1 | F67: C | G67: 0 | H67: 0.1 | I67: 1 | J67: 2.56 | K67: 2.56 | L67: 2.56 | M67: =IF(J67>0,J67,K67)*E67 -> 2.56 | N67: 90.46 | O67: =IF(R67="","",ROUND(R67*(1-Premissas!$B$4),4)) | S67: 98 | T67: 100 | V67: =IF(COUNT(N67:Q67)=0,"",MIN(N67:Q67)) -> 90.46 | W67: =IF(V67="","",INDEX($N$4:$Q$4,MATCH(V67,N67:Q67,0))) -> DIMEC | X67: =IF(COUNT(N67:Q67)<2,"",SMALL(N67:Q67,2)) | Y67: =IF(OR(V67="",M67=0),"",V67/M67-1) -> 34.335938 | Z67: =IF(OR(V67="",L67=""),"",V67/(L67*E67)-1) -> 34.335938 | AA67: =IF(V67="","SEM OFERTA",IF(OR(Y67>Premissas!$B$11,Y67<Premissas!$B$12),"VERIFICAR - UNIDADE/EMBALAGEM",IF(Y67>Premissas!$B$6,"NÃO COMPRAR - REAJUSTE >5%","COMPRAR"))) -> VERIFICAR - UNIDADE/EMBALAGEM | AB67: =IF(W67="DIMEC",S67,IF(W67="MEDCENTRO",U67,"")) -> 98 | AC67: =IF(AA67<>"COMPRAR",0,IF(AB67="",I67,MIN(I67,AB67))) -> 0 | AD67: =IF(AC67>0,AC67*V67,0) -> 0 | AE67: =IF(AC67>0,(M67-V67)*AC67,0) -> 0 | AF67: =IF(AA67<>"COMPRAR","",IF(AB67="",IF(X67="","",IF(X67-V67<0.01,"EMPATE TÉCNICO","")),IF(AB67<I67,"ESTOQUE INSUFICIENTE",IF(X67="","",IF(X67-V67<0.01,"EMPATE TÉCNICO",""))))) | AG67: CAPITAL MED DISTRIBUIDORA DE MEDICAMENTOS LTDA | AH67: CONVENIENCIA
A68: 532161 | B68: 7898031310587 | C68: AGUA OXIGENADA ALMOT. 10 VOL. 100ML | D68: UNIPHAR | E68: 1 | F68: A | G68: 0 | H68: 21.3 | I68: 55 | J68: 2.35 | K68: 2.35 | L68: 2.35 | M68: =IF(J68>0,J68,K68)*E68 -> 2.35 | N68: 2.69 | O68: =IF(R68="","",ROUND(R68*(1-Premissas!$B$4),4)) -> 2.603 | R68: 2.74 | S68: 2169 | T68: 72 | U68: 2051 | V68: =IF(COUNT(N68:Q68)=0,"",MIN(N68:Q68)) -> 2.603 | W68: =IF(V68="","",INDEX($N$4:$Q$4,MATCH(V68,N68:Q68,0))) -> MEDCENTRO | X68: =IF(COUNT(N68:Q68)<2,"",SMALL(N68:Q68,2)) -> 2.69 | Y68: =IF(OR(V68="",M68=0),"",V68/M68-1) -> 0.10765957 | Z68: =IF(OR(V68="",L68=""),"",V68/(L68*E68)-1) -> 0.10765957 | AA68: =IF(V68="","SEM OFERTA",IF(OR(Y68>Premissas!$B$11,Y68<Premissas!$B$12),"VERIFICAR - UNIDADE/EMBALAGEM",IF(Y68>Premissas!$B$6,"NÃO COMPRAR - REAJUSTE >5%","COMPRAR"))) -> NÃO COMPRAR - REAJUSTE >5% | AB68: =IF(W68="DIMEC",S68,IF(W68="MEDCENTRO",U68,"")) -> 2051 | AC68: =IF(AA68<>"COMPRAR",0,IF(AB68="",I68,MIN(I68,AB68))) -> 0 | AD68: =IF(AC68>0,AC68*V68,0) -> 0 | AE68: =IF(AC68>0,(M68-V68)*AC68,0) -> 0 | AF68: =IF(AA68<>"COMPRAR","",IF(AB68="",IF(X68="","",IF(X68-V68<0.01,"EMPATE TÉCNICO","")),IF(AB68<I68,"ESTOQUE INSUFICIENTE",IF(X68="","",IF(X68-V68<0.01,"EMPATE TÉCNICO",""))))) | AG68: C & B LTDA | AH68: CURATIVO
A69: 3233 | B69: 7896902210479 | C69: ALCOOL 70% 50ML | D69: FARMAX | E69: 1 | F69: A | G69: 36 | H69: 35.9 | I69: 57 | J69: 2.42 | K69: 2.42 | L69: 2.38 | M69: =IF(J69>0,J69,K69)*E69 -> 2.42 | N69: 2.37 | O69: =IF(R69="","",ROUND(R69*(1-Premissas!$B$4),4)) | S69: 3735 | T69: 72 | V69: =IF(COUNT(N69:Q69)=0,"",MIN(N69:Q69)) -> 2.37 | W69: =IF(V69="","",INDEX($N$4:$Q$4,MATCH(V69,N69:Q69,0))) -> DIMEC | X69: =IF(COUNT(N69:Q69)<2,"",SMALL(N69:Q69,2)) | Y69: =IF(OR(V69="",M69=0),"",V69/M69-1) -> -0.020661157 | Z69: =IF(OR(V69="",L69=""),"",V69/(L69*E69)-1) -> -0.0042016807 | AA69: =IF(V69="","SEM OFERTA",IF(OR(Y69>Premissas!$B$11,Y69<Premissas!$B$12),"VERIFICAR - UNIDADE/EMBALAGEM",IF(Y69>Premissas!$B$6,"NÃO COMPRAR - REAJUSTE >5%","COMPRAR"))) -> COMPRAR | AB69: =IF(W69="DIMEC",S69,IF(W69="MEDCENTRO",U69,"")) -> 3735 | AC69: =IF(AA69<>"COMPRAR",0,IF(AB69="",I69,MIN(I69,AB69))) -> 57 | AD69: =IF(AC69>0,AC69*V69,0) -> 135.09 | AE69: =IF(AC69>0,(M69-V69)*AC69,0) -> 2.85 | AF69: =IF(AA69<>"COMPRAR","",IF(AB69="",IF(X69="","",IF(X69-V69<0.01,"EMPATE TÉCNICO","")),IF(AB69<I69,"ESTOQUE INSUFICIENTE",IF(X69="","",IF(X69-V69<0.01,"EMPATE TÉCNICO",""))))) | AG69: DSC DISTRIBUIDORA DE MEDICAMENTOS LTDA | AH69: CURATIVO
A70: 542161 | B70: 7898031313465 | C70: ALCOOL 70% 50ML | D70: UNIPHAR | E70: 1 | F70: A | G70: 29 | H70: 30 | I70: 36 | J70: 2.54 | K70: 2.54 | L70: 2.54 | M70: =IF(J70>0,J70,K70)*E70 -> 2.54 | N70: 2.67 | O70: =IF(R70="","",ROUND(R70*(1-Premissas!$B$4),4)) -> 2.584 | R70: 2.72 | S70: 7747 | T70: 216 | U70: 1525 | V70: =IF(COUNT(N70:Q70)=0,"",MIN(N70:Q70)) -> 2.584 | W70: =IF(V70="","",INDEX($N$4:$Q$4,MATCH(V70,N70:Q70,0))) -> MEDCENTRO | X70: =IF(COUNT(N70:Q70)<2,"",SMALL(N70:Q70,2)) -> 2.67 | Y70: =IF(OR(V70="",M70=0),"",V70/M70-1) -> 0.017322835 | Z70: =IF(OR(V70="",L70=""),"",V70/(L70*E70)-1) -> 0.017322835 | AA70: =IF(V70="","SEM OFERTA",IF(OR(Y70>Premissas!$B$11,Y70<Premissas!$B$12),"VERIFICAR - UNIDADE/EMBALAGEM",IF(Y70>Premissas!$B$6,"NÃO COMPRAR - REAJUSTE >5%","COMPRAR"))) -> COMPRAR | AB70: =IF(W70="DIMEC",S70,IF(W70="MEDCENTRO",U70,"")) -> 1525 | AC70: =IF(AA70<>"COMPRAR",0,IF(AB70="",I70,MIN(I70,AB70))) -> 36 | AD70: =IF(AC70>0,AC70*V70,0) -> 93.024 | AE70: =IF(AC70>0,(M70-V70)*AC70,0) -> -1.584 | AF70: =IF(AA70<>"COMPRAR","",IF(AB70="",IF(X70="","",IF(X70-V70<0.01,"EMPATE TÉCNICO","")),IF(AB70<I70,"ESTOQUE INSUFICIENTE",IF(X70="","",IF(X70-V70<0.01,"EMPATE TÉCNICO",""))))) | AG70: DSC DISTRIBUIDORA DE MEDICAMENTOS LTDA | AH70: CURATIVO
A71: 5043 | B71: 7898031310877 | C71: ALCOOL GEL 70% 50G UNISSEPT | D71: UNIPHAR | E71: 1 | F71: B | G71: 6 | H71: 5.4 | I71: 8 | J71: 3.51 | K71: 3.51 | L71: 3.51 | M71: =IF(J71>0,J71,K71)*E71 -> 3.51 | N71: 3.51 | O71: =IF(R71="","",ROUND(R71*(1-Premissas!$B$4),4)) | S71: 219 | T71: 144 | V71: =IF(COUNT(N71:Q71)=0,"",MIN(N71:Q71)) -> 3.51 | W71: =IF(V71="","",INDEX($N$4:$Q$4,MATCH(V71,N71:Q71,0))) -> DIMEC | X71: =IF(COUNT(N71:Q71)<2,"",SMALL(N71:Q71,2)) | Y71: =IF(OR(V71="",M71=0),"",V71/M71-1) -> 0 | Z71: =IF(OR(V71="",L71=""),"",V71/(L71*E71)-1) -> 0 | AA71: =IF(V71="","SEM OFERTA",IF(OR(Y71>Premissas!$B$11,Y71<Premissas!$B$12),"VERIFICAR - UNIDADE/EMBALAGEM",IF(Y71>Premissas!$B$6,"NÃO COMPRAR - REAJUSTE >5%","COMPRAR"))) -> COMPRAR | AB71: =IF(W71="DIMEC",S71,IF(W71="MEDCENTRO",U71,"")) -> 219 | AC71: =IF(AA71<>"COMPRAR",0,IF(AB71="",I71,MIN(I71,AB71))) -> 8 | AD71: =IF(AC71>0,AC71*V71,0) -> 28.08 | AE71: =IF(AC71>0,(M71-V71)*AC71,0) -> 0 | AF71: =IF(AA71<>"COMPRAR","",IF(AB71="",IF(X71="","",IF(X71-V71<0.01,"EMPATE TÉCNICO","")),IF(AB71<I71,"ESTOQUE INSUFICIENTE",IF(X71="","",IF(X71-V71<0.01,"EMPATE TÉCNICO",""))))) | AG71: DSC DISTRIBUIDORA DE MEDICAMENTOS LTDA | AH71: CURATIVO
A72: 3443 | B72: 7898108641323 | C72: ATADURA DE CREPE 06CM C/12 UND | D72: CREMER | E72: 1 | F72: C | G72: 1 | H72: 1.3 | I72: 3 | J72: 1.13 | K72: 1.13 | L72: 1.13 | M72: =IF(J72>0,J72,K72)*E72 -> 1.13 | N72: 1.25 | O72: =IF(R72="","",ROUND(R72*(1-Premissas!$B$4),4)) -> 1.2635 | R72: 1.33 | S72: 1297 | T72: 240 | U72: 320 | V72: =IF(COUNT(N72:Q72)=0,"",MIN(N72:Q72)) -> 1.25 | W72: =IF(V72="","",INDEX($N$4:$Q$4,MATCH(V72,N72:Q72,0))) -> DIMEC | X72: =IF(COUNT(N72:Q72)<2,"",SMALL(N72:Q72,2)) -> 1.2635 | Y72: =IF(OR(V72="",M72=0),"",V72/M72-1) -> 0.10619469 | Z72: =IF(OR(V72="",L72=""),"",V72/(L72*E72)-1) -> 0.10619469 | AA72: =IF(V72="","SEM OFERTA",IF(OR(Y72>Premissas!$B$11,Y72<Premissas!$B$12),"VERIFICAR - UNIDADE/EMBALAGEM",IF(Y72>Premissas!$B$6,"NÃO COMPRAR - REAJUSTE >5%","COMPRAR"))) -> NÃO COMPRAR - REAJUSTE >5% | AB72: =IF(W72="DIMEC",S72,IF(W72="MEDCENTRO",U72,"")) -> 1297 | AC72: =IF(AA72<>"COMPRAR",0,IF(AB72="",I72,MIN(I72,AB72))) -> 0 | AD72: =IF(AC72>0,AC72*V72,0) -> 0 | AE72: =IF(AC72>0,(M72-V72)*AC72,0) -> 0 | AF72: =IF(AA72<>"COMPRAR","",IF(AB72="",IF(X72="","",IF(X72-V72<0.01,"EMPATE TÉCNICO","")),IF(AB72<I72,"ESTOQUE INSUFICIENTE",IF(X72="","",IF(X72-V72<0.01,"EMPATE TÉCNICO",""))))) | AG72: DSC DISTRIBUIDORA DE MEDICAMENTOS LTDA | AH72: CURATIVO
A73: 597791 | B73: 7898933598625 | C73: ATADURA DE CREPE 06CM UND | D73: TEXPHARMA | E73: 12 | F73: A | G73: 1 | H73: 38.3 | I73: 9 | J73: 0.49916667 | K73: 0.49916667 | L73: 0.4992 | M73: =IF(J73>0,J73,K73)*E73 -> 5.99 | N73: 5.25 | O73: =IF(R73="","",ROUND(R73*(1-Premissas!$B$4),4)) | S73: 773 | T73: 12 | V73: =IF(COUNT(N73:Q73)=0,"",MIN(N73:Q73)) -> 5.25 | W73: =IF(V73="","",INDEX($N$4:$Q$4,MATCH(V73,N73:Q73,0))) -> DIMEC | X73: =IF(COUNT(N73:Q73)<2,"",SMALL(N73:Q73,2)) | Y73: =IF(OR(V73="",M73=0),"",V73/M73-1) -> -0.12353923 | Z73: =IF(OR(V73="",L73=""),"",V73/(L73*E73)-1) -> -0.12359776 | AA73: =IF(V73="","SEM OFERTA",IF(OR(Y73>Premissas!$B$11,Y73<Premissas!$B$12),"VERIFICAR - UNIDADE/EMBALAGEM",IF(Y73>Premissas!$B$6,"NÃO COMPRAR - REAJUSTE >5%","COMPRAR"))) -> COMPRAR | AB73: =IF(W73="DIMEC",S73,IF(W73="MEDCENTRO",U73,"")) -> 773 | AC73: =IF(AA73<>"COMPRAR",0,IF(AB73="",I73,MIN(I73,AB73))) -> 9 | AD73: =IF(AC73>0,AC73*V73,0) -> 47.25 | AE73: =IF(AC73>0,(M73-V73)*AC73,0) -> 6.66 | AF73: =IF(AA73<>"COMPRAR","",IF(AB73="",IF(X73="","",IF(X73-V73<0.01,"EMPATE TÉCNICO","")),IF(AB73<I73,"ESTOQUE INSUFICIENTE",IF(X73="","",IF(X73-V73<0.01,"EMPATE TÉCNICO",""))))) | AG73: DSC DISTRIBUIDORA DE MEDICAMENTOS LTDA | AH73: CURATIVO
A74: 623471 | B74: 7898933598755 | C74: ATADURA DE CREPE 15CM C/12 UND | D74: TEXPHARMA | E74: 12 | F74: A | G74: 0 | H74: 56.9 | I74: 13 | J74: 0.81833333 | K74: 0.81833333 | L74: 0.8183 | M74: =IF(J74>0,J74,K74)*E74 -> 9.82 | N74: 9.82 | O74: =IF(R74="","",ROUND(R74*(1-Premissas!$B$4),4)) | S74: 509 | T74: 12 | V74: =IF(COUNT(N74:Q74)=0,"",MIN(N74:Q74)) -> 9.82 | W74: =IF(V74="","",INDEX($N$4:$Q$4,MATCH(V74,N74:Q74,0))) -> DIMEC | X74: =IF(COUNT(N74:Q74)<2,"",SMALL(N74:Q74,2)) | Y74: =IF(OR(V74="",M74=0),"",V74/M74-1) -> 0 | Z74: =IF(OR(V74="",L74=""),"",V74/(L74*E74)-1) -> 4.0734857e-05 | AA74: =IF(V74="","SEM OFERTA",IF(OR(Y74>Premissas!$B$11,Y74<Premissas!$B$12),"VERIFICAR - UNIDADE/EMBALAGEM",IF(Y74>Premissas!$B$6,"NÃO COMPRAR - REAJUSTE >5%","COMPRAR"))) -> COMPRAR | AB74: =IF(W74="DIMEC",S74,IF(W74="MEDCENTRO",U74,"")) -> 509 | AC74: =IF(AA74<>"COMPRAR",0,IF(AB74="",I74,MIN(I74,AB74))) -> 13 | AD74: =IF(AC74>0,AC74*V74,0) -> 127.66 | AE74: =IF(AC74>0,(M74-V74)*AC74,0) -> 0 | AF74: =IF(AA74<>"COMPRAR","",IF(AB74="",IF(X74="","",IF(X74-V74<0.01,"EMPATE TÉCNICO","")),IF(AB74<I74,"ESTOQUE INSUFICIENTE",IF(X74="","",IF(X74-V74<0.01,"EMPATE TÉCNICO",""))))) | AG74: DSC DISTRIBUIDORA DE MEDICAMENTOS LTDA | AH74: CURATIVO
A75: 613211 | B75: 7898933598786 | C75: ATADURA DE CREPE 30CM C/12 UND | D75: TEXPHARMA | E75: 12 | F75: A | G75: 30 | H75: 21.1 | I75: 3 | J75: 1.6391667 | K75: 1.6391667 | L75: 1.6392 | M75: =IF(J75>0,J75,K75)*E75 -> 19.67 | N75: 19.67 | O75: =IF(R75="","",ROUND(R75*(1-Premissas!$B$4),4)) | S75: 49 | T75: 12 | V75: =IF(COUNT(N75:Q75)=0,"",MIN(N75:Q75)) -> 19.67 | W75: =IF(V75="","",INDEX($N$4:$Q$4,MATCH(V75,N75:Q75,0))) -> DIMEC | X75: =IF(COUNT(N75:Q75)<2,"",SMALL(N75:Q75,2)) | Y75: =IF(OR(V75="",M75=0),"",V75/M75-1) -> 0 | Z75: =IF(OR(V75="",L75=""),"",V75/(L75*E75)-1) -> -2.0335123e-05 | AA75: =IF(V75="","SEM OFERTA",IF(OR(Y75>Premissas!$B$11,Y75<Premissas!$B$12),"VERIFICAR - UNIDADE/EMBALAGEM",IF(Y75>Premissas!$B$6,"NÃO COMPRAR - REAJUSTE >5%","COMPRAR"))) -> COMPRAR | AB75: =IF(W75="DIMEC",S75,IF(W75="MEDCENTRO",U75,"")) -> 49 | AC75: =IF(AA75<>"COMPRAR",0,IF(AB75="",I75,MIN(I75,AB75))) -> 3 | AD75: =IF(AC75>0,AC75*V75,0) -> 59.01 | AE75: =IF(AC75>0,(M75-V75)*AC75,0) -> 0 | AF75: =IF(AA75<>"COMPRAR","",IF(AB75="",IF(X75="","",IF(X75-V75<0.01,"EMPATE TÉCNICO","")),IF(AB75<I75,"ESTOQUE INSUFICIENTE",IF(X75="","",IF(X75-V75<0.01,"EMPATE TÉCNICO",""))))) | AG75: DSC DISTRIBUIDORA DE MEDICAMENTOS LTDA | AH75: CURATIVO
A76: 653611 | B76: 7898108642078 | C76: ATADURA DE CREPE MICKEY 06CM | D76: SANFARMA | E76: 1 | F76: C | G76: 0 | H76: 1.6 | I76: 4 | J76: 1.25 | K76: 1.25 | L76: 1.25 | M76: =IF(J76>0,J76,K76)*E76 -> 1.25 | N76: 1.43 | O76: =IF(R76="","",ROUND(R76*(1-Premissas!$B$4),4)) | S76: 960 | T76: 240 | V76: =IF(COUNT(N76:Q76)=0,"",MIN(N76:Q76)) -> 1.43 | W76: =IF(V76="","",INDEX($N$4:$Q$4,MATCH(V76,N76:Q76,0))) -> DIMEC | X76: =IF(COUNT(N76:Q76)<2,"",SMALL(N76:Q76,2)) | Y76: =IF(OR(V76="",M76=0),"",V76/M76-1) -> 0.144 | Z76: =IF(OR(V76="",L76=""),"",V76/(L76*E76)-1) -> 0.144 | AA76: =IF(V76="","SEM OFERTA",IF(OR(Y76>Premissas!$B$11,Y76<Premissas!$B$12),"VERIFICAR - UNIDADE/EMBALAGEM",IF(Y76>Premissas!$B$6,"NÃO COMPRAR - REAJUSTE >5%","COMPRAR"))) -> NÃO COMPRAR - REAJUSTE >5% | AB76: =IF(W76="DIMEC",S76,IF(W76="MEDCENTRO",U76,"")) -> 960 | AC76: =IF(AA76<>"COMPRAR",0,IF(AB76="",I76,MIN(I76,AB76))) -> 0 | AD76: =IF(AC76>0,AC76*V76,0) -> 0 | AE76: =IF(AC76>0,(M76-V76)*AC76,0) -> 0 | AF76: =IF(AA76<>"COMPRAR","",IF(AB76="",IF(X76="","",IF(X76-V76<0.01,"EMPATE TÉCNICO","")),IF(AB76<I76,"ESTOQUE INSUFICIENTE",IF(X76="","",IF(X76-V76<0.01,"EMPATE TÉCNICO",""))))) | AG76: NAZARIA DISTRIBUIDORA DE PRODUTOS FARMACEUTICOS LTDA | AH76: CURATIVO
A77: 661591 | B77: 7898108642085 | C77: ATADURA DE CREPE MICKEY 08CM | D77: SANFARMA | E77: 1 | F77: C | G77: 0 | H77: 1 | I77: 3 | J77: 1.935 | K77: 1.935 | L77: 1.935 | M77: =IF(J77>0,J77,K77)*E77 -> 1.935 | N77: 1.8 | O77: =IF(R77="","",ROUND(R77*(1-Premissas!$B$4),4)) -> 1.5865 | R77: 1.67 | S77: 1080 | T77: 216 | U77: 1 | V77: =IF(COUNT(N77:Q77)=0,"",MIN(N77:Q77)) -> 1.5865 | W77: =IF(V77="","",INDEX($N$4:$Q$4,MATCH(V77,N77:Q77,0))) -> MEDCENTRO | X77: =IF(COUNT(N77:Q77)<2,"",SMALL(N77:Q77,2)) -> 1.8 | Y77: =IF(OR(V77="",M77=0),"",V77/M77-1) -> -0.18010336 | Z77: =IF(OR(V77="",L77=""),"",V77/(L77*E77)-1) -> -0.18010336 | AA77: =IF(V77="","SEM OFERTA",IF(OR(Y77>Premissas!$B$11,Y77<Premissas!$B$12),"VERIFICAR - UNIDADE/EMBALAGEM",IF(Y77>Premissas!$B$6,"NÃO COMPRAR - REAJUSTE >5%","COMPRAR"))) -> COMPRAR | AB77: =IF(W77="DIMEC",S77,IF(W77="MEDCENTRO",U77,"")) -> 1 | AC77: =IF(AA77<>"COMPRAR",0,IF(AB77="",I77,MIN(I77,AB77))) -> 1 | AD77: =IF(AC77>0,AC77*V77,0) -> 1.5865 | AE77: =IF(AC77>0,(M77-V77)*AC77,0) -> 0.3485 | AF77: =IF(AA77<>"COMPRAR","",IF(AB77="",IF(X77="","",IF(X77-V77<0.01,"EMPATE TÉCNICO","")),IF(AB77<I77,"ESTOQUE INSUFICIENTE",IF(X77="","",IF(X77-V77<0.01,"EMPATE TÉCNICO",""))))) -> ESTOQUE INSUFICIENTE | AG77: NAZARIA DISTRIBUIDORA DE PRODUTOS FARMACEUTICOS LTDA | AH77: CURATIVO
A78: 653621 | B78: 7898108642108 | C78: ATADURA DE CREPE MICKEY 12CM | D78: SANFARMA | E78: 1 | F78: C | G78: 2 | H78: 0.6 | I78: 1 | J78: 2.51 | K78: 2.51 | L78: 2.23 | M78: =IF(J78>0,J78,K78)*E78 -> 2.51 | N78: 2.66 | O78: =IF(R78="","",ROUND(R78*(1-Premissas!$B$4),4)) | S78: 1048 | T78: 144 | V78: =IF(COUNT(N78:Q78)=0,"",MIN(N78:Q78)) -> 2.66 | W78: =IF(V78="","",INDEX($N$4:$Q$4,MATCH(V78,N78:Q78,0))) -> DIMEC | X78: =IF(COUNT(N78:Q78)<2,"",SMALL(N78:Q78,2)) | Y78: =IF(OR(V78="",M78=0),"",V78/M78-1) -> 0.059760956 | Z78: =IF(OR(V78="",L78=""),"",V78/(L78*E78)-1) -> 0.19282511 | AA78: =IF(V78="","SEM OFERTA",IF(OR(Y78>Premissas!$B$11,Y78<Premissas!$B$12),"VERIFICAR - UNIDADE/EMBALAGEM",IF(Y78>Premissas!$B$6,"NÃO COMPRAR - REAJUSTE >5%","COMPRAR"))) -> NÃO COMPRAR - REAJUSTE >5% | AB78: =IF(W78="DIMEC",S78,IF(W78="MEDCENTRO",U78,"")) -> 1048 | AC78: =IF(AA78<>"COMPRAR",0,IF(AB78="",I78,MIN(I78,AB78))) -> 0 | AD78: =IF(AC78>0,AC78*V78,0) -> 0 | AE78: =IF(AC78>0,(M78-V78)*AC78,0) -> 0 | AF78: =IF(AA78<>"COMPRAR","",IF(AB78="",IF(X78="","",IF(X78-V78<0.01,"EMPATE TÉCNICO","")),IF(AB78<I78,"ESTOQUE INSUFICIENTE",IF(X78="","",IF(X78-V78<0.01,"EMPATE TÉCNICO",""))))) | AG78: NAZARIA DISTRIBUIDORA DE PRODUTOS FARMACEUTICOS LTDA | AH78: CURATIVO
A79: 661601 | B79: 7898108641347 | C79: ATADURA DE CREPE SANF 12CMX1,80M | D79: SANFARMA | E79: 1 | F79: C | G79: 0 | H79: 0.6 | I79: 2 | J79: 2.23 | K79: 2.23 | L79: 2.23 | M79: =IF(J79>0,J79,K79)*E79 -> 2.23 | N79: 2.38 | O79: =IF(R79="","",ROUND(R79*(1-Premissas!$B$4),4)) -> 2.356 | R79: 2.48 | S79: 3166 | T79: 144 | U79: 53 | V79: =IF(COUNT(N79:Q79)=0,"",MIN(N79:Q79)) -> 2.356 | W79: =IF(V79="","",INDEX($N$4:$Q$4,MATCH(V79,N79:Q79,0))) -> MEDCENTRO | X79: =IF(COUNT(N79:Q79)<2,"",SMALL(N79:Q79,2)) -> 2.38 | Y79: =IF(OR(V79="",M79=0),"",V79/M79-1) -> 0.056502242 | Z79: =IF(OR(V79="",L79=""),"",V79/(L79*E79)-1) -> 0.056502242 | AA79: =IF(V79="","SEM OFERTA",IF(OR(Y79>Premissas!$B$11,Y79<Premissas!$B$12),"VERIFICAR - UNIDADE/EMBALAGEM",IF(Y79>Premissas!$B$6,"NÃO COMPRAR - REAJUSTE >5%","COMPRAR"))) -> NÃO COMPRAR - REAJUSTE >5% | AB79: =IF(W79="DIMEC",S79,IF(W79="MEDCENTRO",U79,"")) -> 53 | AC79: =IF(AA79<>"COMPRAR",0,IF(AB79="",I79,MIN(I79,AB79))) -> 0 | AD79: =IF(AC79>0,AC79*V79,0) -> 0 | AE79: =IF(AC79>0,(M79-V79)*AC79,0) -> 0 | AF79: =IF(AA79<>"COMPRAR","",IF(AB79="",IF(X79="","",IF(X79-V79<0.01,"EMPATE TÉCNICO","")),IF(AB79<I79,"ESTOQUE INSUFICIENTE",IF(X79="","",IF(X79-V79<0.01,"EMPATE TÉCNICO",""))))) | AG79: NAZARIA DISTRIBUIDORA DE PRODUTOS FARMACEUTICOS LTDA | AH79: CURATIVO
A80: 648301 | B80: 7898108640906 | C80: CAIXA DE ALGODAO SANCARE 25G | D80: SANFARMA | E80: 1 | F80: C | G80: 0 | H80: 0.5 | I80: 2 | J80: 1.97 | K80: 1.97 | L80: 1.97 | M80: =IF(J80>0,J80,K80)*E80 -> 1.97 | N80: 2.22 | O80: =IF(R80="","",ROUND(R80*(1-Premissas!$B$4),4)) -> 2.2135 | R80: 2.33 | S80: 112 | T80: 100 | U80: 109 | V80: =IF(COUNT(N80:Q80)=0,"",MIN(N80:Q80)) -> 2.2135 | W80: =IF(V80="","",INDEX($N$4:$Q$4,MATCH(V80,N80:Q80,0))) -> MEDCENTRO | X80: =IF(COUNT(N80:Q80)<2,"",SMALL(N80:Q80,2)) -> 2.22 | Y80: =IF(OR(V80="",M80=0),"",V80/M80-1) -> 0.12360406 | Z80: =IF(OR(V80="",L80=""),"",V80/(L80*E80)-1) -> 0.12360406 | AA80: =IF(V80="","SEM OFERTA",IF(OR(Y80>Premissas!$B$11,Y80<Premissas!$B$12),"VERIFICAR - UNIDADE/EMBALAGEM",IF(Y80>Premissas!$B$6,"NÃO COMPRAR - REAJUSTE >5%","COMPRAR"))) -> NÃO COMPRAR - REAJUSTE >5% | AB80: =IF(W80="DIMEC",S80,IF(W80="MEDCENTRO",U80,"")) -> 109 | AC80: =IF(AA80<>"COMPRAR",0,IF(AB80="",I80,MIN(I80,AB80))) -> 0 | AD80: =IF(AC80>0,AC80*V80,0) -> 0 | AE80: =IF(AC80>0,(M80-V80)*AC80,0) -> 0 | AF80: =IF(AA80<>"COMPRAR","",IF(AB80="",IF(X80="","",IF(X80-V80<0.01,"EMPATE TÉCNICO","")),IF(AB80<I80,"ESTOQUE INSUFICIENTE",IF(X80="","",IF(X80-V80<0.01,"EMPATE TÉCNICO",""))))) | AG80: NAZARIA DISTRIBUIDORA DE PRODUTOS FARMACEUTICOS LTDA | AH80: CURATIVO
A81: 608901 | B81: 7898108640661 | C81: CICATRISAN CURATIVO 10UN | D81: SANFARMA | E81: 1 | F81: B | G81: 0 | H81: 10.7 | I81: 28 | J81: 1.75 | K81: 1.75 | L81: 1.75 | M81: =IF(J81>0,J81,K81)*E81 -> 1.75 | N81: 2.05 | O81: =IF(R81="","",ROUND(R81*(1-Premissas!$B$4),4)) -> 2.128 | R81: 2.24 | S81: 4103 | T81: 80 | U81: 543 | V81: =IF(COUNT(N81:Q81)=0,"",MIN(N81:Q81)) -> 2.05 | W81: =IF(V81="","",INDEX($N$4:$Q$4,MATCH(V81,N81:Q81,0))) -> DIMEC | X81: =IF(COUNT(N81:Q81)<2,"",SMALL(N81:Q81,2)) -> 2.128 | Y81: =IF(OR(V81="",M81=0),"",V81/M81-1) -> 0.17142857 | Z81: =IF(OR(V81="",L81=""),"",V81/(L81*E81)-1) -> 0.17142857 | AA81: =IF(V81="","SEM OFERTA",IF(OR(Y81>Premissas!$B$11,Y81<Premissas!$B$12),"VERIFICAR - UNIDADE/EMBALAGEM",IF(Y81>Premissas!$B$6,"NÃO COMPRAR - REAJUSTE >5%","COMPRAR"))) -> NÃO COMPRAR - REAJUSTE >5% | AB81: =IF(W81="DIMEC",S81,IF(W81="MEDCENTRO",U81,"")) -> 4103 | AC81: =IF(AA81<>"COMPRAR",0,IF(AB81="",I81,MIN(I81,AB81))) -> 0 | AD81: =IF(AC81>0,AC81*V81,0) -> 0 | AE81: =IF(AC81>0,(M81-V81)*AC81,0) -> 0 | AF81: =IF(AA81<>"COMPRAR","",IF(AB81="",IF(X81="","",IF(X81-V81<0.01,"EMPATE TÉCNICO","")),IF(AB81<I81,"ESTOQUE INSUFICIENTE",IF(X81="","",IF(X81-V81<0.01,"EMPATE TÉCNICO",""))))) | AG81: NAZARIA DISTRIBUIDORA DE PRODUTOS FARMACEUTICOS LTDA | AH81: CURATIVO
A82: 608881 | B82: 7898108640678 | C82: CICATRISAN CURATIVO 10UN MICROPOROSO | D82: SANFARMA | E82: 1 | F82: B | G82: 1 | H82: 12.9 | I82: 33 | J82: 1.77 | K82: 1.77 | L82: 1.77 | M82: =IF(J82>0,J82,K82)*E82 -> 1.77 | N82: 2.11 | O82: =IF(R82="","",ROUND(R82*(1-Premissas!$B$4),4)) -> 2.2135 | R82: 2.33 | S82: 1582 | T82: 80 | U82: 164 | V82: =IF(COUNT(N82:Q82)=0,"",MIN(N82:Q82)) -> 2.11 | W82: =IF(V82="","",INDEX($N$4:$Q$4,MATCH(V82,N82:Q82,0))) -> DIMEC | X82: =IF(COUNT(N82:Q82)<2,"",SMALL(N82:Q82,2)) -> 2.2135 | Y82: =IF(OR(V82="",M82=0),"",V82/M82-1) -> 0.1920904 | Z82: =IF(OR(V82="",L82=""),"",V82/(L82*E82)-1) -> 0.1920904 | AA82: =IF(V82="","SEM OFERTA",IF(OR(Y82>Premissas!$B$11,Y82<Premissas!$B$12),"VERIFICAR - UNIDADE/EMBALAGEM",IF(Y82>Premissas!$B$6,"NÃO COMPRAR - REAJUSTE >5%","COMPRAR"))) -> NÃO COMPRAR - REAJUSTE >5% | AB82: =IF(W82="DIMEC",S82,IF(W82="MEDCENTRO",U82,"")) -> 1582 | AC82: =IF(AA82<>"COMPRAR",0,IF(AB82="",I82,MIN(I82,AB82))) -> 0 | AD82: =IF(AC82>0,AC82*V82,0) -> 0 | AE82: =IF(AC82>0,(M82-V82)*AC82,0) -> 0 | AF82: =IF(AA82<>"COMPRAR","",IF(AB82="",IF(X82="","",IF(X82-V82<0.01,"EMPATE TÉCNICO","")),IF(AB82<I82,"ESTOQUE INSUFICIENTE",IF(X82="","",IF(X82-V82<0.01,"EMPATE TÉCNICO",""))))) | AG82: DSC DISTRIBUIDORA DE MEDICAMENTOS LTDA | AH82: CURATIVO
A83: 594911 | B83: 7898108640739 | C83: CICATRISAN CURATIVO UNIDADE | E83: 1 | F83: C | G83: 0 | H83: 0.2 | I83: 1 | J83: 4.45 | K83: 4.45 | L83: 4.45 | M83: =IF(J83>0,J83,K83)*E83 -> 4.45 | N83: 5.22 | O83: =IF(R83="","",ROUND(R83*(1-Premissas!$B$4),4)) -> 5.434 | R83: 5.72 | S83: 655 | T83: 40 | U83: 244 | V83: =IF(COUNT(N83:Q83)=0,"",MIN(N83:Q83)) -> 5.22 | W83: =IF(V83="","",INDEX($N$4:$Q$4,MATCH(V83,N83:Q83,0))) -> DIMEC | X83: =IF(COUNT(N83:Q83)<2,"",SMALL(N83:Q83,2)) -> 5.434 | Y83: =IF(OR(V83="",M83=0),"",V83/M83-1) -> 0.17303371 | Z83: =IF(OR(V83="",L83=""),"",V83/(L83*E83)-1) -> 0.17303371 | AA83: =IF(V83="","SEM OFERTA",IF(OR(Y83>Premissas!$B$11,Y83<Premissas!$B$12),"VERIFICAR - UNIDADE/EMBALAGEM",IF(Y83>Premissas!$B$6,"NÃO COMPRAR - REAJUSTE >5%","COMPRAR"))) -> NÃO COMPRAR - REAJUSTE >5% | AB83: =IF(W83="DIMEC",S83,IF(W83="MEDCENTRO",U83,"")) -> 655 | AC83: =IF(AA83<>"COMPRAR",0,IF(AB83="",I83,MIN(I83,AB83))) -> 0 | AD83: =IF(AC83>0,AC83*V83,0) -> 0 | AE83: =IF(AC83>0,(M83-V83)*AC83,0) -> 0 | AF83: =IF(AA83<>"COMPRAR","",IF(AB83="",IF(X83="","",IF(X83-V83<0.01,"EMPATE TÉCNICO","")),IF(AB83<I83,"ESTOQUE INSUFICIENTE",IF(X83="","",IF(X83-V83<0.01,"EMPATE TÉCNICO",""))))) | AG83: NAZARIA DISTRIBUIDORA DE PRODUTOS FARMACEUTICOS LTDA | AH83: CURATIVO
A84: 596581 | B84: 7898933598151 | C84: COMPRESSA GAZE 11 FIOS C/10 UN TEXPHARMA | D84: TEXPHARMA | E84: 1 | F84: C | G84: 0 | H84: 0.1 | I84: 1 | J84: 0.56 | K84: 0.56 | L84: 0.56 | M84: =IF(J84>0,J84,K84)*E84 -> 0.56 | N84: 0.56 | O84: =IF(R84="","",ROUND(R84*(1-Premissas!$B$4),4)) | S84: 21392 | T84: 300 | V84: =IF(COUNT(N84:Q84)=0,"",MIN(N84:Q84)) -> 0.56 | W84: =IF(V84="","",INDEX($N$4:$Q$4,MATCH(V84,N84:Q84,0))) -> DIMEC | X84: =IF(COUNT(N84:Q84)<2,"",SMALL(N84:Q84,2)) | Y84: =IF(OR(V84="",M84=0),"",V84/M84-1) -> 0 | Z84: =IF(OR(V84="",L84=""),"",V84/(L84*E84)-1) -> 0 | AA84: =IF(V84="","SEM OFERTA",IF(OR(Y84>Premissas!$B$11,Y84<Premissas!$B$12),"VERIFICAR - UNIDADE/EMBALAGEM",IF(Y84>Premissas!$B$6,"NÃO COMPRAR - REAJUSTE >5%","COMPRAR"))) -> COMPRAR | AB84: =IF(W84="DIMEC",S84,IF(W84="MEDCENTRO",U84,"")) -> 21392 | AC84: =IF(AA84<>"COMPRAR",0,IF(AB84="",I84,MIN(I84,AB84))) -> 1 | AD84: =IF(AC84>0,AC84*V84,0) -> 0.56 | AE84: =IF(AC84>0,(M84-V84)*AC84,0) -> 0 | AF84: =IF(AA84<>"COMPRAR","",IF(AB84="",IF(X84="","",IF(X84-V84<0.01,"EMPATE TÉCNICO","")),IF(AB84<I84,"ESTOQUE INSUFICIENTE",IF(X84="","",IF(X84-V84<0.01,"EMPATE TÉCNICO",""))))) | AG84: DSC DISTRIBUIDORA DE MEDICAMENTOS LTDA | AH84: CURATIVO
A85: 648311 | B85: 7898108640104 | C85: COMPRESSA GAZES 11FIOS ESTER 10UN | D85: SANFARMA | E85: 1 | F85: C | G85: 0 | H85: 6.4 | I85: 17 | J85: 1.1616667 | K85: 1.1616667 | L85: 1.1617 | M85: =IF(J85>0,J85,K85)*E85 -> 1.1616667 | O85: =IF(R85="","",ROUND(R85*(1-Premissas!$B$4),4)) -> 1.254 | R85: 1.32 | U85: 15825 | V85: =IF(COUNT(N85:Q85)=0,"",MIN(N85:Q85)) -> 1.254 | W85: =IF(V85="","",INDEX($N$4:$Q$4,MATCH(V85,N85:Q85,0))) -> MEDCENTRO | X85: =IF(COUNT(N85:Q85)<2,"",SMALL(N85:Q85,2)) | Y85: =IF(OR(V85="",M85=0),"",V85/M85-1) -> 0.079483501 | Z85: =IF(OR(V85="",L85=""),"",V85/(L85*E85)-1) -> 0.079452526 | AA85: =IF(V85="","SEM OFERTA",IF(OR(Y85>Premissas!$B$11,Y85<Premissas!$B$12),"VERIFICAR - UNIDADE/EMBALAGEM",IF(Y85>Premissas!$B$6,"NÃO COMPRAR - REAJUSTE >5%","COMPRAR"))) -> NÃO COMPRAR - REAJUSTE >5% | AB85: =IF(W85="DIMEC",S85,IF(W85="MEDCENTRO",U85,"")) -> 15825 | AC85: =IF(AA85<>"COMPRAR",0,IF(AB85="",I85,MIN(I85,AB85))) -> 0 | AD85: =IF(AC85>0,AC85*V85,0) -> 0 | AE85: =IF(AC85>0,(M85-V85)*AC85,0) -> 0 | AF85: =IF(AA85<>"COMPRAR","",IF(AB85="",IF(X85="","",IF(X85-V85<0.01,"EMPATE TÉCNICO","")),IF(AB85<I85,"ESTOQUE INSUFICIENTE",IF(X85="","",IF(X85-V85<0.01,"EMPATE TÉCNICO",""))))) | AG85: NAZARIA DISTRIBUIDORA DE PRODUTOS FARMACEUTICOS LTDA | AH85: CURATIVO
A86: 647131 | B86: 7898136150583 | C86: CURATIVO ADESIVO NATHY BEGE 16UND | D86: NATHY | E86: 1 | F86: C | G86: 0 | H86: 1.1 | I86: 3 | J86: 2 | K86: 2 | L86: 2 | M86: =IF(J86>0,J86,K86)*E86 -> 2 | N86: 1.49 | O86: =IF(R86="","",ROUND(R86*(1-Premissas!$B$4),4)) | S86: 17 | T86: 48 | V86: =IF(COUNT(N86:Q86)=0,"",MIN(N86:Q86)) -> 1.49 | W86: =IF(V86="","",INDEX($N$4:$Q$4,MATCH(V86,N86:Q86,0))) -> DIMEC | X86: =IF(COUNT(N86:Q86)<2,"",SMALL(N86:Q86,2)) | Y86: =IF(OR(V86="",M86=0),"",V86/M86-1) -> -0.255 | Z86: =IF(OR(V86="",L86=""),"",V86/(L86*E86)-1) -> -0.255 | AA86: =IF(V86="","SEM OFERTA",IF(OR(Y86>Premissas!$B$11,Y86<Premissas!$B$12),"VERIFICAR - UNIDADE/EMBALAGEM",IF(Y86>Premissas!$B$6,"NÃO COMPRAR - REAJUSTE >5%","COMPRAR"))) -> COMPRAR | AB86: =IF(W86="DIMEC",S86,IF(W86="MEDCENTRO",U86,"")) -> 17 | AC86: =IF(AA86<>"COMPRAR",0,IF(AB86="",I86,MIN(I86,AB86))) -> 3 | AD86: =IF(AC86>0,AC86*V86,0) -> 4.47 | AE86: =IF(AC86>0,(M86-V86)*AC86,0) -> 1.53 | AF86: =IF(AA86<>"COMPRAR","",IF(AB86="",IF(X86="","",IF(X86-V86<0.01,"EMPATE TÉCNICO","")),IF(AB86<I86,"ESTOQUE INSUFICIENTE",IF(X86="","",IF(X86-V86<0.01,"EMPATE TÉCNICO",""))))) | AG86: SUPERGIRO DISTRIBUIDORA BELEM LTDA | AH86: CURATIVO
A87: 647121 | B87: 7898136150576 | C87: CURATIVO ADESIVO NATHY TRANSPARENTE 16UN | D87: NATHY | E87: 1 | F87: C | G87: 0 | H87: 0.4 | I87: 2 | J87: 2 | K87: 2 | L87: 2 | M87: =IF(J87>0,J87,K87)*E87 -> 2 | N87: 1.49 | O87: =IF(R87="","",ROUND(R87*(1-Premissas!$B$4),4)) | S87: 3 | T87: 48 | V87: =IF(COUNT(N87:Q87)=0,"",MIN(N87:Q87)) -> 1.49 | W87: =IF(V87="","",INDEX($N$4:$Q$4,MATCH(V87,N87:Q87,0))) -> DIMEC | X87: =IF(COUNT(N87:Q87)<2,"",SMALL(N87:Q87,2)) | Y87: =IF(OR(V87="",M87=0),"",V87/M87-1) -> -0.255 | Z87: =IF(OR(V87="",L87=""),"",V87/(L87*E87)-1) -> -0.255 | AA87: =IF(V87="","SEM OFERTA",IF(OR(Y87>Premissas!$B$11,Y87<Premissas!$B$12),"VERIFICAR - UNIDADE/EMBALAGEM",IF(Y87>Premissas!$B$6,"NÃO COMPRAR - REAJUSTE >5%","COMPRAR"))) -> COMPRAR | AB87: =IF(W87="DIMEC",S87,IF(W87="MEDCENTRO",U87,"")) -> 3 | AC87: =IF(AA87<>"COMPRAR",0,IF(AB87="",I87,MIN(I87,AB87))) -> 2 | AD87: =IF(AC87>0,AC87*V87,0) -> 2.98 | AE87: =IF(AC87>0,(M87-V87)*AC87,0) -> 1.02 | AF87: =IF(AA87<>"COMPRAR","",IF(AB87="",IF(X87="","",IF(X87-V87<0.01,"EMPATE TÉCNICO","")),IF(AB87<I87,"ESTOQUE INSUFICIENTE",IF(X87="","",IF(X87-V87<0.01,"EMPATE TÉCNICO",""))))) | AG87: SUPERGIRO DISTRIBUIDORA BELEM LTDA | AH87: CURATIVO
A88: 598531 | B88: 7898108640685 | C88: CURATIVO CICATRISAN COR DE PELE CX 10 UND | E88: 1 | F88: A | G88: 3 | H88: 18.6 | I88: 45 | J88: 1.79 | K88: 1.79 | L88: 1.79 | M88: =IF(J88>0,J88,K88)*E88 -> 1.79 | N88: 2.01 | O88: =IF(R88="","",ROUND(R88*(1-Premissas!$B$4),4)) -> 2.223 | R88: 2.34 | S88: 2405 | T88: 80 | U88: 338 | V88: =IF(COUNT(N88:Q88)=0,"",MIN(N88:Q88)) -> 2.01 | W88: =IF(V88="","",INDEX($N$4:$Q$4,MATCH(V88,N88:Q88,0))) -> DIMEC | X88: =IF(COUNT(N88:Q88)<2,"",SMALL(N88:Q88,2)) -> 2.223 | Y88: =IF(OR(V88="",M88=0),"",V88/M88-1) -> 0.12290503 | Z88: =IF(OR(V88="",L88=""),"",V88/(L88*E88)-1) -> 0.12290503 | AA88: =IF(V88="","SEM OFERTA",IF(OR(Y88>Premissas!$B$11,Y88<Premissas!$B$12),"VERIFICAR - UNIDADE/EMBALAGEM",IF(Y88>Premissas!$B$6,"NÃO COMPRAR - REAJUSTE >5%","COMPRAR"))) -> NÃO COMPRAR - REAJUSTE >5% | AB88: =IF(W88="DIMEC",S88,IF(W88="MEDCENTRO",U88,"")) -> 2405 | AC88: =IF(AA88<>"COMPRAR",0,IF(AB88="",I88,MIN(I88,AB88))) -> 0 | AD88: =IF(AC88>0,AC88*V88,0) -> 0 | AE88: =IF(AC88>0,(M88-V88)*AC88,0) -> 0 | AF88: =IF(AA88<>"COMPRAR","",IF(AB88="",IF(X88="","",IF(X88-V88<0.01,"EMPATE TÉCNICO","")),IF(AB88<I88,"ESTOQUE INSUFICIENTE",IF(X88="","",IF(X88-V88<0.01,"EMPATE TÉCNICO",""))))) | AG88: DSC DISTRIBUIDORA DE MEDICAMENTOS LTDA | AH88: CURATIVO
A89: 631611 | B89: 7896544925496 | C89: CURATIVO FLEXIVEL SHOW DA LUNA C/10UN. | D89: MISSNER | E89: 1 | F89: C | G89: 0 | H89: 2.7 | I89: 7 | J89: 3.06 | K89: 3.06 | L89: 3.06 | M89: =IF(J89>0,J89,K89)*E89 -> 3.06 | O89: =IF(R89="","",ROUND(R89*(1-Premissas!$B$4),4)) -> 2.6695 | R89: 2.81 | U89: 77 | V89: =IF(COUNT(N89:Q89)=0,"",MIN(N89:Q89)) -> 2.6695 | W89: =IF(V89="","",INDEX($N$4:$Q$4,MATCH(V89,N89:Q89,0))) -> MEDCENTRO | X89: =IF(COUNT(N89:Q89)<2,"",SMALL(N89:Q89,2)) | Y89: =IF(OR(V89="",M89=0),"",V89/M89-1) -> -0.12761438 | Z89: =IF(OR(V89="",L89=""),"",V89/(L89*E89)-1) -> -0.12761438 | AA89: =IF(V89="","SEM OFERTA",IF(OR(Y89>Premissas!$B$11,Y89<Premissas!$B$12),"VERIFICAR - UNIDADE/EMBALAGEM",IF(Y89>Premissas!$B$6,"NÃO COMPRAR - REAJUSTE >5%","COMPRAR"))) -> COMPRAR | AB89: =IF(W89="DIMEC",S89,IF(W89="MEDCENTRO",U89,"")) -> 77 | AC89: =IF(AA89<>"COMPRAR",0,IF(AB89="",I89,MIN(I89,AB89))) -> 7 | AD89: =IF(AC89>0,AC89*V89,0) -> 18.6865 | AE89: =IF(AC89>0,(M89-V89)*AC89,0) -> 2.7335 | AF89: =IF(AA89<>"COMPRAR","",IF(AB89="",IF(X89="","",IF(X89-V89<0.01,"EMPATE TÉCNICO","")),IF(AB89<I89,"ESTOQUE INSUFICIENTE",IF(X89="","",IF(X89-V89<0.01,"EMPATE TÉCNICO",""))))) | AG89: C & B LTDA | AH89: CURATIVO
A90: 4103 | B90: 7896544927230 | C90: CURATIVO HIDROCOLOIDE BOLHAS CALOS C/08 | E90: 1 | F90: C | G90: 0 | H90: 0.5 | I90: 2 | J90: 10.96 | K90: 10.96 | L90: 10.96 | M90: =IF(J90>0,J90,K90)*E90 -> 10.96 | N90: 10.96 | O90: =IF(R90="","",ROUND(R90*(1-Premissas!$B$4),4)) | S90: 23 | T90: 24 | V90: =IF(COUNT(N90:Q90)=0,"",MIN(N90:Q90)) -> 10.96 | W90: =IF(V90="","",INDEX($N$4:$Q$4,MATCH(V90,N90:Q90,0))) -> DIMEC | X90: =IF(COUNT(N90:Q90)<2,"",SMALL(N90:Q90,2)) | Y90: =IF(OR(V90="",M90=0),"",V90/M90-1) -> 0 | Z90: =IF(OR(V90="",L90=""),"",V90/(L90*E90)-1) -> 0 | AA90: =IF(V90="","SEM OFERTA",IF(OR(Y90>Premissas!$B$11,Y90<Premissas!$B$12),"VERIFICAR - UNIDADE/EMBALAGEM",IF(Y90>Premissas!$B$6,"NÃO COMPRAR - REAJUSTE >5%","COMPRAR"))) -> COMPRAR | AB90: =IF(W90="DIMEC",S90,IF(W90="MEDCENTRO",U90,"")) -> 23 | AC90: =IF(AA90<>"COMPRAR",0,IF(AB90="",I90,MIN(I90,AB90))) -> 2 | AD90: =IF(AC90>0,AC90*V90,0) -> 21.92 | AE90: =IF(AC90>0,(M90-V90)*AC90,0) -> 0 | AF90: =IF(AA90<>"COMPRAR","",IF(AB90="",IF(X90="","",IF(X90-V90<0.01,"EMPATE TÉCNICO","")),IF(AB90<I90,"ESTOQUE INSUFICIENTE",IF(X90="","",IF(X90-V90<0.01,"EMPATE TÉCNICO",""))))) | AG90: DSC DISTRIBUIDORA DE MEDICAMENTOS LTDA | AH90: CURATIVO
A91: 4033 | B91: 7896544901346 | C91: CURATIVO HIDROCOLOIDE P/ ACNES C/24 UND | E91: 1 | F91: A | G91: 1 | H91: 3.7 | I91: 9 | J91: 8.32 | K91: 8.32 | L91: 8.32 | M91: =IF(J91>0,J91,K91)*E91 -> 8.32 | N91: 8.32 | O91: =IF(R91="","",ROUND(R91*(1-Premissas!$B$4),4)) | S91: 77 | T91: 25 | V91: =IF(COUNT(N91:Q91)=0,"",MIN(N91:Q91)) -> 8.32 | W91: =IF(V91="","",INDEX($N$4:$Q$4,MATCH(V91,N91:Q91,0))) -> DIMEC | X91: =IF(COUNT(N91:Q91)<2,"",SMALL(N91:Q91,2)) | Y91: =IF(OR(V91="",M91=0),"",V91/M91-1) -> 0 | Z91: =IF(OR(V91="",L91=""),"",V91/(L91*E91)-1) -> 0 | AA91: =IF(V91="","SEM OFERTA",IF(OR(Y91>Premissas!$B$11,Y91<Premissas!$B$12),"VERIFICAR - UNIDADE/EMBALAGEM",IF(Y91>Premissas!$B$6,"NÃO COMPRAR - REAJUSTE >5%","COMPRAR"))) -> COMPRAR | AB91: =IF(W91="DIMEC",S91,IF(W91="MEDCENTRO",U91,"")) -> 77 | AC91: =IF(AA91<>"COMPRAR",0,IF(AB91="",I91,MIN(I91,AB91))) -> 9 | AD91: =IF(AC91>0,AC91*V91,0) -> 74.88 | AE91: =IF(AC91>0,(M91-V91)*AC91,0) -> 0 | AF91: =IF(AA91<>"COMPRAR","",IF(AB91="",IF(X91="","",IF(X91-V91<0.01,"EMPATE TÉCNICO","")),IF(AB91<I91,"ESTOQUE INSUFICIENTE",IF(X91="","",IF(X91-V91<0.01,"EMPATE TÉCNICO",""))))) | AG91: DSC DISTRIBUIDORA DE MEDICAMENTOS LTDA | AH91: CURATIVO
A92: 3243 | B92: 7898108640791 | C92: CURATIVO HIDROCOLOIDE SANCARE C/24 UND | D92: PADRAO | E92: 1 | F92: B | G92: 0 | H92: 2.6 | I92: 7 | J92: 14.93 | K92: 14.93 | L92: 14.93 | M92: =IF(J92>0,J92,K92)*E92 -> 14.93 | N92: 17.17 | O92: =IF(R92="","",ROUND(R92*(1-Premissas!$B$4),4)) | S92: 137 | T92: 40 | V92: =IF(COUNT(N92:Q92)=0,"",MIN(N92:Q92)) -> 17.17 | W92: =IF(V92="","",INDEX($N$4:$Q$4,MATCH(V92,N92:Q92,0))) -> DIMEC | X92: =IF(COUNT(N92:Q92)<2,"",SMALL(N92:Q92,2)) | Y92: =IF(OR(V92="",M92=0),"",V92/M92-1) -> 0.15003349 | Z92: =IF(OR(V92="",L92=""),"",V92/(L92*E92)-1) -> 0.15003349 | AA92: =IF(V92="","SEM OFERTA",IF(OR(Y92>Premissas!$B$11,Y92<Premissas!$B$12),"VERIFICAR - UNIDADE/EMBALAGEM",IF(Y92>Premissas!$B$6,"NÃO COMPRAR - REAJUSTE >5%","COMPRAR"))) -> NÃO COMPRAR - REAJUSTE >5% | AB92: =IF(W92="DIMEC",S92,IF(W92="MEDCENTRO",U92,"")) -> 137 | AC92: =IF(AA92<>"COMPRAR",0,IF(AB92="",I92,MIN(I92,AB92))) -> 0 | AD92: =IF(AC92>0,AC92*V92,0) -> 0 | AE92: =IF(AC92>0,(M92-V92)*AC92,0) -> 0 | AF92: =IF(AA92<>"COMPRAR","",IF(AB92="",IF(X92="","",IF(X92-V92<0.01,"EMPATE TÉCNICO","")),IF(AB92<I92,"ESTOQUE INSUFICIENTE",IF(X92="","",IF(X92-V92<0.01,"EMPATE TÉCNICO",""))))) | AG92: DSC DISTRIBUIDORA DE MEDICAMENTOS LTDA | AH92: CURATIVO
A93: 661581 | B93: 7898108642009 | C93: CURATIVO MICKEY E AMIGOS 20UN SANF %DN:2.00 | D93: SANFARMA | E93: 1 | F93: C | G93: 0 | H93: 0.4 | I93: 1 | J93: 5.88 | K93: 5.88 | L93: 5.88 | M93: =IF(J93>0,J93,K93)*E93 -> 5.88 | N93: 7.3 | O93: =IF(R93="","",ROUND(R93*(1-Premissas!$B$4),4)) -> 6.403 | R93: 6.74 | S93: 451 | T93: 40 | U93: 4 | V93: =IF(COUNT(N93:Q93)=0,"",MIN(N93:Q93)) -> 6.403 | W93: =IF(V93="","",INDEX($N$4:$Q$4,MATCH(V93,N93:Q93,0))) -> MEDCENTRO | X93: =IF(COUNT(N93:Q93)<2,"",SMALL(N93:Q93,2)) -> 7.3 | Y93: =IF(OR(V93="",M93=0),"",V93/M93-1) -> 0.088945578 | Z93: =IF(OR(V93="",L93=""),"",V93/(L93*E93)-1) -> 0.088945578 | AA93: =IF(V93="","SEM OFERTA",IF(OR(Y93>Premissas!$B$11,Y93<Premissas!$B$12),"VERIFICAR - UNIDADE/EMBALAGEM",IF(Y93>Premissas!$B$6,"NÃO COMPRAR - REAJUSTE >5%","COMPRAR"))) -> NÃO COMPRAR - REAJUSTE >5% | AB93: =IF(W93="DIMEC",S93,IF(W93="MEDCENTRO",U93,"")) -> 4 | AC93: =IF(AA93<>"COMPRAR",0,IF(AB93="",I93,MIN(I93,AB93))) -> 0 | AD93: =IF(AC93>0,AC93*V93,0) -> 0 | AE93: =IF(AC93>0,(M93-V93)*AC93,0) -> 0 | AF93: =IF(AA93<>"COMPRAR","",IF(AB93="",IF(X93="","",IF(X93-V93<0.01,"EMPATE TÉCNICO","")),IF(AB93<I93,"ESTOQUE INSUFICIENTE",IF(X93="","",IF(X93-V93<0.01,"EMPATE TÉCNICO",""))))) | AG93: NAZARIA DISTRIBUIDORA DE PRODUTOS FARMACEUTICOS LTDA | AH93: CURATIVO
A94: 5003 | B94: 7898108641989 | C94: CURATIVO MICKEY E MINNIE C/10 UND | D94: SANFARMA | E94: 1 | F94: B | G94: 0 | H94: 4.6 | I94: 12 | J94: 2.94 | K94: 2.94 | L94: 2.94 | M94: =IF(J94>0,J94,K94)*E94 -> 2.94 | N94: 3.23 | O94: =IF(R94="","",ROUND(R94*(1-Premissas!$B$4),4)) | S94: 759 | T94: 80 | V94: =IF(COUNT(N94:Q94)=0,"",MIN(N94:Q94)) -> 3.23 | W94: =IF(V94="","",INDEX($N$4:$Q$4,MATCH(V94,N94:Q94,0))) -> DIMEC | X94: =IF(COUNT(N94:Q94)<2,"",SMALL(N94:Q94,2)) | Y94: =IF(OR(V94="",M94=0),"",V94/M94-1) -> 0.098639456 | Z94: =IF(OR(V94="",L94=""),"",V94/(L94*E94)-1) -> 0.098639456 | AA94: =IF(V94="","SEM OFERTA",IF(OR(Y94>Premissas!$B$11,Y94<Premissas!$B$12),"VERIFICAR - UNIDADE/EMBALAGEM",IF(Y94>Premissas!$B$6,"NÃO COMPRAR - REAJUSTE >5%","COMPRAR"))) -> NÃO COMPRAR - REAJUSTE >5% | AB94: =IF(W94="DIMEC",S94,IF(W94="MEDCENTRO",U94,"")) -> 759 | AC94: =IF(AA94<>"COMPRAR",0,IF(AB94="",I94,MIN(I94,AB94))) -> 0 | AD94: =IF(AC94>0,AC94*V94,0) -> 0 | AE94: =IF(AC94>0,(M94-V94)*AC94,0) -> 0 | AF94: =IF(AA94<>"COMPRAR","",IF(AB94="",IF(X94="","",IF(X94-V94<0.01,"EMPATE TÉCNICO","")),IF(AB94<I94,"ESTOQUE INSUFICIENTE",IF(X94="","",IF(X94-V94<0.01,"EMPATE TÉCNICO",""))))) | AG94: DSC DISTRIBUIDORA DE MEDICAMENTOS LTDA | AH94: CURATIVO
A95: 656461 | B95: 7898136150620 | C95: CURATIVO NATHY C/35UN BEGE | D95: NATHY | E95: 1 | F95: A | G95: 0 | H95: 10.4 | I95: 27 | J95: 3.25 | K95: 3.25 | L95: 3.25 | M95: =IF(J95>0,J95,K95)*E95 -> 3.25 | N95: 3.25 | O95: =IF(R95="","",ROUND(R95*(1-Premissas!$B$4),4)) | S95: 23 | T95: 24 | V95: =IF(COUNT(N95:Q95)=0,"",MIN(N95:Q95)) -> 3.25 | W95: =IF(V95="","",INDEX($N$4:$Q$4,MATCH(V95,N95:Q95,0))) -> DIMEC | X95: =IF(COUNT(N95:Q95)<2,"",SMALL(N95:Q95,2)) | Y95: =IF(OR(V95="",M95=0),"",V95/M95-1) -> 0 | Z95: =IF(OR(V95="",L95=""),"",V95/(L95*E95)-1) -> 0 | AA95: =IF(V95="","SEM OFERTA",IF(OR(Y95>Premissas!$B$11,Y95<Premissas!$B$12),"VERIFICAR - UNIDADE/EMBALAGEM",IF(Y95>Premissas!$B$6,"NÃO COMPRAR - REAJUSTE >5%","COMPRAR"))) -> COMPRAR | AB95: =IF(W95="DIMEC",S95,IF(W95="MEDCENTRO",U95,"")) -> 23 | AC95: =IF(AA95<>"COMPRAR",0,IF(AB95="",I95,MIN(I95,AB95))) -> 23 | AD95: =IF(AC95>0,AC95*V95,0) -> 74.75 | AE95: =IF(AC95>0,(M95-V95)*AC95,0) -> 0 | AF95: =IF(AA95<>"COMPRAR","",IF(AB95="",IF(X95="","",IF(X95-V95<0.01,"EMPATE TÉCNICO","")),IF(AB95<I95,"ESTOQUE INSUFICIENTE",IF(X95="","",IF(X95-V95<0.01,"EMPATE TÉCNICO",""))))) -> ESTOQUE INSUFICIENTE | AG95: JLCS COMERCIO E DISTRIBUICAO DE ALIMENTO LTDA | AH95: CURATIVO
A96: 3433 | B96: 7898108640692 | C96: CURATIVO REDONDO CICATRISAN C/20 UND | E96: 1 | F96: C | G96: 1 | H96: 0.9 | I96: 2 | J96: 5.94 | K96: 5.94 | L96: 5.94 | M96: =IF(J96>0,J96,K96)*E96 -> 5.94 | N96: 5.42 | O96: =IF(R96="","",ROUND(R96*(1-Premissas!$B$4),4)) -> 5.5005 | R96: 5.79 | S96: 212 | T96: 40 | U96: 196 | V96: =IF(COUNT(N96:Q96)=0,"",MIN(N96:Q96)) -> 5.42 | W96: =IF(V96="","",INDEX($N$4:$Q$4,MATCH(V96,N96:Q96,0))) -> DIMEC | X96: =IF(COUNT(N96:Q96)<2,"",SMALL(N96:Q96,2)) -> 5.5005 | Y96: =IF(OR(V96="",M96=0),"",V96/M96-1) -> -0.087542088 | Z96: =IF(OR(V96="",L96=""),"",V96/(L96*E96)-1) -> -0.087542088 | AA96: =IF(V96="","SEM OFERTA",IF(OR(Y96>Premissas!$B$11,Y96<Premissas!$B$12),"VERIFICAR - UNIDADE/EMBALAGEM",IF(Y96>Premissas!$B$6,"NÃO COMPRAR - REAJUSTE >5%","COMPRAR"))) -> COMPRAR | AB96: =IF(W96="DIMEC",S96,IF(W96="MEDCENTRO",U96,"")) -> 212 | AC96: =IF(AA96<>"COMPRAR",0,IF(AB96="",I96,MIN(I96,AB96))) -> 2 | AD96: =IF(AC96>0,AC96*V96,0) -> 10.84 | AE96: =IF(AC96>0,(M96-V96)*AC96,0) -> 1.04 | AF96: =IF(AA96<>"COMPRAR","",IF(AB96="",IF(X96="","",IF(X96-V96<0.01,"EMPATE TÉCNICO","")),IF(AB96<I96,"ESTOQUE INSUFICIENTE",IF(X96="","",IF(X96-V96<0.01,"EMPATE TÉCNICO",""))))) | AG96: NAZARIA DISTRIBUIDORA DE PRODUTOS FARMACEUTICOS LTDA | AH96: CURATIVO
A97: 613791 | B97: 7896544900073 | C97: ESPARAD IMP MISSNER 1,2CMX4,5M | D97: MISSNER | E97: 1 | F97: A | G97: 1 | H97: 14.4 | I97: 36 | J97: 2.83 | K97: 2.83 | L97: 2.83 | M97: =IF(J97>0,J97,K97)*E97 -> 2.83 | N97: 2.83 | O97: =IF(R97="","",ROUND(R97*(1-Premissas!$B$4),4)) -> 3.3725 | R97: 3.55 | S97: 9853 | T97: 144 | U97: 1618 | V97: =IF(COUNT(N97:Q97)=0,"",MIN(N97:Q97)) -> 2.83 | W97: =IF(V97="","",INDEX($N$4:$Q$4,MATCH(V97,N97:Q97,0))) -> DIMEC | X97: =IF(COUNT(N97:Q97)<2,"",SMALL(N97:Q97,2)) -> 3.3725 | Y97: =IF(OR(V97="",M97=0),"",V97/M97-1) -> 0 | Z97: =IF(OR(V97="",L97=""),"",V97/(L97*E97)-1) -> 0 | AA97: =IF(V97="","SEM OFERTA",IF(OR(Y97>Premissas!$B$11,Y97<Premissas!$B$12),"VERIFICAR - UNIDADE/EMBALAGEM",IF(Y97>Premissas!$B$6,"NÃO COMPRAR - REAJUSTE >5%","COMPRAR"))) -> COMPRAR | AB97: =IF(W97="DIMEC",S97,IF(W97="MEDCENTRO",U97,"")) -> 9853 | AC97: =IF(AA97<>"COMPRAR",0,IF(AB97="",I97,MIN(I97,AB97))) -> 36 | AD97: =IF(AC97>0,AC97*V97,0) -> 101.88 | AE97: =IF(AC97>0,(M97-V97)*AC97,0) -> 0 | AF97: =IF(AA97<>"COMPRAR","",IF(AB97="",IF(X97="","",IF(X97-V97<0.01,"EMPATE TÉCNICO","")),IF(AB97<I97,"ESTOQUE INSUFICIENTE",IF(X97="","",IF(X97-V97<0.01,"EMPATE TÉCNICO",""))))) | AG97: NAZARIA DISTRIBUIDORA DE PRODUTOS FARMACEUTICOS LTDA | AH97: CURATIVO
A98: 540961 | B98: 7896544910102 | C98: ESPARADRAPO BRANCO 10 X 4,5 | D98: PADRAO | E98: 1 | F98: A | G98: 2 | H98: 4.8 | I98: 11 | J98: 12.33 | K98: 12.33 | L98: 12.32 | M98: =IF(J98>0,J98,K98)*E98 -> 12.33 | N98: 12.33 | O98: =IF(R98="","",ROUND(R98*(1-Premissas!$B$4),4)) -> 14.5255 | R98: 15.29 | S98: 4232 | T98: 24 | U98: 434 | V98: =IF(COUNT(N98:Q98)=0,"",MIN(N98:Q98)) -> 12.33 | W98: =IF(V98="","",INDEX($N$4:$Q$4,MATCH(V98,N98:Q98,0))) -> DIMEC | X98: =IF(COUNT(N98:Q98)<2,"",SMALL(N98:Q98,2)) -> 14.5255 | Y98: =IF(OR(V98="",M98=0),"",V98/M98-1) -> 0 | Z98: =IF(OR(V98="",L98=""),"",V98/(L98*E98)-1) -> 0.00081168831 | AA98: =IF(V98="","SEM OFERTA",IF(OR(Y98>Premissas!$B$11,Y98<Premissas!$B$12),"VERIFICAR - UNIDADE/EMBALAGEM",IF(Y98>Premissas!$B$6,"NÃO COMPRAR - REAJUSTE >5%","COMPRAR"))) -> COMPRAR | AB98: =IF(W98="DIMEC",S98,IF(W98="MEDCENTRO",U98,"")) -> 4232 | AC98: =IF(AA98<>"COMPRAR",0,IF(AB98="",I98,MIN(I98,AB98))) -> 11 | AD98: =IF(AC98>0,AC98*V98,0) -> 135.63 | AE98: =IF(AC98>0,(M98-V98)*AC98,0) -> 0 | AF98: =IF(AA98<>"COMPRAR","",IF(AB98="",IF(X98="","",IF(X98-V98<0.01,"EMPATE TÉCNICO","")),IF(AB98<I98,"ESTOQUE INSUFICIENTE",IF(X98="","",IF(X98-V98<0.01,"EMPATE TÉCNICO",""))))) | AG98: DSC DISTRIBUIDORA DE MEDICAMENTOS LTDA | AH98: CURATIVO
A99: 541301 | B99: 7896544925014 | C99: ESPARADRAPO IMP BRANCO 2,5CM X 0,90MTS UND QTD. 14.00 UN | D99: PADRAO | E99: 1 | F99: A | G99: 11 | H99: 22.8 | I99: 48 | J99: 2.15 | K99: 2.15 | L99: 2.15 | M99: =IF(J99>0,J99,K99)*E99 -> 2.15 | N99: 2.15 | O99: =IF(R99="","",ROUND(R99*(1-Premissas!$B$4),4)) -> 2.6125 | R99: 2.75 | S99: 14483 | T99: 204 | U99: 1272 | V99: =IF(COUNT(N99:Q99)=0,"",MIN(N99:Q99)) -> 2.15 | W99: =IF(V99="","",INDEX($N$4:$Q$4,MATCH(V99,N99:Q99,0))) -> DIMEC | X99: =IF(COUNT(N99:Q99)<2,"",SMALL(N99:Q99,2)) -> 2.6125 | Y99: =IF(OR(V99="",M99=0),"",V99/M99-1) -> 0 | Z99: =IF(OR(V99="",L99=""),"",V99/(L99*E99)-1) -> 0 | AA99: =IF(V99="","SEM OFERTA",IF(OR(Y99>Premissas!$B$11,Y99<Premissas!$B$12),"VERIFICAR - UNIDADE/EMBALAGEM",IF(Y99>Premissas!$B$6,"NÃO COMPRAR - REAJUSTE >5%","COMPRAR"))) -> COMPRAR | AB99: =IF(W99="DIMEC",S99,IF(W99="MEDCENTRO",U99,"")) -> 14483 | AC99: =IF(AA99<>"COMPRAR",0,IF(AB99="",I99,MIN(I99,AB99))) -> 48 | AD99: =IF(AC99>0,AC99*V99,0) -> 103.2 | AE99: =IF(AC99>0,(M99-V99)*AC99,0) -> 0 | AF99: =IF(AA99<>"COMPRAR","",IF(AB99="",IF(X99="","",IF(X99-V99<0.01,"EMPATE TÉCNICO","")),IF(AB99<I99,"ESTOQUE INSUFICIENTE",IF(X99="","",IF(X99-V99<0.01,"EMPATE TÉCNICO",""))))) | AG99: DSC DISTRIBUIDORA DE MEDICAMENTOS LTDA | AH99: CURATIVO
A100: 541421 | B100: 7896544925458 | C100: ESPARADRAPO IMP BRANCO 2,5CM X 4,5MTS UND QTD. 10.00 UN | D100: PADRAO | E100: 1 | F100: A | G100: 11 | H100: 40.6 | I100: 94 | J100: 3.71 | K100: 3.71 | L100: 3.71 | M100: =IF(J100>0,J100,K100)*E100 -> 3.71 | N100: 3.71 | O100: =IF(R100="","",ROUND(R100*(1-Premissas!$B$4),4)) -> 4.5505 | R100: 4.79 | S100: 17444 | T100: 96 | U100: 2253 | V100: =IF(COUNT(N100:Q100)=0,"",MIN(N100:Q100)) -> 3.71 | W100: =IF(V100="","",INDEX($N$4:$Q$4,MATCH(V100,N100:Q100,0))) -> DIMEC | X100: =IF(COUNT(N100:Q100)<2,"",SMALL(N100:Q100,2)) -> 4.5505 | Y100: =IF(OR(V100="",M100=0),"",V100/M100-1) -> 0 | Z100: =IF(OR(V100="",L100=""),"",V100/(L100*E100)-1) -> 0 | AA100: =IF(V100="","SEM OFERTA",IF(OR(Y100>Premissas!$B$11,Y100<Premissas!$B$12),"VERIFICAR - UNIDADE/EMBALAGEM",IF(Y100>Premissas!$B$6,"NÃO COMPRAR - REAJUSTE >5%","COMPRAR"))) -> COMPRAR | AB100: =IF(W100="DIMEC",S100,IF(W100="MEDCENTRO",U100,"")) -> 17444 | AC100: =IF(AA100<>"COMPRAR",0,IF(AB100="",I100,MIN(I100,AB100))) -> 94 | AD100: =IF(AC100>0,AC100*V100,0) -> 348.74 | AE100: =IF(AC100>0,(M100-V100)*AC100,0) -> 0 | AF100: =IF(AA100<>"COMPRAR","",IF(AB100="",IF(X100="","",IF(X100-V100<0.01,"EMPATE TÉCNICO","")),IF(AB100<I100,"ESTOQUE INSUFICIENTE",IF(X100="","",IF(X100-V100<0.01,"EMPATE TÉCNICO",""))))) | AG100: DSC DISTRIBUIDORA DE MEDICAMENTOS LTDA | AH100: CURATIVO
A101: 567761 | B101: 7896544900332 | C101: ESPARADRAPO IMPERM BEGE. 2,5CM X 4,5M | D101: MISSNER | E101: 1 | F101: B | G101: 0 | H101: 1.8 | I101: 5 | J101: 3.7 | K101: 3.7 | L101: 3.7 | M101: =IF(J101>0,J101,K101)*E101 -> 3.7 | N101: 3.7 | O101: =IF(R101="","",ROUND(R101*(1-Premissas!$B$4),4)) -> 4.4175 | R101: 4.65 | S101: 1179 | T101: 96 | U101: 118 | V101: =IF(COUNT(N101:Q101)=0,"",MIN(N101:Q101)) -> 3.7 | W101: =IF(V101="","",INDEX($N$4:$Q$4,MATCH(V101,N101:Q101,0))) -> DIMEC | X101: =IF(COUNT(N101:Q101)<2,"",SMALL(N101:Q101,2)) -> 4.4175 | Y101: =IF(OR(V101="",M101=0),"",V101/M101-1) -> 0 | Z101: =IF(OR(V101="",L101=""),"",V101/(L101*E101)-1) -> 0 | AA101: =IF(V101="","SEM OFERTA",IF(OR(Y101>Premissas!$B$11,Y101<Premissas!$B$12),"VERIFICAR - UNIDADE/EMBALAGEM",IF(Y101>Premissas!$B$6,"NÃO COMPRAR - REAJUSTE >5%","COMPRAR"))) -> COMPRAR | AB101: =IF(W101="DIMEC",S101,IF(W101="MEDCENTRO",U101,"")) -> 1179 | AC101: =IF(AA101<>"COMPRAR",0,IF(AB101="",I101,MIN(I101,AB101))) -> 5 | AD101: =IF(AC101>0,AC101*V101,0) -> 18.5 | AE101: =IF(AC101>0,(M101-V101)*AC101,0) -> 0 | AF101: =IF(AA101<>"COMPRAR","",IF(AB101="",IF(X101="","",IF(X101-V101<0.01,"EMPATE TÉCNICO","")),IF(AB101<I101,"ESTOQUE INSUFICIENTE",IF(X101="","",IF(X101-V101<0.01,"EMPATE TÉCNICO",""))))) | AG101: DSC DISTRIBUIDORA DE MEDICAMENTOS LTDA | AH101: CURATIVO
A102: 552501 | B102: 7896544910058 | C102: ESPARADRAPO IMPERM. BRANCO 5CMX4,5M | D102: PADRAO | E102: 1 | F102: A | G102: 15 | H102: 25.1 | I102: 50 | J102: 5.98 | K102: 5.98 | L102: 5.98 | M102: =IF(J102>0,J102,K102)*E102 -> 5.98 | N102: 5.98 | O102: =IF(R102="","",ROUND(R102*(1-Premissas!$B$4),4)) -> 7.1345 | R102: 7.51 | S102: 8969 | T102: 96 | U102: 1334 | V102: =IF(COUNT(N102:Q102)=0,"",MIN(N102:Q102)) -> 5.98 | W102: =IF(V102="","",INDEX($N$4:$Q$4,MATCH(V102,N102:Q102,0))) -> DIMEC | X102: =IF(COUNT(N102:Q102)<2,"",SMALL(N102:Q102,2)) -> 7.1345 | Y102: =IF(OR(V102="",M102=0),"",V102/M102-1) -> 0 | Z102: =IF(OR(V102="",L102=""),"",V102/(L102*E102)-1) -> 0 | AA102: =IF(V102="","SEM OFERTA",IF(OR(Y102>Premissas!$B$11,Y102<Premissas!$B$12),"VERIFICAR - UNIDADE/EMBALAGEM",IF(Y102>Premissas!$B$6,"NÃO COMPRAR - REAJUSTE >5%","COMPRAR"))) -> COMPRAR | AB102: =IF(W102="DIMEC",S102,IF(W102="MEDCENTRO",U102,"")) -> 8969 | AC102: =IF(AA102<>"COMPRAR",0,IF(AB102="",I102,MIN(I102,AB102))) -> 50 | AD102: =IF(AC102>0,AC102*V102,0) -> 299 | AE102: =IF(AC102>0,(M102-V102)*AC102,0) -> 0 | AF102: =IF(AA102<>"COMPRAR","",IF(AB102="",IF(X102="","",IF(X102-V102<0.01,"EMPATE TÉCNICO","")),IF(AB102<I102,"ESTOQUE INSUFICIENTE",IF(X102="","",IF(X102-V102<0.01,"EMPATE TÉCNICO",""))))) | AG102: DSC DISTRIBUIDORA DE MEDICAMENTOS LTDA | AH102: CURATIVO
...

Sheet Premissas
A1: Premissas e parâmetros da cotação
A3: Parâmetro | B3: Valor | C3: Observação / fonte
A4: Desconto adicional MEDCENTRO (sobre PRECO_FINAL) | B4: 0.05 | C4: Informado pelo usuário em 20/10/2026
A5: Preço DIMEC | B5: PRECO 2% = preço final | C5: Informado pelo usuário: já é preço final, sem ajuste
A6: Limite de reajuste aceito (vs. preço de referência) | B6: 0.05 | C6: Regra do usuário: sem compra em reajuste superior a 5%
A7: Preço de referência | B7: Últ. preço compra (se 0/vazio, usa Custo un da lista) | C7: Fonte: Lista_de_Compra_20261020_150341.xlsx
A8: Quantidade e preço SEMPRE POR CAIXA | B8: Qtd = Caixas da Lista; ref. caixa = preço unitário × Un/Cx; distribuidor não vende fração | C8: Instrução do usuário. Qtd limitada ao estoque do vencedor (em caixas). Palmed não informa estoque; Q.MÁX do encarte será aplicada
A9: Palmed CAST x MAB | B9: Mesmo distribuidor, 2 setores logísticos, preços distintos — colunas separadas | C9: Aguardando planilha de correlação COD Palmed x EAN
A10: Casamento de itens | B10: Somente por EAN (principal + 5 adicionais). Sem casamento por descrição. | C10: Instrução do usuário
A11: Suspeita de unidade/embalagem divergente (var. acima de) | B11: 1 | C11: Premissa da análise: preço ofertado > 2x a referência indica unidade diferente (caixa x unidade/flaconete) ou ref. bonificada (R$0,01) — conferir antes de decidir
A12: Suspeita de unidade divergente (var. abaixo de) | B12: -0.5 | C12: Premissa da análise: oferta < metade da referência por caixa — provável Un/Cx incorreto na lista
A15: Legenda: células amarelas com texto azul são parâmetros editáveis — alterar recalcula toda a cotação.

Sheet Pedido DIMEC
A1: PEDIDO DIMEC — 20/10/2026 (preço final)
A3: Cód. interno | B3: EAN | C3: Produto | D3: Fabricante | E3: ABC | F3: Dem./mês | G3: Preço ref. (cx) | H3: Melhor 3m (un) | I3: Preço ofertado (cx) | J3: Var. vs ref. | K3: Qtd pedido (cx) | L3: Valor pedido | M3: Economia | N3: Estoque forn. | O3: Alerta
A4: =Cotação!A647 -> 634551 | B4: =Cotação!B647 -> 7895143226942 | C4: =Cotação!C647 -> 5MAG 500MG 60CAPS QUALYNUTRI | D4: =Cotação!D647 -> QUALYNUTRI | E4: =Cotação!F647 -> A | F4: =Cotação!H647 -> 3.2 | G4: =Cotação!M647 -> 33.53 | H4: =Cotação!L647 -> 33.53 | I4: =Cotação!V647 -> 33.53 | J4: =Cotação!Y647 -> 0 | K4: =Cotação!AC647 -> 6 | L4: =Cotação!AD647 -> 201.18 | M4: =Cotação!AE647 -> 0 | N4: =Cotação!AB647 -> 191 | O4: =Cotação!AF647
A5: =Cotação!A136 -> 2081 | B5: =Cotação!B136 -> 7899620912731 | C5: =Cotação!C136 -> ACEBROFILINA 10MG/ML XPE FR 120ML+COP MED | D5: =Cotação!D136 -> GLOBO | E5: =Cotação!F136 -> C | F5: =Cotação!H136 -> 1.2 | G5: =Cotação!M136 -> 7.01 | H5: =Cotação!L136 -> 7.01 | I5: =Cotação!V136 -> 7.13 | J5: =Cotação!Y136 -> 0.017118402 | K5: =Cotação!AC136 -> 2 | L5: =Cotação!AD136 -> 14.26 | M5: =Cotação!AE136 -> -0.24 | N5: =Cotação!AB136 -> 878 | O5: =Cotação!AF136
A6: =Cotação!A139 -> 6261 | B6: =Cotação!B139 -> 7896006267072 | C6: =Cotação!C139 -> ACETATO DE HIDROCORTISONA 10MG CREME DERM BG 20G | D6: =Cotação!D139 -> UNIAO QUIMICA | E6: =Cotação!F139 -> B | F6: =Cotação!H139 -> 2.9 | G6: =Cotação!M139 -> 7.473 | H6: =Cotação!L139 -> 7.47 | I6: =Cotação!V139 -> 7.08 | J6: =Cotação!Y139 -> -0.052589322 | K6: =Cotação!AC139 -> 1 | L6: =Cotação!AD139 -> 7.08 | M6: =Cotação!AE139 -> 0.393 | N6: =Cotação!AB139 -> 1183 | O6: =Cotação!AF139
A7: =Cotação!A143 -> 469021 | B7: =Cotação!B143 -> 7896004712031 | C7: =Cotação!C143 -> ACETONIDO TRIANCINOLONA 1MG POM BG 10G | D7: =Cotação!D143 -> GERMED GENERICOS | E7: =Cotação!F143 -> B | F7: =Cotação!H143 -> 4.9 | G7: =Cotação!M143 -> 4.02 | H7: =Cotação!L143 -> 4.02 | I7: =Cotação!V143 -> 4.08 | J7: =Cotação!Y143 -> 0.014925373 | K7: =Cotação!AC143 -> 12 | L7: =Cotação!AD143 -> 48.96 | M7: =Cotação!AE143 -> -0.72 | N7: =Cotação!AB143 -> 1178 | O7: =Cotação!AF143
A8: =Cotação!A148 -> 11821 | B8: =Cotação!B148 -> 7896112128847 | C8: =Cotação!C148 -> ACICLOVIR 50MG/G CREME DERM BG 10G | D8: =Cotação!D148 -> TEUTO | E8: =Cotação!F148 -> A | F8: =Cotação!H148 -> 20.4 | G8: =Cotação!M148 -> 4.9 | H8: =Cotação!L148 -> 4.9 | I8: =Cotação!V148 -> 5.09 | J8: =Cotação!Y148 -> 0.03877551 | K8: =Cotação!AC148 -> 19 | L8: =Cotação!AD148 -> 96.71 | M8: =Cotação!AE148 -> -3.61 | N8: =Cotação!AB148 -> 9678 | O8: =Cotação!AF148
A9: =Cotação!A1047 -> 2953 | B9: =Cotação!B1047 -> 7898665751411 | C9: =Cotação!C1047 -> ACIDO HIALURONICO+VITAMINAS 75MG C/60 CP | D9: =Cotação!D1047 -> DUOM | E9: =Cotação!F1047 -> C | F9: =Cotação!H1047 -> 0.1 | G9: =Cotação!M1047 -> 37.67 | H9: =Cotação!L1047 -> 37.67 | I9: =Cotação!V1047 -> 39.01 | J9: =Cotação!Y1047 -> 0.035572073 | K9: =Cotação!AC1047 -> 1 | L9: =Cotação!AD1047 -> 39.01 | M9: =Cotação!AE1047 -> -1.34 | N9: =Cotação!AB1047 -> 13 | O9: =Cotação!AF1047
A10: =Cotação!A657 -> 541181 | B10: =Cotação!B657 -> 7898048691419 | C10: =Cotação!C657 -> AGUA FLOR DE LARANJEIRA 100ML | D10: =Cotação!D657 -> LAPON | E10: =Cotação!F657 -> C | F10: =Cotação!H657 -> 0.8 | G10: =Cotação!M657 -> 5.06 | H10: =Cotação!L657 -> 5.06 | I10: =Cotação!V657 -> 5.25 | J10: =Cotação!Y657 -> 0.037549407 | K10: =Cotação!AC657 -> 2 | L10: =Cotação!AD657 -> 10.5 | M10: =Cotação!AE657 -> -0.38 | N10: =Cotação!AB657 -> 2168 | O10: =Cotação!AF657
A11: =Cotação!A993 -> 631571 | B11: =Cotação!B993 -> 7898652371967 | C11: =Cotação!C993 -> AGULHA HIPODERMICA 30X0,70MM | D11: =Cotação!D993 -> 0 | E11: =Cotação!F993 -> C | F11: =Cotação!H993 -> 31.2 | G11: =Cotação!M993 -> 14 | H11: =Cotação!L993 -> 0.14 | I11: =Cotação!V993 -> 12.44 | J11: =Cotação!Y993 -> -0.11142857 | K11: =Cotação!AC993 -> 1 | L11: =Cotação!AD993 -> 12.44 | M11: =Cotação!AE993 -> 1.56 | N11: =Cotação!AB993 -> 971 | O11: =Cotação!AF993
A12: =Cotação!A69 -> 3233 | B12: =Cotação!B69 -> 7896902210479 | C12: =Cotação!C69 -> ALCOOL 70% 50ML | D12: =Cotação!D69 -> FARMAX | E12: =Cotação!F69 -> A | F12: =Cotação!H69 -> 35.9 | G12: =Cotação!M69 -> 2.42 | H12: =Cotação!L69 -> 2.38 | I12: =Cotação!V69 -> 2.37 | J12: =Cotação!Y69 -> -0.020661157 | K12: =Cotação!AC69 -> 57 | L12: =Cotação!AD69 -> 135.09 | M12: =Cotação!AE69 -> 2.85 | N12: =Cotação!AB69 -> 3735 | O12: =Cotação!AF69
A13: =Cotação!A71 -> 5043 | B13: =Cotação!B71 -> 7898031310877 | C13: =Cotação!C71 -> ALCOOL GEL 70% 50G UNISSEPT | D13: =Cotação!D71 -> UNIPHAR | E13: =Cotação!F71 -> B | F13: =Cotação!H71 -> 5.4 | G13: =Cotação!M71 -> 3.51 | H13: =Cotação!L71 -> 3.51 | I13: =Cotação!V71 -> 3.51 | J13: =Cotação!Y71 -> 0 | K13: =Cotação!AC71 -> 8 | L13: =Cotação!AD71 -> 28.08 | M13: =Cotação!AE71 -> 0 | N13: =Cotação!AB71 -> 219 | O13: =Cotação!AF71
A14: =Cotação!A660 -> 571901 | B14: =Cotação!B660 -> 7898582291694 | C14: =Cotação!C660 -> ALCOOL GEL 70% PERFUMAD COM MICROES 60ML | D14: =Cotação!D660 -> PAIXAO | E14: =Cotação!F660 -> B | F14: =Cotação!H660 -> 3.2 | G14: =Cotação!M660 -> 5.6 | H14: =Cotação!L660 -> 5.59 | I14: =Cotação!V660 -> 5.6 | J14: =Cotação!Y660 -> 0 | K14: =Cotação!AC660 -> 8 | L14: =Cotação!AD660 -> 44.8 | M14: =Cotação!AE660 -> 0 | N14: =Cotação!AB660 -> 199 | O14: =Cotação!AF660
A15: =Cotação!A985 -> 3453 | B15: =Cotação!B985 -> 7898206190044 | C15: =Cotação!C985 -> ALCOOL J FERES 70% 1 LITRO | D15: =Cotação!D985 -> 0 | E15: =Cotação!F985 -> C | F15: =Cotação!H985 -> 0.1 | G15: =Cotação!M985 -> 9.21 | H15: =Cotação!L985 -> 9.21 | I15: =Cotação!V985 -> 8.98 | J15: =Cotação!Y985 -> -0.024972856 | K15: =Cotação!AC985 -> 1 | L15: =Cotação!AD985 -> 8.98 | M15: =Cotação!AE985 -> 0.23 | N15: =Cotação!AB985 -> 4660 | O15: =Cotação!AF985
A16: =Cotação!A662 -> 331061 | B16: =Cotação!B662 -> 7896523209715 | C16: =Cotação!C662 -> ALERGOMINE 10MG/G CREME BG 30G | D16: =Cotação!D662 -> CIMED | E16: =Cotação!F662 -> C | F16: =Cotação!H662 -> 1.5 | G16: =Cotação!M662 -> 6.89 | H16: =Cotação!L662 -> 6.89 | I16: =Cotação!V662 -> 4.99 | J16: =Cotação!Y662 -> -0.27576197 | K16: =Cotação!AC662 -> 4 | L16: =Cotação!AD662 -> 19.96 | M16: =Cotação!AE662 -> 7.6 | N16: =Cotação!AB662 -> 7 | O16: =Cotação!AF662
A17: =Cotação!A547 -> 562421 | B17: =Cotação!B547 -> 7894488000019 | C17: =Cotação!C547 -> ALGODAO SPARTERX MULTIUSO 25G | D17: =Cotação!D547 -> COTTONBABY | E17: =Cotação!F547 -> B | F17: =Cotação!H547 -> 13.9 | G17: =Cotação!M547 -> 1.09 | H17: =Cotação!L547 -> 1.09 | I17: =Cotação!V547 -> 1.12 | J17: =Cotação!Y547 -> 0.027522936 | K17: =Cotação!AC547 -> 20 | L17: =Cotação!AD547 -> 22.4 | M17: =Cotação!AE547 -> -0.6 | N17: =Cotação!AB547 -> 7904 | O17: =Cotação!AF547
A18: =Cotação!A459 -> 32281 | B18: =Cotação!B459 -> 7896004709116 | C18: =Cotação!C459 -> AMOXICILINA 400MG SUS ORAL FR 100ML | D18: =Cotação!D459 -> GERMED GENERICOS | E18: =Cotação!F459 -> C | F18: =Cotação!H459 -> 0.1 | G18: =Cotação!M459 -> 18.96 | H18: =Cotação!L459 -> 18.96 | I18: =Cotação!V459 -> 19.87 | J18: =Cotação!Y459 -> 0.047995781 | K18: =Cotação!AC459 -> 1 | L18: =Cotação!AD459 -> 19.87 | M18: =Cotação!AE459 -> -0.91 | N18: =Cotação!AB459 -> 138 | O18: =Cotação!AF459
A19: =Cotação!A461 -> 33681 | B19: =Cotação!B461 -> 7896004710501 | C19: =Cotação!C461 -> AMOXICILINA 875MG CX 14 COMP REV | D19: =Cotação!D461 -> GERMED GENERICOS | E19: =Cotação!F461 -> C | F19: =Cotação!H461 -> 0.2 | G19: =Cotação!M461 -> 24.97 | H19: =Cotação!L461 -> 24.97 | I19: =Cotação!V461 -> 26.18 | J19: =Cotação!Y461 -> 0.04845815 | K19: =Cotação!AC461 -> 1 | L19: =Cotação!AD461 -> 26.18 | M19: =Cotação!AE461 -> -1.21 | N19: =Cotação!AB461 -> 94 | O19: =Cotação!AF461
A20: =Cotação!A1051 -> 547741 | B20: =Cotação!B1051 -> 7899620910584 | C20: =Cotação!C1051 -> APETISINA BC 240ML UVA | D20: =Cotação!D1051 -> GLOBO | E20: =Cotação!F1051 -> C | F20: =Cotação!H1051 -> 1.2 | G20: =Cotação!M1051 -> 5.29 | H20: =Cotação!L1051 -> 5.29 | I20: =Cotação!V1051 -> 5.49 | J20: =Cotação!Y1051 -> 0.037807183 | K20: =Cotação!AC1051 -> 1 | L20: =Cotação!AD1051 -> 5.49 | M20: =Cotação!AE1051 -> -0.2 | N20: =Cotação!AB1051 -> 130 | O20: =Cotação!AF1051
A21: =Cotação!A126 -> 274861 | B21: =Cotação!B126 -> 7898133136757 | C21: =Cotação!C126 -> ARLIVRY 7 MG/ML XPE CT FR PLAS AMB X 100 ML + CP MED (SABOR MEL) | D21: =Cotação!D126 -> NATULAB LABORATORIO | E21: =Cotação!F126 -> C | F21: =Cotação!H126 -> 0.9 | G21: =Cotação!M126 -> 8.62 | H21: =Cotação!L126 -> 8.62 | I21: =Cotação!V126 -> 8.62 | J21: =Cotação!Y126 -> 0 | K21: =Cotação!AC126 -> 3 | L21: =Cotação!AD126 -> 25.86 | M21: =Cotação!AE126 -> 0 | N21: =Cotação!AB126 -> 1732 | O21: =Cotação!AF126
A22: =Cotação!A73 -> 597791 | B22: =Cotação!B73 -> 7898933598625 | C22: =Cotação!C73 -> ATADURA DE CREPE 06CM UND | D22: =Cotação!D73 -> TEXPHARMA | E22: =Cotação!F73 -> A | F22: =Cotação!H73 -> 38.3 | G22: =Cotação!M73 -> 5.99 | H22: =Cotação!L73 -> 0.4992 | I22: =Cotação!V73 -> 5.25 | J22: =Cotação!Y73 -> -0.12353923 | K22: =Cotação!AC73 -> 9 | L22: =Cotação!AD73 -> 47.25 | M22: =Cotação!AE73 -> 6.66 | N22: =Cotação!AB73 -> 773 | O22: =Cotação!AF73
A23: =Cotação!A74 -> 623471 | B23: =Cotação!B74 -> 7898933598755 | C23: =Cotação!C74 -> ATADURA DE CREPE 15CM C/12 UND | D23: =Cotação!D74 -> TEXPHARMA | E23: =Cotação!F74 -> A | F23: =Cotação!H74 -> 56.9 | G23: =Cotação!M74 -> 9.82 | H23: =Cotação!L74 -> 0.8183 | I23: =Cotação!V74 -> 9.82 | J23: =Cotação!Y74 -> 0 | K23: =Cotação!AC74 -> 13 | L23: =Cotação!AD74 -> 127.66 | M23: =Cotação!AE74 -> 0 | N23: =Cotação!AB74 -> 509 | O23: =Cotação!AF74
A24: =Cotação!A75 -> 613211 | B24: =Cotação!B75 -> 7898933598786 | C24: =Cotação!C75 -> ATADURA DE CREPE 30CM C/12 UND | D24: =Cotação!D75 -> TEXPHARMA | E24: =Cotação!F75 -> A | F24: =Cotação!H75 -> 21.1 | G24: =Cotação!M75 -> 19.67 | H24: =Cotação!L75 -> 1.6392 | I24: =Cotação!V75 -> 19.67 | J24: =Cotação!Y75 -> 0 | K24: =Cotação!AC75 -> 3 | L24: =Cotação!AD75 -> 59.01 | M24: =Cotação!AE75 -> 0 | N24: =Cotação!AB75 -> 49 | O24: =Cotação!AF75
A25: =Cotação!A160 -> 25603 | B25: =Cotação!B160 -> 7898049799213 | C25: =Cotação!C160 -> ATENOLOL+CLORTALIDONA 50,0+12,5MG CX 30 COMP | D25: =Cotação!D160 -> VITAMEDIC | E25: =Cotação!F160 -> C | F25: =Cotação!H160 -> 1.4 | G25: =Cotação!M160 -> 7.15 | H25: =Cotação!L160 -> 7.15 | I25: =Cotação!V160 -> 6.26 | J25: =Cotação!Y160 -> -0.12447552 | K25: =Cotação!AC160 -> 3 | L25: =Cotação!AD160 -> 18.78 | M25: =Cotação!AE160 -> 2.67 | N25: =Cotação!AB160 -> 125 | O25: =Cotação!AF160
A26: =Cotação!A163 -> 43721 | B26: =Cotação!B163 -> 7895296087131 | C26: =Cotação!C163 -> ATORVASTATINA CALCICA 40MG CX 30 COMP REV | D26: =Cotação!D163 -> NOVA QUIMICA GENERICOS | E26: =Cotação!F163 -> C | F26: =Cotação!H163 -> 0.2 | G26: =Cotação!M163 -> 25.74 | H26: =Cotação!L163 -> 25.74 | I26: =Cotação!V163 -> 14.94 | J26: =Cotação!Y163 -> -0.41958042 | K26: =Cotação!AC163 -> 1 | L26: =Cotação!AD163 -> 14.94 | M26: =Cotação!AE163 -> 10.8 | N26: =Cotação!AB163 -> 2 | O26: =Cotação!AF163
A27: =Cotação!A997 -> 648171 | B27: =Cotação!B997 -> 7908007905478 | C27: =Cotação!C997 -> AUTOTESTE COVID-19 AG (TESTE RAPIDO) | D27: =Cotação!D997 -> G-TECH | E27: =Cotação!F997 -> C | F27: =Cotação!H997 -> 0.2 | G27: =Cotação!M997 -> 8.29 | H27: =Cotação!L997 -> 8.29 | I27: =Cotação!V997 -> 8.29 | J27: =Cotação!Y997 -> 0 | K27: =Cotação!AC997 -> 1 | L27: =Cotação!AD997 -> 8.29 | M27: =Cotação!AE997 -> 0 | N27: =Cotação!AB997 -> 89 | O27: =Cotação!AF997
A28: =Cotação!A670 -> 547701 | B28: =Cotação!B670 -> 7898031310686 | C28: =Cotação!C670 -> AZEITE DOCE (OLEO DOCE) 30ML | D28: =Cotação!D670 -> UNIPHAR | E28: =Cotação!F670 -> B | F28: =Cotação!H670 -> 3 | G28: =Cotação!M670 -> 3.61 | H28: =Cotação!L670 -> 3.61 | I28: =Cotação!V670 -> 3.61 | J28: =Cotação!Y670 -> 0 | K28: =Cotação!AC670 -> 5 | L28: =Cotação!AD670 -> 18.05 | M28: =Cotação!AE670 -> 0 | N28: =Cotação!AB670 -> 1815 | O28: =Cotação!AF670
A29: =Cotação!A672 -> 532681 | B29: =Cotação!B672 -> 7899470805726 | C29: =Cotação!C672 -> BABY D PDA NATULAB 45GRS | D29: =Cotação!D672 -> NATULAB LABORATORIO | E29: =Cotação!F672 -> C | F29: =Cotação!H672 -> 0.2 | G29: =Cotação!M672 -> 6.59 | H29: =Cotação!L672 -> 6.59 | I29: =Cotação!V672 -> 4.49 | J29: =Cotação!Y672 -> -0.31866464 | K29: =Cotação!AC672 -> 1 | L29: =Cotação!AD672 -> 4.49 | M29: =Cotação!AE672 -> 2.1 | N29: =Cotação!AB672 -> 16 | O29: =Cotação!AF672
A30: =Cotação!A998 -> 674731 | B30: =Cotação!B998 -> 7898582292332 | C30: =Cotação!C998 -> BALSAMO CANELA VELHO DOUTOR HOUSE 120ML | D30: =Cotação!D998 -> 0 | E30: =Cotação!F998 -> C | F30: =Cotação!H998 -> 1 | G30: =Cotação!M998 -> 10.99 | H30: =Cotação!L998 -> 10.99 | I30: =Cotação!V998 -> 10.99 | J30: =Cotação!Y998 -> 0 | K30: =Cotação!AC998 -> 3 | L30: =Cotação!AD998 -> 32.97 | M30: =Cotação!AE998 -> 0 | N30: =Cotação!AB998 -> 79 | O30: =Cotação!AF998
A31: =Cotação!A525 -> 541321 | B31: =Cotação!B525 -> 7898563802468 | C31: =Cotação!C525 -> BATOM DE CACAU UN | D31: =Cotação!D525 -> TROL | E31: =Cotação!F525 -> B | F31: =Cotação!H525 -> 13.9 | G31: =Cotação!M525 -> 1.61 | H31: =Cotação!L525 -> 1.61 | I31: =Cotação!V525 -> 1.61 | J31: =Cotação!Y525 -> 0 | K31: =Cotação!AC525 -> 18 | L31: =Cotação!AD525 -> 28.98 | M31: =Cotação!AE525 -> 0 | N31: =Cotação!AB525 -> 1004 | O31: =Cotação!AF525
A32: =Cotação!A676 -> 590701 | B32: =Cotação!B676 -> 7898031310075 | C32: =Cotação!C676 -> BAZELIN 10G UN | D32: =Cotação!D676 -> UNIPHAR | E32: =Cotação!F676 -> B | F32: =Cotação!H676 -> 5.8 | G32: =Cotação!M676 -> 3.81 | H32: =Cotação!L676 -> 3.79 | I32: =Cotação!V676 -> 3.81 | J32: =Cotação!Y676 -> 0 | K32: =Cotação!AC676 -> 14 | L32: =Cotação!AD676 -> 53.34 | M32: =Cotação!AE676 -> 0 | N32: =Cotação!AB676 -> 1728 | O32: =Cotação!AF676
A33: =Cotação!A681 -> 49581 | B33: =Cotação!B681 -> 7898014560077 | C33: =Cotação!C681 -> BENZODERM 100 MG/G SAB CT FIL PP X 60 G | D33: =Cotação!D681 -> PHARMASCIENCE INDUSTRIA FARMACEUTICA | E33: =Cotação!F681 -> C | F33: =Cotação!H681 -> 1 | G33: =Cotação!M681 -> 6.59 | H33: =Cotação!L681 -> 6.59 | I33: =Cotação!V681 -> 6.59 | J33: =Cotação!Y681 -> 0 | K33: =Cotação!AC681 -> 3 | L33: =Cotação!AD681 -> 19.77 | M33: =Cotação!AE681 -> 0 | N33: =Cotação!AB681 -> 738 | O33: =Cotação!AF681
A34: =Cotação!A165 -> 50281 | B34: =Cotação!B165 -> 7899095238473 | C34: =Cotação!C165 -> BESILATO DE ANLODIPINO 10MG CX 30 COMP | D34: =Cotação!D165 -> GEOLAB | E34: =Cotação!F165 -> B | F34: =Cotação!H165 -> 4.7 | G34: =Cotação!M165 -> 3.88 | H34: =Cotação!L165 -> 3.65 | I34: =Cotação!V165 -> 3.89 | J34: =Cotação!Y165 -> 0.0025773196 | K34: =Cotação!AC165 -> 11 | L34: =Cotação!AD165 -> 42.79 | M34: =Cotação!AE165 -> -0.11 | N34: =Cotação!AB165 -> 669 | O34: =Cotação!AF165
A35: =Cotação!A472 -> 611641 | B35: =Cotação!B472 -> 7896006201182 | C35: =Cotação!C472 -> BETAMETASONA+CLIOQUINOL+SULFATO DE GENTAMICINA+TOLNAFATO CREM DERM BG 20G | D35: =Cotação!D472 -> UNIAO QUIMICA | E35: =Cotação!F472 -> B | F35: =Cotação!H472 -> 2.5 | G35: =Cotação!M472 -> 8.865 | H35: =Cotação!L472 -> 8.86 | I35: =Cotação!V472 -> 9.21 | J35: =Cotação!Y472 -> 0.03891709 | K35: =Cotação!AC472 -> 3 | L35: =Cotação!AD472 -> 27.63 | M35: =Cotação!AE472 -> -1.035 | N35: =Cotação!AB472 -> 87 | O35: =Cotação!AF472
A36: =Cotação!A954 -> 449241 | B36: =Cotação!B954 -> 7899095204430 | C36: =Cotação!C954 -> BETOGENTA 0,5+1,0MG POM BG 30G | D36: =Cotação!D954 -> GEOLAB | E36: =Cotação!F954 -> A | F36: =Cotação!H954 -> 6.7 | G36: =Cotação!M954 -> 7.83 | H36: =Cotação!L954 -> 7.83 | I36: =Cotação!V954 -> 8.15 | J36: =Cotação!Y954 -> 0.040868455 | K36: =Cotação!AC954 -> 3 | L36: =Cotação!AD954 -> 24.45 | M36: =Cotação!AE954 -> -0.96 | N36: =Cotação!AB954 -> 4161 | O36: =Cotação!AF954
A37: =Cotação!A21 -> 619101 | B37: =Cotação!B21 -> 7898953484243 | C37: =Cotação!C21 -> BICO P/ SERINGA DE LAVAGEN NASAL C/2 | D37: =Cotação!D21 -> 3B | E37: =Cotação!F21 -> B | F37: =Cotação!H21 -> 5 | G37: =Cotação!M21 -> 4.3 | H37: =Cotação!L21 -> 4.3 | I37: =Cotação!V21 -> 4.3 | J37: =Cotação!Y21 -> 0 | K37: =Cotação!AC21 -> 2 | L37: =Cotação!AD21 -> 8.6 | M37: =Cotação!AE21 -> 0 | N37: =Cotação!AB21 -> 988 | O37: =Cotação!AF21
A38: =Cotação!A686 -> 611711 | B38: =Cotação!B686 -> 7896920303320 | C38: =Cotação!C686 -> BILIPLEX BOLD 10ML | D38: =Cotação!D686 -> ECOFITUS | E38: =Cotação!F686 -> A | F38: =Cotação!H686 -> 225 | G38: =Cotação!M686 -> 38.13 | H38: =Cotação!L686 -> 0.7944 | I38: =Cotação!V686 -> 22.384 | J38: =Cotação!Y686 -> -0.41295568 | K38: =Cotação!AC686 -> 3 | L38: =Cotação!AD686 -> 67.152 | M38: =Cotação!AE686 -> 47.238 | N38: =Cotação!AB686 -> 3687 | O38: =Cotação!AF686
A39: =Cotação!A687 -> 624041 | B39: =Cotação!B687 -> 7898958836818 | C39: =Cotação!C687 -> BIOTINA 450MG C/60 CPS | D39: =Cotação!D687 -> NATULAB LABORATORIO | E39: =Cotação!F687 -> B | F39: =Cotação!H687 -> 3.2 | G39: =Cotação!M687 -> 14.55 | H39: =Cotação!L687 -> 14.55 | I39: =Cotação!V687 -> 14.6 | J39: =Cotação!Y687 -> 0.0034364261 | K39: =Cotação!AC687 -> 8 | L39: =Cotação!AD687 -> 116.8 | M39: =Cotação!AE687 -> -0.4 | N39: =Cotação!AB687 -> 76 | O39: =Cotação!AF687
A40: =Cotação!A688 -> 3893 | B40: =Cotação!B688 -> 7908414448933 | C40: =Cotação!C688 -> BOLSA TERMICA GEL AZUL HC353 | D40: =Cotação!D688 -> MULTILASER | E40: =Cotação!F688 -> B | F40: =Cotação!H688 -> 3.2 | G40: =Cotação!M688 -> 12.92 | H40: =Cotação!L688 -> 12.92 | I40: =Cotação!V688 -> 12.06 | J40: =Cotação!Y688 -> -0.066563467 | K40: =Cotação!AC688 -> 7 | L40: =Cotação!AD688 -> 84.42 | M40: =Cotação!AE688 -> 6.02 | N40: =Cotação!AB688 -> 146 | O40: =Cotação!AF688
A41: =Cotação!A999 -> 674321 | B41: =Cotação!B999 -> 7898975719040 | C41: =Cotação!C999 -> BOLSA TERMICA GEL QUENTE OU FRIO GRANDE | D41: =Cotação!D999 -> 0 | E41: =Cotação!F999 -> C | F41: =Cotação!H999 -> 1.2 | G41: =Cotação!M999 -> 10.63 | H41: =Cotação!L999 -> 10.63 | I41: =Cotação!V999 -> 10.69 | J41: =Cotação!Y999 -> 0.0056444026 | K41: =Cotação!AC999 -> 2 | L41: =Cotação!AD999 -> 21.38 | M41: =Cotação!AE999 -> -0.12 | N41: =Cotação!AB999 -> 305 | O41: =Cotação!AF999
A42: =Cotação!A689 -> 294981 | B42: =Cotação!B689 -> 7896472513284 | C42: =Cotação!C689 -> BUPROVIL 300MG CX 20 COMP | D42: =Cotação!D689 -> MULTILAB | E42: =Cotação!F689 -> C | F42: =Cotação!H689 -> 0.5 | G42: =Cotação!M689 -> 5.63 | H42: =Cotação!L689 -> 5.63 | I42: =Cotação!V689 -> 5.63 | J42: =Cotação!Y689 -> 0 | K42: =Cotação!AC689 -> 1 | L42: =Cotação!AD689 -> 5.63 | M42: =Cotação!AE689 -> 0 | N42: =Cotação!AB689 -> 95 | O42: =Cotação!AF689
A43: =Cotação!A690 -> 297061 | B43: =Cotação!B690 -> 7896472502769 | C43: =Cotação!C690 -> BUPROVIL 300MG CX 30 COMP | D43: =Cotação!D690 -> MULTILAB | E43: =Cotação!F690 -> C | F43: =Cotação!H690 -> 0.5 | G43: =Cotação!M690 -> 7.08 | H43: =Cotação!L690 -> 7.08 | I43: =Cotação!V690 -> 7.33 | J43: =Cotação!Y690 -> 0.035310734 | K43: =Cotação!AC690 -> 3 | L43: =Cotação!AD690 -> 21.99 | M43: =Cotação!AE690 -> -0.75 | N43: =Cotação!AB690 -> 195 | O43: =Cotação!AF690
A44: =Cotação!A180 -> 74721 | B44: =Cotação!B180 -> 7899620910164 | C44: =Cotação!C180 -> CAPTOPRIL 50MG CX 30 COMP | D44: =Cotação!D180 -> GLOBO | E44: =Cotação!F180 -> C | F44: =Cotação!H180 -> 1.9 | G44: =Cotação!M180 -> 4.04 | H44: =Cotação!L180 -> 4.04 | I44: =Cotação!V180 -> 4.04 | J44: =Cotação!Y180 -> 0 | K44: =Cotação!AC180 -> 4 | L44: =Cotação!AD180 -> 16.16 | M44: =Cotação!AE180 -> 0 | N44: =Cotação!AB180 -> 4095 | O44: =Cotação!AF180
A45: =Cotação!A697 -> 3913 | B45: =Cotação!B697 -> 7897848500921 | C45: =Cotação!C697 -> CARBOTRAT AD 50MG 100ML XPE | D45: =Cotação!D697 -> NATULAB LABORATORIO | E45: =Cotação!F697 -> C | F45: =Cotação!H697 -> 0.2 | G45: =Cotação!M697 -> 8.09 | H45: =Cotação!L697 -> 8.09 | I45: =Cotação!V697 -> 8.09 | J45: =Cotação!Y697 -> 0 | K45: =Cotação!AC697 -> 1 | L45: =Cotação!AD697 -> 8.09 | M45: =Cotação!AE697 -> 0 | N45: =Cotação!AB697 -> 636 | O45: =Cotação!AF697
A46: =Cotação!A702 -> 56581 | B46: =Cotação!B702 -> 7896006241003 | C46: =Cotação!C702 -> CELESTRAT 2+0,25MG CX 20 COMP | D46: =Cotação!D702 -> UNIAO QUIMICA | E46: =Cotação!F702 -> A | F46: =Cotação!H702 -> 11.7 | G46: =Cotação!M702 -> 4.989 | H46: =Cotação!L702 -> 4.989 | I46: =Cotação!V702 -> 3.85 | J46: =Cotação!Y702 -> -0.22830226 | K46: =Cotação!AC702 -> 16 | L46: =Cotação!AD702 -> 61.6 | M46: =Cotação!AE702 -> 18.224 | N46: =Cotação!AB702 -> 1610 | O46: =Cotação!AF702
A47: =Cotação!A1053 -> 630661 | B47: =Cotação!B1053 -> 7896920304556 | C47: =Cotação!C1053 -> CENTROMAX A Z 60 CAPS | D47: =Cotação!D1053 -> ECOFITUS | E47: =Cotação!F1053 -> C | F47: =Cotação!H1053 -> 0.1 | G47: =Cotação!M1053 -> 26.85 | H47: =Cotação!L1053 -> 26.85 | I47: =Cotação!V1053 -> 24.590207 | J47: =Cotação!Y1053 -> -0.084163613 | K47: =Cotação!AC1053 -> 1 | L47: =Cotação!AD1053 -> 24.590207 | M47: =Cotação!AE1053 -> 2.259793 | N47: =Cotação!AB1053 -> 378 | O47: =Cotação!AF1053
A48: =Cotação!A705 -> 532281 | B48: =Cotação!B705 -> 7898031311782 | C48: =Cotação!C705 -> CETOCASP SHAMPOO 120ML | D48: =Cotação!D705 -> PADRAO | E48: =Cotação!F705 -> B | F48: =Cotação!H705 -> 2.5 | G48: =Cotação!M705 -> 8.64 | H48: =Cotação!L705 -> 8.64 | I48: =Cotação!V705 -> 9.02 | J48: =Cotação!Y705 -> 0.043981481 | K48: =Cotação!AC705 -> 7 | L48: =Cotação!AD705 -> 63.14 | M48: =Cotação!AE705 -> -2.66 | N48: =Cotação!AB705 -> 2496 | O48: =Cotação!AF705
A49: =Cotação!A189 -> 95361 | B49: =Cotação!B189 -> 7891317001926 | C49: =Cotação!C189 -> CETOPROFENO 150MG CX 10 COMP LIB PROL | D49: =Cotação!D189 -> EUROFARMA | E49: =Cotação!F189 -> A | F49: =Cotação!H189 -> 26.8 | G49: =Cotação!M189 -> 7.09 | H49: =Cotação!L189 -> 7.0893 | I49: =Cotação!V189 -> 6.82 | J49: =Cotação!Y189 -> -0.038081805 | K49: =Cotação!AC189 -> 64 | L49: =Cotação!AD189 -> 436.48 | M49: =Cotação!AE189 -> 17.28 | N49: =Cotação!AB189 -> 4235 | O49: =Cotação!AF189
A50: =Cotação!A198 -> 630181 | B50: =Cotação!B198 -> 7896004784335 | C50: =Cotação!C198 -> CLOR.FEXOFENADINA 180MG 1BLX10COM REV-GD | D50: =Cotação!D198 -> GERMED GENERICOS | E50: =Cotação!F198 -> B | F50: =Cotação!H198 -> 3.5 | G50: =Cotação!M198 -> 11.09 | H50: =Cotação!L198 -> 10.75 | I50: =Cotação!V198 -> 11.27 | J50: =Cotação!Y198 -> 0.016230839 | K50: =Cotação!AC198 -> 8 | L50: =Cotação!AD198 -> 90.16 | M50: =Cotação!AE198 -> -1.44 | N50: =Cotação!AB198 -> 180 | O50: =Cotação!AF198
A51: =Cotação!A526 -> 644921 | B51: =Cotação!B526 -> 7898938440530 | C51: =Cotação!C526 -> CLORETO DE MAGNESIO P.A 580MG C/60 CPS | D51: =Cotação!D526 -> DUOM | E51: =Cotação!F526 -> C | F51: =Cotação!H526 -> 0.5 | G51: =Cotação!M526 -> 15.26 | H51: =Cotação!L526 -> 15.26 | I51: =Cotação!V526 -> 15.38 | J51: =Cotação!Y526 -> 0.0078636959 | K51: =Cotação!AC526 -> 1 | L51: =Cotação!AD526 -> 15.38 | M51: =Cotação!AE526 -> -0.12 | N51: =Cotação!AB526 -> 31 | O51: =Cotação!AF526
A52: =Cotação!A1054 -> 646641 | B52: =Cotação!B1054 -> 7898048690405 | C52: =Cotação!C1054 -> CLORETO DE MAGNESIO P.A 600MG C/60 CPR | D52: =Cotação!D1054 -> 0 | E52: =Cotação!F1054 -> B | F52: =Cotação!H1054 -> 5.4 | G52: =Cotação!M1054 -> 9.18 | H52: =Cotação!L1054 -> 9.18 | I52: =Cotação!V1054 -> 9.14 | J52: =Cotação!Y1054 -> -0.0043572985 | K52: =Cotação!AC1054 -> 8 | L52: =Cotação!AD1054 -> 73.12 | M52: =Cotação!AE1054 -> 0.32 | N52: =Cotação!AB1054 -> 706 | O52: =Cotação!AF1054
A53: =Cotação!A1055 -> 607241 | B53: =Cotação!B1055 -> 7898964832057 | C53: =Cotação!C1055 -> CLORETO DE MAGNESIO P.A C/60 CPR | D53: =Cotação!D1055 -> NATULAB LABORATORIO | E53: =Cotação!F1055 -> C | F53: =Cotação!H1055 -> 0.5 | G53: =Cotação!M1055 -> 8.82 | H53: =Cotação!L1055 -> 8.82 | I53: =Cotação!V1055 -> 8.83 | J53: =Cotação!Y1055 -> 0.0011337868 | K53: =Cotação!AC1055 -> 2 | L53: =Cotação!AD1055 -> 17.66 | M53: =Cotação!AE1055 -> -0.02 | N53: =Cotação!AB1055 -> 631 | O53: =Cotação!AF1055
A54: =Cotação!A1003 -> 119861 | B54: =Cotação!B1003 -> 7898166041400 | C54: =Cotação!C1003 -> CLORETO DE SODIO 9 MG/ML SOL INJ IV CX 24 FR PLAS TRANS PE SIST FECH X 500 ML | D54: =Cotação!D1003 -> FARMACE INDUSTRIA QUIMICO-FARMACEUTICA CEARENSE | E54: =Cotação!F1003 -> B | F54: =Cotação!H1003 -> 0.5 | G54: =Cotação!M1003 -> 8.99 | H54: =Cotação!L1003 -> 8.99 | I54: =Cotação!V1003 -> 6.66 | J54: =Cotação!Y1003 -> -0.25917686 | K54: =Cotação!AC1003 -> 2 | L54: =Cotação!AD1003 -> 13.32 | M54: =Cotação!AE1003 -> 4.66 | N54: =Cotação!AB1003 -> 4899 | O54: =Cotação!AF1003
A55: =Cotação!A1004 -> 119901 | B55: =Cotação!B1004 -> 7898166041387 | C55: =Cotação!C1004 -> CLORETO DE SODIO 9 MG/ML SOL INJ IV CX 60 FR PLAS TRANS PE SIST FECH X 100 ML | D55: =Cotação!D1004 -> FARMACE INDUSTRIA QUIMICO-FARMACEUTICA CEARENSE | E55: =Cotação!F1004 -> A | F55: =Cotação!H1004 -> 8.6 | G55: =Cotação!M1004 -> 4.86 | H55: =Cotação!L1004 -> 4.05 | I55: =Cotação!V1004 -> 4.05 | J55: =Cotação!Y1004 -> -0.16666667 | K55: =Cotação!AC1004 -> 19 | L55: =Cotação!AD1004 -> 76.95 | M55: =Cotação!AE1004 -> 15.39 | N55: =Cotação!AB1004 -> 14748 | O55: =Cotação!AF1004
A56: =Cotação!A199 -> 124821 | B56: =Cotação!B199 -> 7899095245631 | C56: =Cotação!C199 -> CLORIDRATO DE AMIODARONA 200MG CX 30 COMP | D56: =Cotação!D199 -> GEOLAB | E56: =Cotação!F199 -> A | F56: =Cotação!H199 -> 1.6 | G56: =Cotação!M199 -> 21.51 | H56: =Cotação!L199 -> 21.51 | I56: =Cotação!V199 -> 22.01 | J56: =Cotação!Y199 -> 0.023245002 | K56: =Cotação!AC199 -> 5 | L56: =Cotação!AD199 -> 110.05 | M56: =Cotação!AE199 -> -2.5 | N56: =Cotação!AB199 -> 276 | O56: =Cotação!AF199
A57: =Cotação!A202 -> 129761 | B57: =Cotação!B202 -> 7898060131504 | C57: =Cotação!C202 -> CLORIDRATO DE BROMEXINA 1,6MG XPE FR 120ML+CM | D57: =Cotação!D202 -> GLOBO | E57: =Cotação!F202 -> B | F57: =Cotação!H202 -> 3.2 | G57: =Cotação!M202 -> 6.49 | H57: =Cotação!L202 -> 6.49 | I57: =Cotação!V202 -> 6.74 | J57: =Cotação!Y202 -> 0.038520801 | K57: =Cotação!AC202 -> 2 | L57: =Cotação!AD202 -> 13.48 | M57: =Cotação!AE202 -> -0.5 | N57: =Cotação!AB202 -> 960 | O57: =Cotação!AF202
A58: =Cotação!A204 -> 134601 | B58: =Cotação!B204 -> 7898060139951 | C58: =Cotação!C204 -> CLORIDRATO DE CICLOBENZAPRINA 10MG CX 30 COMP REV | D58: =Cotação!D204 -> GLOBO | E58: =Cotação!F204 -> C | F58: =Cotação!H204 -> 2.1 | G58: =Cotação!M204 -> 5.48 | H58: =Cotação!L204 -> 5.48 | I58: =Cotação!V204 -> 5.58 | J58: =Cotação!Y204 -> 0.018248175 | K58: =Cotação!AC204 -> 2 | L58: =Cotação!AD204 -> 11.16 | M58: =Cotação!AE204 -> -0.2 | N58: =Cotação!AB204 -> 3 | O58: =Cotação!AF204
A59: =Cotação!A207 -> 134661 | B59: =Cotação!B207 -> 7898060139913 | C59: =Cotação!C207 -> CLORIDRATO DE CICLOBENZAPRINA 5MG CX 15 COMP REV | D59: =Cotação!D207 -> GLOBO | E59: =Cotação!F207 -> C | F59: =Cotação!H207 -> 1.4 | G59: =Cotação!M207 -> 2.53 | H59: =Cotação!L207 -> 2.53 | I59: =Cotação!V207 -> 2.55 | J59: =Cotação!Y207 -> 0.0079051383 | K59: =Cotação!AC207 -> 1 | L59: =Cotação!AD207 -> 2.55 | M59: =Cotação!AE207 -> -0.02 | N59: =Cotação!AB207 -> 1 | O59: =Cotação!AF207
A60: =Cotação!A208 -> 132761 | B60: =Cotação!B208 -> 7896523214627 | C60: =Cotação!C208 -> CLORIDRATO DE CICLOBENZAPRINA 5MG CX 30 COMP REV | D60: =Cotação!D208 -> CIMED | E60: =Cotação!F208 -> B | F60: =Cotação!H208 -> 4.7 | G60: =Cotação!M208 -> 3.15 | H60: =Cotação!L208 -> 3.15 | I60: =Cotação!V208 -> 3.23 | J60: =Cotação!Y208 -> 0.025396825 | K60: =Cotação!AC208 -> 1 | L60: =Cotação!AD208 -> 3.23 | M60: =Cotação!AE208 -> -0.08 | N60: =Cotação!AB208 -> 279 | O60: =Cotação!AF208
A61: =Cotação!A480 -> 137941 | B61: =Cotação!B480 -> 7896006225744 | C61: =Cotação!C480 -> CLORIDRATO DE CLINDAMICINA 300MG CX 16 CAP | D61: =Cotação!D480 -> UNIAO QUIMICA | E61: =Cotação!F480 -> B | F61: =Cotação!H480 -> 1 | G61: =Cotação!M480 -> 17.99 | H61: =Cotação!L480 -> 17.99 | I61: =Cotação!V480 -> 14.92 | J61: =Cotação!Y480 -> -0.17065036 | K61: =Cotação!AC480 -> 3 | L61: =Cotação!AD480 -> 44.76 | M61: =Cotação!AE480 -> 9.21 | N61: =Cotação!AB480 -> 158 | O61: =Cotação!AF480
A62: =Cotação!A498 -> 162481 | B62: =Cotação!B498 -> 7896112103028 | C62: =Cotação!C498 -> CLORIDRATO DE NEBIVOLOL 5MG CX 30 COMP | D62: =Cotação!D498 -> TEUTO | E62: =Cotação!F498 -> A | F62: =Cotação!H498 -> 7.5 | G62: =Cotação!M498 -> 16.76 | H62: =Cotação!L498 -> 16.76 | I62: =Cotação!V498 -> 17.09 | J62: =Cotação!Y498 -> 0.019689737 | K62: =Cotação!AC498 -> 6 | L62: =Cotação!AD498 -> 102.54 | M62: =Cotação!AE498 -> -1.98 | N62: =Cotação!AB498 -> 994 | O62: =Cotação!AF498
A63: =Cotação!A225 -> 163981 | B63: =Cotação!B225 -> 7896112400387 | C63: =Cotação!C225 -> CLORIDRATO DE ONDANSETRONA 4MG CX 10 COMP | D63: =Cotação!D225 -> BIOLAB GENERICOS | E63: =Cotação!F225 -> C | F63: =Cotação!H225 -> 1.8 | G63: =Cotação!M225 -> 3.12 | H63: =Cotação!L225 -> 3.36 | I63: =Cotação!V225 -> 3.24 | J63: =Cotação!Y225 -> 0.038461538 | K63: =Cotação!AC225 -> 1 | L63: =Cotação!AD225 -> 3.24 | M63: =Cotação!AE225 -> -0.12 | N63: =Cotação!AB225 -> 88 | O63: =Cotação!AF225
A64: =Cotação!A501 -> 183041 | B64: =Cotação!B501 -> 7896004708607 | C64: =Cotação!C501 -> CLORIDRATO DE TRAMADOL 100MG SOL ORAL FR 15ML | D64: =Cotação!D501 -> GERMED GENERICOS | E64: =Cotação!F501 -> B | F64: =Cotação!H501 -> 0.4 | G64: =Cotação!M501 -> 16.61 | H64: =Cotação!L501 -> 16.61 | I64: =Cotação!V501 -> 16.61 | J64: =Cotação!Y501 -> 0 | K64: =Cotação!AC501 -> 1 | L64: =Cotação!AD501 -> 16.61 | M64: =Cotação!AE501 -> 0 | N64: =Cotação!AB501 -> 132 | O64: =Cotação!AF501
A65: =Cotação!A232 -> 651131 | B65: =Cotação!B232 -> 7899620916616 | C65: =Cotação!C232 -> CLORIDRATO DE TRAZODONA 100MG CX 30 COMP | D65: =Cotação!D232 -> GLOBO | E65: =Cotação!F232 -> C | F65: =Cotação!H232 -> 0.1 | G65: =Cotação!M232 -> 22 | H65: =Cotação!L232 -> 22 | I65: =Cotação!V232 -> 22.26 | J65: =Cotação!Y232 -> 0.011818182 | K65: =Cotação!AC232 -> 1 | L65: =Cotação!AD232 -> 22.26 | M65: =Cotação!AE232 -> -0.26 | N65: =Cotação!AB232 -> 136 | O65: =Cotação!AF232
A66: =Cotação!A234 -> 189301 | B66: =Cotação!B234 -> 7896004721231 | C66: =Cotação!C234 -> CLOTRIMAZOL 10MG CREM BG 20G | D66: =Cotação!D234 -> GERMED GENERICOS | E66: =Cotação!F234 -> A | F66: =Cotação!H234 -> 4.4 | G66: =Cotação!M234 -> 6.1816667 | H66: =Cotação!L234 -> 6.1817 | I66: =Cotação!V234 -> 6.38 | J66: =Cotação!Y234 -> 0.03208412 | K66: =Cotação!AC234 -> 12 | L66: =Cotação!AD234 -> 76.56 | M66: =Cotação!AE234 -> -2.38 | N66: =Cotação!AB234 -> 457 | O66: =Cotação!AF234
A67: =Cotação!A1056 -> 657411 | B67: =Cotação!B1056 -> 7898593053465 | C67: =Cotação!C1056 -> COENZIMA Q-10 50MG CX C/60 CAPS | D67: =Cotação!D1056 -> MIX NUTRI | E67: =Cotação!F1056 -> A | F67: =Cotação!H1056 -> 0.8 | G67: =Cotação!M1056 -> 35.51 | H67: =Cotação!L1056 -> 35.51 | I67: =Cotação!V1056 -> 36.86 | J67: =Cotação!Y1056 -> 0.03801746 | K67: =Cotação!AC1056 -> 2 | L67: =Cotação!AD1056 -> 73.72 | M67: =Cotação!AE1056 -> -2.7 | N67: =Cotação!AB1056 -> 63 | O67: =Cotação!AF1056
A68: =Cotação!A712 -> 2943 | B68: =Cotação!B712 -> 7898938440912 | C68: =Cotação!C712 -> COLAGENO + VITAMINA C 1000MG C/60 CPR | D68: =Cotação!D712 -> DUOM | E68: =Cotação!F712 -> A | F68: =Cotação!H712 -> 0.5 | G68: =Cotação!M712 -> 39.02 | H68: =Cotação!L712 -> 39.02 | I68: =Cotação!V712 -> 40.66 | J68: =Cotação!Y712 -> 0.042029728 | K68: =Cotação!AC712 -> 1 | L68: =Cotação!AD712 -> 40.66 | M68: =Cotação!AE712 -> -1.64 | N68: =Cotação!AB712 -> 44 | O68: =Cotação!AF712
A69: =Cotação!A714 -> 3323 | B69: =Cotação!B714 -> 7898277713272 | C69: =Cotação!C714 -> COMPLEXO B 30ML GTS | D69: =Cotação!D714 -> NATIVITA IND | E69: =Cotação!F714 -> C | F69: =Cotação!H714 -> 0.7 | G69: =Cotação!M714 -> 4.99 | H69: =Cotação!L714 -> 4.99 | I69: =Cotação!V714 -> 2.89 | J69: =Cotação!Y714 -> -0.42084168 | K69: =Cotação!AC714 -> 2 | L69: =Cotação!AD714 -> 5.78 | M69: =Cotação!AE714 -> 4.2 | N69: =Cotação!AB714 -> 1136 | O69: =Cotação!AF714
A70: =Cotação!A1057 -> 644931 | B70: =Cotação!B1057 -> 7898958836986 | C70: =Cotação!C1057 -> COMPLEXO B 400MG C/60 CPS. | D70: =Cotação!D1057 -> DUOM | E70: =Cotação!F1057 -> B | F70: =Cotação!H1057 -> 0.8 | G70: =Cotação!M1057 -> 15.32 | H70: =Cotação!L1057 -> 15.32 | I70: =Cotação!V1057 -> 14.64 | J70: =Cotação!Y1057 -> -0.044386423 | K70: =Cotação!AC1057 -> 2 | L70: =Cotação!AD1057 -> 29.28 | M70: =Cotação!AE1057 -> 1.36 | N70: =Cotação!AB1057 -> 41 | O70: =Cotação!AF1057
A71: =Cotação!A1058 -> 661121 | B71: =Cotação!B1058 -> 7897146650021 | C71: =Cotação!C1058 -> COMPLEXO B C/100 CPR. | D71: =Cotação!D1058 -> 0 | E71: =Cotação!F1058 -> C | F71: =Cotação!H1058 -> 2.1 | G71: =Cotação!M1058 -> 7.97 | H71: =Cotação!L1058 -> 7.97 | I71: =Cotação!V1058 -> 7.97 | J71: =Cotação!Y1058 -> 0 | K71: =Cotação!AC1058 -> 6 | L71: =Cotação!AD1058 -> 47.82 | M71: =Cotação!AE1058 -> 0 | N71: =Cotação!AB1058 -> 214 | O71: =Cotação!AF1058
A72: =Cotação!A715 -> 3343 | B72: =Cotação!B715 -> 7898277714880 | C72: =Cotação!C715 -> COMPLEXO B C/20 CPR CONCENTRADO | D72: =Cotação!D715 -> 0 | E72: =Cotação!F715 -> C | F72: =Cotação!H715 -> 0.4 | G72: =Cotação!M715 -> 6.37 | H72: =Cotação!L715 -> 6.37 | I72: =Cotação!V715 -> 6.37 | J72: =Cotação!Y715 -> 0 | K72: =Cotação!AC715 -> 1 | L72: =Cotação!AD715 -> 6.37 | M72: =Cotação!AE715 -> 0 | N72: =Cotação!AB715 -> 214 | O72: =Cotação!AF715
A73: =Cotação!A716 -> 608751 | B73: =Cotação!B716 -> 7897146600200 | C73: =Cotação!C716 -> COMPLEXO B C/30 CPR | D73: =Cotação!D716 -> HENFER | E73: =Cotação!F716 -> C | F73: =Cotação!H716 -> 1.3 | G73: =Cotação!M716 -> 3.38 | H73: =Cotação!L716 -> 3.38 | I73: =Cotação!V716 -> 3.38 | J73: =Cotação!Y716 -> 0 | K73: =Cotação!AC716 -> 4 | L73: =Cotação!AD716 -> 13.52 | M73: =Cotação!AE716 -> 0 | N73: =Cotação!AB716 -> 2207 | O73: =Cotação!AF716
A74: =Cotação!A718 -> 592581 | B74: =Cotação!B718 -> 7897146600064 | C74: =Cotação!C718 -> COMPLEXO B C/50 CPR | D74: =Cotação!D718 -> ARTE NATIVA | E74: =Cotação!F718 -> A | F74: =Cotação!H718 -> 7.5 | G74: =Cotação!M718 -> 5 | H74: =Cotação!L718 -> 5 | I74: =Cotação!V718 -> 5 | J74: =Cotação!Y718 -> 0 | K74: =Cotação!AC718 -> 17 | L74: =Cotação!AD718 -> 85 | M74: =Cotação!AE718 -> 0 | N74: =Cotação!AB718 -> 1484 | O74: =Cotação!AF718
A75: =Cotação!A719 -> 541341 | B75: =Cotação!B719 -> 7898964832156 | C75: =Cotação!C719 -> COMPLEXO B C/60COMP. | D75: =Cotação!D719 -> NUTRITIVE | E75: =Cotação!F719 -> B | F75: =Cotação!H719 -> 4.3 | G75: =Cotação!M719 -> 5.24 | H75: =Cotação!L719 -> 5.24 | I75: =Cotação!V719 -> 5.24 | J75: =Cotação!Y719 -> 0 | K75: =Cotação!AC719 -> 9 | L75: =Cotação!AD719 -> 47.16 | M75: =Cotação!AE719 -> 0 | N75: =Cotação!AB719 -> 1248 | O75: =Cotação!AF719
A76: =Cotação!A720 -> 581021 | B76: =Cotação!B720 -> 7898277713333 | C76: =Cotação!C720 -> COMPLEXO B SOL ORAL 100ML (POLIVITAMINAS | D76: =Cotação!D720 -> ARTE NATIVA | E76: =Cotação!F720 -> C | F76: =Cotação!H720 -> 1.5 | G76: =Cotação!M720 -> 3.9 | H76: =Cotação!L720 -> 3.9 | I76: =Cotação!V720 -> 3.9 | J76: =Cotação!Y720 -> 0 | K76: =Cotação!AC720 -> 2 | L76: =Cotação!AD720 -> 7.8 | M76: =Cotação!AE720 -> 0 | N76: =Cotação!AB720 -> 63 | O76: =Cotação!AF720
A77: =Cotação!A84 -> 596581 | B77: =Cotação!B84 -> 7898933598151 | C77: =Cotação!C84 -> COMPRESSA GAZE 11 FIOS C/10 UN TEXPHARMA | D77: =Cotação!D84 -> TEXPHARMA | E77: =Cotação!F84 -> C | F77: =Cotação!H84 -> 0.1 | G77: =Cotação!M84 -> 0.56 | H77: =Cotação!L84 -> 0.56 | I77: =Cotação!V84 -> 0.56 | J77: =Cotação!Y84 -> 0 | K77: =Cotação!AC84 -> 1 | L77: =Cotação!AD84 -> 0.56 | M77: =Cotação!AE84 -> 0 | N77: =Cotação!AB84 -> 21392 | O77: =Cotação!AF84
A78: =Cotação!A1007 -> 538361 | B78: =Cotação!B1007 -> 7898668060190 | C78: =Cotação!C1007 -> COMPRESSA GAZE 13 FIOS C/10 UND LIVIA | D78: =Cotação!D1007 -> PADRAO | E78: =Cotação!F1007 -> A | F78: =Cotação!H1007 -> 346.2 | G78: =Cotação!M1007 -> 0.58 | H78: =Cotação!L1007 -> 0.58 | I78: =Cotação!V1007 -> 0.58 | J78: =Cotação!Y1007 -> 0 | K78: =Cotação!AC1007 -> 844 | L78: =Cotação!AD1007 -> 489.52 | M78: =Cotação!AE1007 -> 0 | N78: =Cotação!AB1007 -> 156885 | O78: =Cotação!AF1007
A79: =Cotação!A968 -> 643291 | B79: =Cotação!B968 -> 7898669306716 | C79: =Cotação!C968 -> CREATINA 100% PURE ABSOLUT 150G | D79: =Cotação!D968 -> ABSOLUTY | E79: =Cotação!F968 -> C | F79: =Cotação!H968 -> 1 | G79: =Cotação!M968 -> 37.6 | H79: =Cotação!L968 -> 37.6 | I79: =Cotação!V968 -> 24.08 | J79: =Cotação!Y968 -> -0.35957447 | K79: =Cotação!AC968 -> 3 | L79: =Cotação!AD968 -> 72.24 | M79: =Cotação!AE968 -> 40.56 | N79: =Cotação!AB968 -> 25 | O79: =Cotação!AF968
A80: =Cotação!A723 -> 3923 | B80: =Cotação!B723 -> 7898665752388 | C80: =Cotação!C723 -> CREATINA 3000MG 150G PO | D80: =Cotação!D723 -> NATULAB LABORATORIO | E80: =Cotação!F723 -> C | F80: =Cotação!H723 -> 0.1 | G80: =Cotação!M723 -> 34.97 | H80: =Cotação!L723 -> 34.97 | I80: =Cotação!V723 -> 27.44 | J80: =Cotação!Y723 -> -0.21532742 | K80: =Cotação!AC723 -> 1 | L80: =Cotação!AD723 -> 27.44 | M80: =Cotação!AE723 -> 7.53 | N80: =Cotação!AB723 -> 31 | O80: =Cotação!AF723
A81: =Cotação!A1059 -> 651441 | B81: =Cotação!B1059 -> 7898665752500 | C81: =Cotação!C1059 -> CREATINA 3000MG C/120 CPS | D81: =Cotação!D1059 -> NATULAB LABORATORIO | E81: =Cotação!F1059 -> B | F81: =Cotação!H1059 -> 0.6 | G81: =Cotação!M1059 -> 32.84 | H81: =Cotação!L1059 -> 32.84 | I81: =Cotação!V1059 -> 31.71 | J81: =Cotação!Y1059 -> -0.034409257 | K81: =Cotação!AC1059 -> 1 | L81: =Cotação!AD1059 -> 31.71 | M81: =Cotação!AE1059 -> 1.13 | N81: =Cotação!AB1059 -> 7 | O81: =Cotação!AF1059
A82: =Cotação!A724 -> 673701 | B82: =Cotação!B724 -> 7898277712695 | C82: =Cotação!C724 -> CREME DE ARNICA MONTANA 60G | D82: =Cotação!D724 -> ARTE NATIVA | E82: =Cotação!F724 -> C | F82: =Cotação!H724 -> 0.4 | G82: =Cotação!M724 -> 9.09 | H82: =Cotação!L724 -> 9.09 | I82: =Cotação!V724 -> 9.09 | J82: =Cotação!Y724 -> 0 | K82: =Cotação!AC724 -> 2 | L82: =Cotação!AD724 -> 18.18 | M82: =Cotação!AE724 -> 0 | N82: =Cotação!AB724 -> 362 | O82: =Cotação!AF724
A83: =Cotação!A549 -> 620031 | B83: =Cotação!B549 -> 7898136150613 | C83: =Cotação!C549 -> CURATIVO ADESIVO NATHY BEGE 10UND | D83: =Cotação!D549 -> NATHY | E83: =Cotação!F549 -> B | F83: =Cotação!H549 -> 27.9 | G83: =Cotação!M549 -> 2.61 | H83: =Cotação!L549 -> 2.61 | I83: =Cotação!V549 -> 1.42 | J83: =Cotação!Y549 -> -0.4559387 | K83: =Cotação!AC549 -> 19 | L83: =Cotação!AD549 -> 26.98 | M83: =Cotação!AE549 -> 22.61 | N83: =Cotação!AB549 -> 19 | O83: =Cotação!AF549 -> ESTOQUE INSUFICIENTE
A84: =Cotação!A86 -> 647131 | B84: =Cotação!B86 -> 7898136150583 | C84: =Cotação!C86 -> CURATIVO ADESIVO NATHY BEGE 16UND | D84: =Cotação!D86 -> NATHY | E84: =Cotação!F86 -> C | F84: =Cotação!H86 -> 1.1 | G84: =Cotação!M86 -> 2 | H84: =Cotação!L86 -> 2 | I84: =Cotação!V86 -> 1.49 | J84: =Cotação!Y86 -> -0.255 | K84: =Cotação!AC86 -> 3 | L84: =Cotação!AD86 -> 4.47 | M84: =Cotação!AE86 -> 1.53 | N84: =Cotação!AB86 -> 17 | O84: =Cotação!AF86
A85: =Cotação!A550 -> 620061 | B85: =Cotação!B550 -> 7898136150446 | C85: =Cotação!C550 -> CURATIVO ADESIVO NATHY TRANSPARENTE 10UN | D85: =Cotação!D550 -> NATHY | E85: =Cotação!F550 -> C | F85: =Cotação!H550 -> 10.7 | G85: =Cotação!M550 -> 2.41 | H85: =Cotação!L550 -> 2.41 | I85: =Cotação!V550 -> 1.42 | J85: =Cotação!Y550 -> -0.41078838 | K85: =Cotação!AC550 -> 15 | L85: =Cotação!AD550 -> 21.3 | M85: =Cotação!AE550 -> 14.85 | N85: =Cotação!AB550 -> 23 | O85: =Cotação!AF550
A86: =Cotação!A87 -> 647121 | B86: =Cotação!B87 -> 7898136150576 | C86: =Cotação!C87 -> CURATIVO ADESIVO NATHY TRANSPARENTE 16UN | D86: =Cotação!D87 -> NATHY | E86: =Cotação!F87 -> C | F86: =Cotação!H87 -> 0.4 | G86: =Cotação!M87 -> 2 | H86: =Cotação!L87 -> 2 | I86: =Cotação!V87 -> 1.49 | J86: =Cotação!Y87 -> -0.255 | K86: =Cotação!AC87 -> 2 | L86: =Cotação!AD87 -> 2.98 | M86: =Cotação!AE87 -> 1.02 | N86: =Cotação!AB87 -> 3 | O86: =Cotação!AF87
A87: =Cotação!A90 -> 4103 | B87: =Cotação!B90 -> 7896544927230 | C87: =Cotação!C90 -> CURATIVO HIDROCOLOIDE BOLHAS CALOS C/08 | D87: =Cotação!D90 -> 0 | E87: =Cotação!F90 -> C | F87: =Cotação!H90 -> 0.5 | G87: =Cotação!M90 -> 10.96 | H87: =Cotação!L90 -> 10.96 | I87: =Cotação!V90 -> 10.96 | J87: =Cotação!Y90 -> 0 | K87: =Cotação!AC90 -> 2 | L87: =Cotação!AD90 -> 21.92 | M87: =Cotação!AE90 -> 0 | N87: =Cotação!AB90 -> 23 | O87: =Cotação!AF90
A88: =Cotação!A91 -> 4033 | B88: =Cotação!B91 -> 7896544901346 | C88: =Cotação!C91 -> CURATIVO HIDROCOLOIDE P/ ACNES C/24 UND | D88: =Cotação!D91 -> 0 | E88: =Cotação!F91 -> A | F88: =Cotação!H91 -> 3.7 | G88: =Cotação!M91 -> 8.32 | H88: =Cotação!L91 -> 8.32 | I88: =Cotação!V91 -> 8.32 | J88: =Cotação!Y91 -> 0 | K88: =Cotação!AC91 -> 9 | L88: =Cotação!AD91 -> 74.88 | M88: =Cotação!AE91 -> 0 | N88: =Cotação!AB91 -> 77 | O88: =Cotação!AF91
A89: =Cotação!A95 -> 656461 | B89: =Cotação!B95 -> 7898136150620 | C89: =Cotação!C95 -> CURATIVO NATHY C/35UN BEGE | D89: =Cotação!D95 -> NATHY | E89: =Cotação!F95 -> A | F89: =Cotação!H95 -> 10.4 | G89: =Cotação!M95 -> 3.25 | H89: =Cotação!L95 -> 3.25 | I89: =Cotação!V95 -> 3.25 | J89: =Cotação!Y95 -> 0 | K89: =Cotação!AC95 -> 23 | L89: =Cotação!AD95 -> 74.75 | M89: =Cotação!AE95 -> 0 | N89: =Cotação!AB95 -> 23 | O89: =Cotação!AF95 -> ESTOQUE INSUFICIENTE
A90: =Cotação!A96 -> 3433 | B90: =Cotação!B96 -> 7898108640692 | C90: =Cotação!C96 -> CURATIVO REDONDO CICATRISAN C/20 UND | D90: =Cotação!D96 -> 0 | E90: =Cotação!F96 -> C | F90: =Cotação!H96 -> 0.9 | G90: =Cotação!M96 -> 5.94 | H90: =Cotação!L96 -> 5.94 | I90: =Cotação!V96 -> 5.42 | J90: =Cotação!Y96 -> -0.087542088 | K90: =Cotação!AC96 -> 2 | L90: =Cotação!AD96 -> 10.84 | M90: =Cotação!AE96 -> 1.04 | N90: =Cotação!AB96 -> 212 | O90: =Cotação!AF96
A91: =Cotação!A240 -> 39203 | B91: =Cotação!B240 -> 7896004821948 | C91: =Cotação!C240 -> DAPAGLIFLOZINA 10MG C/30 CPR GMD-GENERICO | D91: =Cotação!D240 -> GERMED | E91: =Cotação!F240 -> C | F91: =Cotação!H240 -> 0.2 | G91: =Cotação!M240 -> 39.71 | H91: =Cotação!L240 -> 39.71 | I91: =Cotação!V240 -> 29.99 | J91: =Cotação!Y240 -> -0.24477462 | K91: =Cotação!AC240 -> 1 | L91: =Cotação!AD240 -> 29.99 | M91: =Cotação!AE240 -> 9.72 | N91: =Cotação!AB240 -> 238 | O91: =Cotação!AF240
A92: =Cotação!A1061 -> 691501 | B92: =Cotação!B1061 -> 7898593050716 | C92: =Cotação!C1061 -> DERMUP COLAGENO VERISOL C/90 CPS | D92: =Cotação!D1061 -> MAXINUTRI | E92: =Cotação!F1061 -> B | F92: =Cotação!H1061 -> 0.5 | G92: =Cotação!M1061 -> 42.53 | H92: =Cotação!L1061 -> 42.53 | I92: =Cotação!V1061 -> 42.53 | J92: =Cotação!Y1061 -> 0 | K92: =Cotação!AC1061 -> 2 | L92: =Cotação!AD1061 -> 85.06 | M92: =Cotação!AE1061 -> 0 | N92: =Cotação!AB1061 -> 15 | O92: =Cotação!AF1061
A93: =Cotação!A244 -> 648181 | B93: =Cotação!B244 -> 7896004820798 | C93: =Cotação!C244 -> DESLORATADINA 5MG CX 10 COMP REV | D93: =Cotação!D244 -> GERMED GENERICOS | E93: =Cotação!F244 -> C | F93: =Cotação!H244 -> 0.6 | G93: =Cotação!M244 -> 6.1842857 | H93: =Cotação!L244 -> 6.1843 | I93: =Cotação!V244 -> 4.99 | J93: =Cotação!Y244 -> -0.19311619 | K93: =Cotação!AC244 -> 2 | L93: =Cotação!AD244 -> 9.98 | M93: =Cotação!AE244 -> 2.3885714 | N93: =Cotação!AB244 -> 449 | O93: =Cotação!AF244
A94: =Cotação!A248 -> 206161 | B94: =Cotação!B248 -> 7896004711362 | C94: =Cotação!C248 -> DESONIDA 0,5MG POM BG 30G | D94: =Cotação!D248 -> GERMED GENERICOS | E94: =Cotação!F248 -> C | F94: =Cotação!H248 -> 0.3 | G94: =Cotação!M248 -> 12.41 | H94: =Cotação!L248 -> 12.41 | I94: =Cotação!V248 -> 12.77 | J94: =Cotação!Y248 -> 0.029008864 | K94: =Cotação!AC248 -> 2 | L94: =Cotação!AD248 -> 25.54 | M94: =Cotação!AE248 -> -0.72 | N94: =Cotação!AB248 -> 1129 | O94: =Cotação!AF248
A95: =Cotação!A733 -> 590711 | B95: =Cotação!B733 -> 7898277713067 | C95: =Cotação!C733 -> DESUPRE GTS VITAMINA D 200UI 20ML LIMAO | D95: =Cotação!D733 -> ALTHAIA S.A INDUSTRIA FARMACEUTICA | E95: =Cotação!F733 -> B | F95: =Cotação!H733 -> 3.2 | G95: =Cotação!M733 -> 4.31 | H95: =Cotação!L733 -> 4.31 | I95: =Cotação!V733 -> 4.31 | J95: =Cotação!Y733 -> 0 | K95: =Cotação!AC733 -> 6 | L95: =Cotação!AD733 -> 25.86 | M95: =Cotação!AE733 -> 0 | N95: =Cotação!AB733 -> 313 | O95: =Cotação!AF733
A96: =Cotação!A734 -> 3783 | B96: =Cotação!B734 -> 7898719041673 | C96: =Cotação!C734 -> DIABETYLL 300G CREME. | D96: =Cotação!D734 -> 0 | E96: =Cotação!F734 -> C | F96: =Cotação!H734 -> 0.1 | G96: =Cotação!M734 -> 29.33 | H96: =Cotação!L734 -> 29.33 | I96: =Cotação!V734 -> 29.33 | J96: =Cotação!Y734 -> 0 | K96: =Cotação!AC734 -> 1 | L96: =Cotação!AD734 -> 29.33 | M96: =Cotação!AE734 -> 0 | N96: =Cotação!AB734 -> 1 | O96: =Cotação!AF734
A97: =Cotação!A252 -> 490121 | B97: =Cotação!B252 -> 7897917004008 | C97: =Cotação!C252 -> DICLOFENACO SODICO 50MG CX 20 COMP REV | D97: =Cotação!D252 -> BELFAR | E97: =Cotação!F252 -> C | F97: =Cotação!H252 -> 0.8 | G97: =Cotação!M252 -> 1.65 | H97: =Cotação!L252 -> 1.65 | I97: =Cotação!V252 -> 1.65 | J97: =Cotação!Y252 -> 0 | K97: =Cotação!AC252 -> 1 | L97: =Cotação!AD252 -> 1.65 | M97: =Cotação!AE252 -> 0 | N97: =Cotação!AB252 -> 6 | O97: =Cotação!AF252
A98: =Cotação!A257 -> 214001 | B98: =Cotação!B257 -> 7897076921499 | C98: =Cotação!C257 -> DICLORIDRATO DE LEVOCETIRIZINA 5MG CX 10 COMP REV | D98: =Cotação!D257 -> RANBAXY | E98: =Cotação!F257 -> A | F98: =Cotação!H257 -> 3.2 | G98: =Cotação!M257 -> 9.29 | H98: =Cotação!L257 -> 8.5444 | I98: =Cotação!V257 -> 9.73 | J98: =Cotação!Y257 -> 0.047362756 | K98: =Cotação!AC257 -> 2 | L98: =Cotação!AD257 -> 19.46 | M98: =Cotação!AE257 -> -0.88 | N98: =Cotação!AB257 -> 89 | O98: =Cotação!AF257
A99: =Cotação!A481 -> 449201 | B99: =Cotação!B481 -> 7899095233522 | C99: =Cotação!C481 -> DIP BETAMETASONA+SULF GENTAMICINA 0,5+1,0MG/G POM BG 30G | D99: =Cotação!D481 -> GEOLAB | E99: =Cotação!F481 -> C | F99: =Cotação!H481 -> 0.7 | G99: =Cotação!M481 -> 8.55 | H99: =Cotação!L481 -> 8.55 | I99: =Cotação!V481 -> 8.36 | J99: =Cotação!Y481 -> -0.022222222 | K99: =Cotação!AC481 -> 1 | L99: =Cotação!AD481 -> 8.36 | M99: =Cotação!AE481 -> 0.19 | N99: =Cotação!AB481 -> 137 | O99: =Cotação!AF481
A100: =Cotação!A737 -> 222061 | B100: =Cotação!B737 -> 7896862940027 | C100: =Cotação!C737 -> DIPIMED 500MG/ML SOL OR FR 10ML | D100: =Cotação!D737 -> MEDQUIMICA | E100: =Cotação!F737 -> C | F100: =Cotação!H737 -> 2.1 | G100: =Cotação!M737 -> 1.88 | H100: =Cotação!L737 -> 1.88 | I100: =Cotação!V737 -> 1.88 | J100: =Cotação!Y737 -> 0 | K100: =Cotação!AC737 -> 6 | L100: =Cotação!AD737 -> 11.28 | M100: =Cotação!AE737 -> 0 | N100: =Cotação!AB737 -> 3302 | O100: =Cotação!AF737
A101: =Cotação!A260 -> 627881 | B101: =Cotação!B260 -> 7896004715650 | C101: =Cotação!C260 -> DIPIRONA SODICA 50MG SOL ORAL FR 100ML | D101: =Cotação!D260 -> GERMED GENERICOS | E101: =Cotação!F260 -> B | F101: =Cotação!H260 -> 6 | G101: =Cotação!M260 -> 7.02 | H101: =Cotação!L260 -> 7.02 | I101: =Cotação!V260 -> 7.36 | J101: =Cotação!Y260 -> 0.048433048 | K101: =Cotação!AC260 -> 14 | L101: =Cotação!AD260 -> 103.04 | M101: =Cotação!AE260 -> -4.76 | N101: =Cotação!AB260 -> 389 | O101: =Cotação!AF260
...

Sheet Pedido MEDCENTRO
A1: PEDIDO MEDCENTRO — 20/10/2026 (PRECO_FINAL −5%)
A3: Cód. interno | B3: EAN | C3: Produto | D3: Fabricante | E3: ABC | F3: Dem./mês | G3: Preço ref. (cx) | H3: Melhor 3m (un) | I3: Preço ofertado (cx) | J3: Var. vs ref. | K3: Qtd pedido (cx) | L3: Valor pedido | M3: Economia | N3: Estoque forn. | O3: Alerta
A4: =Cotação!A7 -> 643491 | B4: =Cotação!B7 -> 7896699032520 | C4: =Cotação!C7 -> 1560-01-F MAM TIP 80ML SIL R F CX C/6 - LOLLY | D4: =Cotação!D7 -> LOLLY | E4: =Cotação!F7 -> B | F4: =Cotação!H7 -> 0.5 | G4: =Cotação!M7 -> 12.8 | H4: =Cotação!L7 -> 12.8 | I4: =Cotação!V7 -> 12.3215 | J4: =Cotação!Y7 -> -0.037382813 | K4: =Cotação!AC7 -> 1 | L4: =Cotação!AD7 -> 12.3215 | M4: =Cotação!AE7 -> 0.4785 | N4: =Cotação!AB7 -> 78 | O4: =Cotação!AF7
A5: =Cotação!A8 -> 643501 | B5: =Cotação!B8 -> 7896699032537 | C5: =Cotação!C8 -> 1560-01-M MAM TIP 80ML SIL R M LOLLY | D5: =Cotação!D8 -> LOLLY | E5: =Cotação!F8 -> C | F5: =Cotação!H8 -> 0.8 | G5: =Cotação!M8 -> 12.8 | H5: =Cotação!L8 -> 12.26 | I5: =Cotação!V8 -> 12.3215 | J5: =Cotação!Y8 -> -0.037382813 | K5: =Cotação!AC8 -> 1 | L5: =Cotação!AD8 -> 12.3215 | M5: =Cotação!AE8 -> 0.4785 | N5: =Cotação!AB8 -> 29 | O5: =Cotação!AF8
A6: =Cotação!A9 -> 643511 | B6: =Cotação!B9 -> 7896699015479 | C6: =Cotação!C9 -> 1970-01-F MINI MAM CLEAN 50ML F - LOLLY | D6: =Cotação!D9 -> LOLLY | E6: =Cotação!F9 -> B | F6: =Cotação!H9 -> 4.3 | G6: =Cotação!M9 -> 9.07 | H6: =Cotação!L9 -> 9.07 | I6: =Cotação!V9 -> 9.12 | J6: =Cotação!Y9 -> 0.0055126792 | K6: =Cotação!AC9 -> 11 | L6: =Cotação!AD9 -> 100.32 | M6: =Cotação!AE9 -> -0.55 | N6: =Cotação!AB9 -> 333 | O6: =Cotação!AF9
A7: =Cotação!A10 -> 643521 | B7: =Cotação!B10 -> 7896699015455 | C7: =Cotação!C10 -> 1970-01-M MINI MAM CLEAN 50ML M CX C/6 - LOLLY | D7: =Cotação!D10 -> LOLLY | E7: =Cotação!F10 -> B | F7: =Cotação!H10 -> 2.1 | G7: =Cotação!M10 -> 9.07 | H7: =Cotação!L10 -> 9.07 | I7: =Cotação!V10 -> 9.12 | J7: =Cotação!Y10 -> 0.0055126792 | K7: =Cotação!AC10 -> 6 | L7: =Cotação!AD10 -> 54.72 | M7: =Cotação!AE10 -> -0.3 | N7: =Cotação!AB10 -> 250 | O7: =Cotação!AF10
A8: =Cotação!A15 -> 653461 | B8: =Cotação!B15 -> 7896699033244 | C8: =Cotação!C15 -> 4915-01-F CH VIVA SIL O T2 F LOLLY | D8: =Cotação!D15 -> LOLLY | E8: =Cotação!F15 -> C | F8: =Cotação!H15 -> 0.1 | G8: =Cotação!M15 -> 8.76 | H8: =Cotação!L15 -> 8.76 | I8: =Cotação!V15 -> 8.8065 | J8: =Cotação!Y15 -> 0.0053082192 | K8: =Cotação!AC15 -> 1 | L8: =Cotação!AD15 -> 8.8065 | M8: =Cotação!AE15 -> -0.0465 | N8: =Cotação!AB15 -> 36 | O8: =Cotação!AF15
A9: =Cotação!A17 -> 643591 | B9: =Cotação!B17 -> 7896699032230 | C9: =Cotação!C17 -> 6014-01-F CH 100% SILICONE OT1 F LOLLY | D9: =Cotação!D17 -> LOLLY | E9: =Cotação!F17 -> B | F9: =Cotação!H17 -> 0.7 | G9: =Cotação!M17 -> 15.13 | H9: =Cotação!L17 -> 15.13 | I9: =Cotação!V17 -> 15.2095 | J9: =Cotação!Y17 -> 0.0052544613 | K9: =Cotação!AC17 -> 2 | L9: =Cotação!AD17 -> 30.419 | M9: =Cotação!AE17 -> -0.159 | N9: =Cotação!AB17 -> 472 | O9: =Cotação!AF17
A10: =Cotação!A541 -> 659151 | B10: =Cotação!B541 -> 7896699034456 | C10: =Cotação!C541 -> 7197-00-F COPO STAR BICO SIL 250ML F CX/6 - LOLLY | D10: =Cotação!D541 -> LOLLY | E10: =Cotação!F541 -> B | F10: =Cotação!H541 -> 0.4 | G10: =Cotação!M541 -> 45.59 | H10: =Cotação!L541 -> 45.59 | I10: =Cotação!V541 -> 41.7905 | J10: =Cotação!Y541 -> -0.083340645 | K10: =Cotação!AC541 -> 1 | L10: =Cotação!AD541 -> 41.7905 | M10: =Cotação!AE541 -> 3.7995 | N10: =Cotação!AB541 -> 1 | O10: =Cotação!AF541
A11: =Cotação!A140 -> 10241 | B11: =Cotação!B140 -> 7896004713366 | C11: =Cotação!C140 -> ACETILCISTEINA 40MG XPE FR 120ML ADU | D11: =Cotação!D140 -> EMS GENERICO | E11: =Cotação!F140 -> A | F11: =Cotação!H140 -> 1.3 | G11: =Cotação!M140 -> 11.22 | H11: =Cotação!L140 -> 11.22 | I11: =Cotação!V140 -> 11.286 | J11: =Cotação!Y140 -> 0.0058823529 | K11: =Cotação!AC140 -> 4 | L11: =Cotação!AD140 -> 45.144 | M11: =Cotação!AE140 -> -0.264 | N11: =Cotação!AB140 -> 63 | O11: =Cotação!AF140
A12: =Cotação!A142 -> 231861 | B12: =Cotação!B142 -> 7896004713625 | C12: =Cotação!C142 -> ACETONIDO DE ALGESTONA+ENANTATO DE ESTRADIOL 150+10MG INJ AMP X 1ML | D12: =Cotação!D142 -> GERMED GENERICOS | E12: =Cotação!F142 -> C | F12: =Cotação!H142 -> 82.3 | G12: =Cotação!M142 -> 9.66 | H12: =Cotação!L142 -> 9.66 | I12: =Cotação!V142 -> 9.6615 | J12: =Cotação!Y142 -> 0.0001552795 | K12: =Cotação!AC142 -> 28 | L12: =Cotação!AD142 -> 270.522 | M12: =Cotação!AE142 -> -0.042 | N12: =Cotação!AB142 -> 28 | O12: =Cotação!AF142 -> ESTOQUE INSUFICIENTE
A13: =Cotação!A654 -> 630541 | B13: =Cotação!B654 -> 7894913002137 | C13: =Cotação!C654 -> AFTIKE MEL ROSADO SPRAY 30ML | D13: =Cotação!D654 -> KRESS | E13: =Cotação!F654 -> C | F13: =Cotação!H654 -> 0.7 | G13: =Cotação!M654 -> 15.6 | H13: =Cotação!L654 -> 15.6 | I13: =Cotação!V654 -> 15.7225 | J13: =Cotação!Y654 -> 0.0078525641 | K13: =Cotação!AC654 -> 1 | L13: =Cotação!AD654 -> 15.7225 | M13: =Cotação!AE654 -> -0.1225 | N13: =Cotação!AB654 -> 475 | O13: =Cotação!AF654
A14: =Cotação!A543 -> 657951 | B14: =Cotação!B543 -> 7896902210561 | C14: =Cotação!C543 -> AGUA OXIG FARMAX 90ML 20V | D14: =Cotação!D543 -> FARMAX | E14: =Cotação!F543 -> C | F14: =Cotação!H543 -> 0 | G14: =Cotação!M543 -> 2.22 | H14: =Cotação!L543 -> 2.22 | I14: =Cotação!V543 -> 1.995 | J14: =Cotação!Y543 -> -0.10135135 | K14: =Cotação!AC543 -> 1 | L14: =Cotação!AD543 -> 1.995 | M14: =Cotação!AE543 -> 0.225 | N14: =Cotação!AB543 -> 183 | O14: =Cotação!AF543
A15: =Cotação!A990 -> 674721 | B15: =Cotação!B990 -> 7896902210530 | C15: =Cotação!C990 -> AGUA OXIGENADA CR 10VOL DESCOLOR 90ML | D15: =Cotação!D990 -> 0 | E15: =Cotação!F990 -> B | F15: =Cotação!H990 -> 9.6 | G15: =Cotação!M990 -> 2 | H15: =Cotação!L990 -> 2 | I15: =Cotação!V990 -> 2.014 | J15: =Cotação!Y990 -> 0.007 | K15: =Cotação!AC990 -> 20 | L15: =Cotação!AD990 -> 40.28 | M15: =Cotação!AE990 -> -0.28 | N15: =Cotação!AB990 -> 122 | O15: =Cotação!AF990
A16: =Cotação!A545 -> 534761 | B16: =Cotação!B545 -> 7896902210905 | C16: =Cotação!C545 -> AGUA OXIGENADA CREMOSA - AMONIA 100ML | D16: =Cotação!D545 -> FARMAX | E16: =Cotação!F545 -> C | F16: =Cotação!H545 -> 1.9 | G16: =Cotação!M545 -> 2.02 | H16: =Cotação!L545 -> 2.02 | I16: =Cotação!V545 -> 2.109 | J16: =Cotação!Y545 -> 0.044059406 | K16: =Cotação!AC545 -> 1 | L16: =Cotação!AD545 -> 2.109 | M16: =Cotação!AE545 -> -0.089 | N16: =Cotação!AB545 -> 1 | O16: =Cotação!AF545
A17: =Cotação!A521 -> 3273 | B17: =Cotação!B521 -> 7897732609259 | C17: =Cotação!C521 -> AGUALEMA JALAPA 200ML | D17: =Cotação!D521 -> SOBRAL | E17: =Cotação!F521 -> B | F17: =Cotação!H521 -> 2.1 | G17: =Cotação!M521 -> 15.82 | H17: =Cotação!L521 -> 13.39 | I17: =Cotação!V521 -> 15.9315 | J17: =Cotação!Y521 -> 0.0070480405 | K17: =Cotação!AC521 -> 1 | L17: =Cotação!AD521 -> 15.9315 | M17: =Cotação!AE521 -> -0.1115 | N17: =Cotação!AB521 -> 2297 | O17: =Cotação!AF521 -> EMPATE TÉCNICO
A18: =Cotação!A522 -> 651171 | B18: =Cotação!B522 -> 7898048690900 | C18: =Cotação!C522 -> AGUARDENTE ALEMA JALAPA 200ML | D18: =Cotação!D522 -> SOBRAL | E18: =Cotação!F522 -> C | F18: =Cotação!H522 -> 0.1 | G18: =Cotação!M522 -> 8.09 | H18: =Cotação!L522 -> 8.09 | I18: =Cotação!V522 -> 7.7615 | J18: =Cotação!Y522 -> -0.040605686 | K18: =Cotação!AC522 -> 1 | L18: =Cotação!AD522 -> 7.7615 | M18: =Cotação!AE522 -> 0.3285 | N18: =Cotação!AB522 -> 1 | O18: =Cotação!AF522
A19: =Cotação!A659 -> 573221 | B19: =Cotação!B659 -> 7899095201354 | C19: =Cotação!C659 -> ALBEL 400MG CX 03 COMP. | D19: =Cotação!D659 -> GEOLAB | E19: =Cotação!F659 -> C | F19: =Cotação!H659 -> 3.5 | G19: =Cotação!M659 -> 4.06 | H19: =Cotação!L659 -> 4.06 | I19: =Cotação!V659 -> 3.9615 | J19: =Cotação!Y659 -> -0.024261084 | K19: =Cotação!AC659 -> 1 | L19: =Cotação!AD659 -> 3.9615 | M19: =Cotação!AE659 -> 0.0985 | N19: =Cotação!AB659 -> 2015 | O19: =Cotação!AF659
A20: =Cotação!A152 -> 657521 | B20: =Cotação!B152 -> 7899095202436 | C20: =Cotação!C152 -> ALBENDAZOL 400MG CX 05 COMP | D20: =Cotação!D152 -> GEOLAB | E20: =Cotação!F152 -> A | F20: =Cotação!H152 -> 6.4 | G20: =Cotação!M152 -> 6.11 | H20: =Cotação!L152 -> 6.11 | I20: =Cotação!V152 -> 6.251 | J20: =Cotação!Y152 -> 0.023076923 | K20: =Cotação!AC152 -> 3 | L20: =Cotação!AD152 -> 18.753 | M20: =Cotação!AE152 -> -0.423 | N20: =Cotação!AB152 -> 41 | O20: =Cotação!AF152
A21: =Cotação!A70 -> 542161 | B21: =Cotação!B70 -> 7898031313465 | C21: =Cotação!C70 -> ALCOOL 70% 50ML | D21: =Cotação!D70 -> UNIPHAR | E21: =Cotação!F70 -> A | F21: =Cotação!H70 -> 30 | G21: =Cotação!M70 -> 2.54 | H21: =Cotação!L70 -> 2.54 | I21: =Cotação!V70 -> 2.584 | J21: =Cotação!Y70 -> 0.017322835 | K21: =Cotação!AC70 -> 36 | L21: =Cotação!AD70 -> 93.024 | M21: =Cotação!AE70 -> -1.584 | N21: =Cotação!AB70 -> 1525 | O21: =Cotação!AF70
A22: =Cotação!A661 -> 203301 | B22: =Cotação!B661 -> 7896004820811 | C22: =Cotação!C661 -> ALERADINA 5MG CX 10 COMP REV | D22: =Cotação!D661 -> NOVA QUIMICA | E22: =Cotação!F661 -> A | F22: =Cotação!H661 -> 7.8 | G22: =Cotação!M661 -> 4.96 | H22: =Cotação!L661 -> 4.96 | I22: =Cotação!V661 -> 4.9875 | J22: =Cotação!Y661 -> 0.0055443548 | K22: =Cotação!AC661 -> 2 | L22: =Cotação!AD661 -> 9.975 | M22: =Cotação!AE661 -> -0.055 | N22: =Cotação!AB661 -> 881 | O22: =Cotação!AF661
A23: =Cotação!A996 -> 667631 | B23: =Cotação!B996 -> 7896075707158 | C23: =Cotação!C996 -> ALICATE MERH.CUT.C/ESP.LILAS | D23: =Cotação!D996 -> MERHEJE | E23: =Cotação!F996 -> C | F23: =Cotação!H996 -> 1.4 | G23: =Cotação!M996 -> 6.89 | H23: =Cotação!L996 -> 6.89 | I23: =Cotação!V996 -> 6.3745 | J23: =Cotação!Y996 -> -0.074818578 | K23: =Cotação!AC996 -> 4 | L23: =Cotação!AD996 -> 25.498 | M23: =Cotação!AE996 -> 2.062 | N23: =Cotação!AB996 -> 7 | O23: =Cotação!AF996
A24: =Cotação!A666 -> 559861 | B24: =Cotação!B666 -> 7898179711048 | C24: =Cotação!C666 -> ALUMINEC 60MG/ML | D24: =Cotação!D666 -> IMEC | E24: =Cotação!F666 -> A | F24: =Cotação!H666 -> 11.8 | G24: =Cotação!M666 -> 4.93 | H24: =Cotação!L666 -> 4.93 | I24: =Cotação!V666 -> 4.959 | J24: =Cotação!Y666 -> 0.0058823529 | K24: =Cotação!AC666 -> 1 | L24: =Cotação!AD666 -> 4.959 | M24: =Cotação!AE666 -> -0.029 | N24: =Cotação!AB666 -> 1 | O24: =Cotação!AF666 -> ESTOQUE INSUFICIENTE
A25: =Cotação!A669 -> 125181 | B25: =Cotação!B669 -> 7899095200456 | C25: =Cotação!C669 -> AMIORON 200MG CX 20 COMP | D25: =Cotação!D669 -> GEOLAB | E25: =Cotação!F669 -> B | F25: =Cotação!H669 -> 3.2 | G25: =Cotação!M669 -> 13.72 | H25: =Cotação!L669 -> 13.72 | I25: =Cotação!V669 -> 13.68 | J25: =Cotação!Y669 -> -0.0029154519 | K25: =Cotação!AC669 -> 7 | L25: =Cotação!AD669 -> 95.76 | M25: =Cotação!AE669 -> 0.28 | N25: =Cotação!AB669 -> 258 | O25: =Cotação!AF669
A26: =Cotação!A458 -> 32821 | B26: =Cotação!B458 -> 7896004700458 | C26: =Cotação!C458 -> AMOXICILINA 250MG SUS FR 150ML | D26: =Cotação!D458 -> EMS GENERICO | E26: =Cotação!F458 -> B | F26: =Cotação!H458 -> 0.5 | G26: =Cotação!M458 -> 11.5 | H26: =Cotação!L458 -> 11.5 | I26: =Cotação!V458 -> 11.5615 | J26: =Cotação!Y458 -> 0.0053478261 | K26: =Cotação!AC458 -> 2 | L26: =Cotação!AD458 -> 23.123 | M26: =Cotação!AE458 -> -0.123 | N26: =Cotação!AB458 -> 173 | O26: =Cotação!AF458
A27: =Cotação!A462 -> 109161 | B27: =Cotação!B462 -> 7896181900498 | C27: =Cotação!C462 -> AMOXICILINA TRIIDRATADA+CLAVULANATO DE POTASSIO 400+57MG/5ML FR 70ML | D27: =Cotação!D462 -> ACHE | E27: =Cotação!F462 -> A | F27: =Cotação!H462 -> 4.5 | G27: =Cotação!M462 -> 16.58 | H27: =Cotação!L462 -> 16.05 | I27: =Cotação!V462 -> 17.195 | J27: =Cotação!Y462 -> 0.037092883 | K27: =Cotação!AC462 -> 5 | L27: =Cotação!AD462 -> 85.975 | M27: =Cotação!AE462 -> -3.075 | N27: =Cotação!AB462 -> 423 | O27: =Cotação!AF462
A28: =Cotação!A463 -> 33861 | B28: =Cotação!B463 -> 7896181919452 | C28: =Cotação!C463 -> AMOXICILINA TRIIDRATADA+CLAVULANATO DE POTASSIO 875/125MG FR 14 COMP | D28: =Cotação!D463 -> ACHE | E28: =Cotação!F463 -> A | F28: =Cotação!H463 -> 2.1 | G28: =Cotação!M463 -> 39.86 | H28: =Cotação!L463 -> 35.53 | I28: =Cotação!V463 -> 39.786 | J28: =Cotação!Y463 -> -0.0018564977 | K28: =Cotação!AC463 -> 5 | L28: =Cotação!AD463 -> 198.93 | M28: =Cotação!AE463 -> 0.37 | N28: =Cotação!AB463 -> 640 | O28: =Cotação!AF463
A29: =Cotação!A1048 -> 664111 | B29: =Cotação!B1048 -> 7894913000805 | C29: =Cotação!C1048 -> ANTIAZIL MENTA 150ML | D29: =Cotação!D1048 -> KRESS | E29: =Cotação!F1048 -> C | F29: =Cotação!H1048 -> 0.4 | G29: =Cotação!M1048 -> 13.13 | H29: =Cotação!L1048 -> 13.13 | I29: =Cotação!V1048 -> 13.1955 | J29: =Cotação!Y1048 -> 0.0049885758 | K29: =Cotação!AC1048 -> 1 | L29: =Cotação!AD1048 -> 13.1955 | M29: =Cotação!AE1048 -> -0.0655 | N29: =Cotação!AB1048 -> 539 | O29: =Cotação!AF1048
A30: =Cotação!A1049 -> 642871 | B30: =Cotação!B1049 -> 7894913003516 | C30: =Cotação!C1049 -> APETIKIDS BC XPE FRUTAS VERMELHAS 240ML | D30: =Cotação!D1049 -> KRESS | E30: =Cotação!F1049 -> C | F30: =Cotação!H1049 -> 0.5 | G30: =Cotação!M1049 -> 13.45 | H30: =Cotação!L1049 -> 13.45 | I30: =Cotação!V1049 -> 13.5185 | J30: =Cotação!Y1049 -> 0.0050929368 | K30: =Cotação!AC1049 -> 1 | L30: =Cotação!AD1049 -> 13.5185 | M30: =Cotação!AE1049 -> -0.0685 | N30: =Cotação!AB1049 -> 554 | O30: =Cotação!AF1049
A31: =Cotação!A158 -> 33203 | B31: =Cotação!B158 -> 7897595634771 | C31: =Cotação!C158 -> APIXABANA 2,5MG CX 60 COMP REV | D31: =Cotação!D158 -> SANDOZ | E31: =Cotação!F158 -> A | F31: =Cotação!H158 -> 0.9 | G31: =Cotação!M158 -> 35.32 | H31: =Cotação!L158 -> 35.32 | I31: =Cotação!V158 -> 35.53 | J31: =Cotação!Y158 -> 0.0059456399 | K31: =Cotação!AC158 -> 3 | L31: =Cotação!AD158 -> 106.59 | M31: =Cotação!AE158 -> -0.63 | N31: =Cotação!AB158 -> 399 | O31: =Cotação!AF158
A32: =Cotação!A77 -> 661591 | B32: =Cotação!B77 -> 7898108642085 | C32: =Cotação!C77 -> ATADURA DE CREPE MICKEY 08CM | D32: =Cotação!D77 -> SANFARMA | E32: =Cotação!F77 -> C | F32: =Cotação!H77 -> 1 | G32: =Cotação!M77 -> 1.935 | H32: =Cotação!L77 -> 1.935 | I32: =Cotação!V77 -> 1.5865 | J32: =Cotação!Y77 -> -0.18010336 | K32: =Cotação!AC77 -> 1 | L32: =Cotação!AD77 -> 1.5865 | M32: =Cotação!AE77 -> 0.3485 | N32: =Cotação!AB77 -> 1 | O32: =Cotação!AF77 -> ESTOQUE INSUFICIENTE
A33: =Cotação!A470 -> 46141 | B33: =Cotação!B470 -> 7898060132518 | C33: =Cotação!C470 -> AZITROMICINA 500MG CX 5 COMP | D33: =Cotação!D470 -> GLOBO | E33: =Cotação!F470 -> B | F33: =Cotação!H470 -> 1.3 | G33: =Cotação!M470 -> 5.99 | H33: =Cotação!L470 -> 5.86 | I33: =Cotação!V470 -> 5.89 | J33: =Cotação!Y470 -> -0.016694491 | K33: =Cotação!AC470 -> 2 | L33: =Cotação!AD470 -> 11.78 | M33: =Cotação!AE470 -> 0.2 | N33: =Cotação!AB470 -> 2 | O33: =Cotação!AF470 -> ESTOQUE INSUFICIENTE
A34: =Cotação!A471 -> 47221 | B34: =Cotação!B471 -> 7898216365708 | C34: =Cotação!C471 -> AZITROMICINA DI-HIDRATADA 500MG CX 5 COMP REV | D34: =Cotação!D471 -> PHARLAB | E34: =Cotação!F471 -> A | F34: =Cotação!H471 -> 17.5 | G34: =Cotação!M471 -> 5.65 | H34: =Cotação!L471 -> 5.65 | I34: =Cotação!V471 -> 5.814 | J34: =Cotação!Y471 -> 0.029026549 | K34: =Cotação!AC471 -> 15 | L34: =Cotação!AD471 -> 87.21 | M34: =Cotação!AE471 -> -2.46 | N34: =Cotação!AB471 -> 1733 | O34: =Cotação!AF471
A35: =Cotação!A950 -> 48221 | B35: =Cotação!B950 -> 7898216360123 | C35: =Cotação!C950 -> AZITROPHAR 500MG CX 3 COM REV | D35: =Cotação!D950 -> PHARLAB | E35: =Cotação!F950 -> A | F35: =Cotação!H950 -> 7.5 | G35: =Cotação!M950 -> 3.63 | H35: =Cotação!L950 -> 3.63 | I35: =Cotação!V950 -> 3.7715 | J35: =Cotação!Y950 -> 0.038980716 | K35: =Cotação!AC950 -> 11 | L35: =Cotação!AD950 -> 41.4865 | M35: =Cotação!AE950 -> -1.5565 | N35: =Cotação!AB950 -> 446 | O35: =Cotação!AF950
A36: =Cotação!A164 -> 47701 | B36: =Cotação!B164 -> 7898216364510 | C36: =Cotação!C164 -> AZITROPHAR 600MG PO SUS OR FR 15ML + SER DOS 5ML | D36: =Cotação!D164 -> PHARLAB | E36: =Cotação!F164 -> A | F36: =Cotação!H164 -> 2.5 | G36: =Cotação!M164 -> 13.6 | H36: =Cotação!L164 -> 13.6 | I36: =Cotação!V164 -> 14.0315 | J36: =Cotação!Y164 -> 0.031727941 | K36: =Cotação!AC164 -> 3 | L36: =Cotação!AD164 -> 42.0945 | M36: =Cotação!AE164 -> -1.2945 | N36: =Cotação!AB164 -> 155 | O36: =Cotação!AF164
A37: =Cotação!A675 -> 655521 | B37: =Cotação!B675 -> 7899811100596 | C37: =Cotação!C675 -> BASILICAO POMADA BISNAGA 27G BASILIFLAM | D37: =Cotação!D675 -> 0 | E37: =Cotação!F675 -> C | F37: =Cotação!H675 -> 0.3 | G37: =Cotação!M675 -> 14.62 | H37: =Cotação!L675 -> 14.62 | I37: =Cotação!V675 -> 14.934 | J37: =Cotação!Y675 -> 0.021477428 | K37: =Cotação!AC675 -> 1 | L37: =Cotação!AD675 -> 14.934 | M37: =Cotação!AE675 -> -0.314 | N37: =Cotação!AB675 -> 4 | O37: =Cotação!AF675
A38: =Cotação!A677 -> 388501 | B38: =Cotação!B677 -> 7899095220492 | C38: =Cotação!C677 -> BEBEX ADE POM BG 45G | D38: =Cotação!D677 -> GEOLAB | E38: =Cotação!F677 -> C | F38: =Cotação!H677 -> 0.4 | G38: =Cotação!M677 -> 8.95 | H38: =Cotação!L677 -> 8.95 | I38: =Cotação!V677 -> 9.044 | J38: =Cotação!Y677 -> 0.010502793 | K38: =Cotação!AC677 -> 1 | L38: =Cotação!AD677 -> 9.044 | M38: =Cotação!AE677 -> -0.094 | N38: =Cotação!AB677 -> 8 | O38: =Cotação!AF677
A39: =Cotação!A952 -> 470461 | B39: =Cotação!B952 -> 7897917001694 | C39: =Cotação!C952 -> BELFACTRIM 800+160MG CX 10 COMP | D39: =Cotação!D952 -> BELFAR | E39: =Cotação!F952 -> A | F39: =Cotação!H952 -> 2.7 | G39: =Cotação!M952 -> 5.7 | H39: =Cotação!L952 -> 5.7 | I39: =Cotação!V952 -> 5.206 | J39: =Cotação!Y952 -> -0.086666667 | K39: =Cotação!AC952 -> 7 | L39: =Cotação!AD952 -> 36.442 | M39: =Cotação!AE952 -> 3.458 | N39: =Cotação!AB952 -> 1212 | O39: =Cotação!AF952
A40: =Cotação!A678 -> 212581 | B40: =Cotação!B678 -> 7897917001762 | C40: =Cotação!C678 -> BELFAREN 10MG GEL BG 60G | D40: =Cotação!D678 -> BELFAR | E40: =Cotação!F678 -> C | F40: =Cotação!H678 -> 0.6 | G40: =Cotação!M678 -> 5.53 | H40: =Cotação!L678 -> 5.53 | I40: =Cotação!V678 -> 5.2155 | J40: =Cotação!Y678 -> -0.056871609 | K40: =Cotação!AC678 -> 2 | L40: =Cotação!AD678 -> 10.431 | M40: =Cotação!AE678 -> 0.629 | N40: =Cotação!AB678 -> 103 | O40: =Cotação!AF678
A41: =Cotação!A953 -> 470701 | B41: =Cotação!B953 -> 7896004810065 | C41: =Cotação!C953 -> BENECTRIN F CX 10 COMP | D41: =Cotação!D953 -> LEGRAND PHARMA | E41: =Cotação!F953 -> B | F41: =Cotação!H953 -> 3.3 | G41: =Cotação!M953 -> 5.23 | H41: =Cotação!L953 -> 5.23 | I41: =Cotação!V953 -> 5.263 | J41: =Cotação!Y953 -> 0.0063097514 | K41: =Cotação!AC953 -> 1 | L41: =Cotação!AD953 -> 5.263 | M41: =Cotação!AE953 -> -0.033 | N41: =Cotação!AB953 -> 416 | O41: =Cotação!AF953
A42: =Cotação!A123 -> 50201 | B42: =Cotação!B123 -> 7899095258051 | C42: =Cotação!C123 -> BESILAPIN 10MG CX 30 COMP | D42: =Cotação!D123 -> GEOLAB | E42: =Cotação!F123 -> C | F42: =Cotação!H123 -> 0.2 | G42: =Cotação!M123 -> 3.96 | H42: =Cotação!L123 -> 3.96 | I42: =Cotação!V123 -> 4.085 | J42: =Cotação!Y123 -> 0.031565657 | K42: =Cotação!AC123 -> 2 | L42: =Cotação!AD123 -> 8.17 | M42: =Cotação!AE123 -> -0.25 | N42: =Cotação!AB123 -> 221 | O42: =Cotação!AF123
A43: =Cotação!A684 -> 538061 | B43: =Cotação!B684 -> 7898031310303 | C43: =Cotação!C684 -> BICARBONATO DE SODIO 100G | D43: =Cotação!D684 -> UNIPHAR | E43: =Cotação!F684 -> B | F43: =Cotação!H684 -> 10.3 | G43: =Cotação!M684 -> 3.23 | H43: =Cotação!L684 -> 3.23 | I43: =Cotação!V684 -> 3.1255 | J43: =Cotação!Y684 -> -0.032352941 | K43: =Cotação!AC684 -> 20 | L43: =Cotação!AD684 -> 62.51 | M43: =Cotação!AE684 -> 2.09 | N43: =Cotação!AB684 -> 137 | O43: =Cotação!AF684
A44: =Cotação!A20 -> 610631 | B44: =Cotação!B20 -> 7896699011617 | C44: =Cotação!C20 -> BICO MAMAD SIL BIG REDONDO | D44: =Cotação!D20 -> LOLLY | E44: =Cotação!F20 -> C | F44: =Cotação!H20 -> 0.9 | G44: =Cotação!M20 -> 7.51 | H44: =Cotação!L20 -> 7.51 | I44: =Cotação!V20 -> 7.828 | J44: =Cotação!Y20 -> 0.042343542 | K44: =Cotação!AC20 -> 1 | L44: =Cotação!AD20 -> 7.828 | M44: =Cotação!AE20 -> -0.318 | N44: =Cotação!AB20 -> 391 | O44: =Cotação!AF20
A45: =Cotação!A172 -> 58381 | B45: =Cotação!B172 -> 7899095249639 | C45: =Cotação!C172 -> BIMATOPROSTA 0,3MG/ML FR 3ML | D45: =Cotação!D172 -> GEOLAB | E45: =Cotação!F172 -> B | F45: =Cotação!H172 -> 0.6 | G45: =Cotação!M172 -> 24.99 | H45: =Cotação!L172 -> 24.99 | I45: =Cotação!V172 -> 24.871 | J45: =Cotação!Y172 -> -0.0047619048 | K45: =Cotação!AC172 -> 1 | L45: =Cotação!AD172 -> 24.871 | M45: =Cotação!AE172 -> 0.119 | N45: =Cotação!AB172 -> 149 | O45: =Cotação!AF172
A46: =Cotação!A1000 -> 670271 | B46: =Cotação!B1000 -> 7896033295192 | C46: =Cotação!C1000 -> BOMBA MANUAL P/TIRAR LEITE MAMY 629501 | D46: =Cotação!D1000 -> LILLO | E46: =Cotação!F1000 -> A | F46: =Cotação!H1000 -> 0.6 | G46: =Cotação!M1000 -> 49.25 | H46: =Cotação!L1000 -> 49.25 | I46: =Cotação!V1000 -> 48.3455 | J46: =Cotação!Y1000 -> -0.018365482 | K46: =Cotação!AC1000 -> 1 | L46: =Cotação!AD1000 -> 48.3455 | M46: =Cotação!AE1000 -> 0.9045 | N46: =Cotação!AB1000 -> 122 | O46: =Cotação!AF1000
A47: =Cotação!A173 -> 62441 | B47: =Cotação!B173 -> 7896004725420 | C47: =Cotação!C173 -> BROMETO DE IPRATROPIO SOL INAL FR 20ML | D47: =Cotação!D173 -> EMS GENERICO | E47: =Cotação!F173 -> C | F47: =Cotação!H173 -> 3.2 | G47: =Cotação!M173 -> 5.2533333 | H47: =Cotação!L173 -> 3.72 | I47: =Cotação!V173 -> 3.781 | J47: =Cotação!Y173 -> -0.2802665 | K47: =Cotação!AC173 -> 7 | L47: =Cotação!AD173 -> 26.467 | M47: =Cotação!AE173 -> 10.306333 | N47: =Cotação!AB173 -> 348 | O47: =Cotação!AF173
A48: =Cotação!A176 -> 68701 | B48: =Cotação!B176 -> 7896004758268 | C48: =Cotação!C176 -> BUDESONIDA 32MCG FR X 120ML | D48: =Cotação!D176 -> EMS GENERICO | E48: =Cotação!F176 -> B | F48: =Cotação!H176 -> 1.4 | G48: =Cotação!M176 -> 15.49 | H48: =Cotação!L176 -> 15.36 | I48: =Cotação!V176 -> 15.5895 | J48: =Cotação!Y176 -> 0.006423499 | K48: =Cotação!AC176 -> 4 | L48: =Cotação!AD176 -> 62.358 | M48: =Cotação!AE176 -> -0.398 | N48: =Cotação!AB176 -> 276 | O48: =Cotação!AF176
A49: =Cotação!A177 -> 68721 | B49: =Cotação!B177 -> 7896004758275 | C49: =Cotação!C177 -> BUDESONIDA 64MCG FR X 120ML | D49: =Cotação!D177 -> EMS GENERICO | E49: =Cotação!F177 -> A | F49: =Cotação!H177 -> 1.7 | G49: =Cotação!M177 -> 22.79 | H49: =Cotação!L177 -> 21.3 | I49: =Cotação!V177 -> 21.6125 | J49: =Cotação!Y177 -> -0.051667398 | K49: =Cotação!AC177 -> 3 | L49: =Cotação!AD177 -> 64.8375 | M49: =Cotação!AE177 -> 3.5325 | N49: =Cotação!AB177 -> 37 | O49: =Cotação!AF177
A50: =Cotação!A696 -> 596481 | B50: =Cotação!B696 -> 7894164005260 | C50: =Cotação!C696 -> CALOFIM 5ML SOL (AIRELA) | D50: =Cotação!D696 -> AIRELA | E50: =Cotação!F696 -> B | F50: =Cotação!H696 -> 3.2 | G50: =Cotação!M696 -> 8.53 | H50: =Cotação!L696 -> 8.53 | I50: =Cotação!V696 -> 8.6165 | J50: =Cotação!Y696 -> 0.01014068 | K50: =Cotação!AC696 -> 5 | L50: =Cotação!AD696 -> 43.0825 | M50: =Cotação!AE696 -> -0.4325 | N50: =Cotação!AB696 -> 112 | O50: =Cotação!AF696
A51: =Cotação!A22 -> 603521 | B51: =Cotação!B22 -> 7896033233736 | C51: =Cotação!C22 -> CANECA LILLO AP S 150ML MENINA | D51: =Cotação!D22 -> LILLO | E51: =Cotação!F22 -> C | F51: =Cotação!H22 -> 0.1 | G51: =Cotação!M22 -> 25.77 | H51: =Cotação!L22 -> 25.77 | I51: =Cotação!V22 -> 25.346 | J51: =Cotação!Y22 -> -0.01645324 | K51: =Cotação!AC22 -> 1 | L51: =Cotação!AD22 -> 25.346 | M51: =Cotação!AE22 -> 0.424 | N51: =Cotação!AB22 -> 18 | O51: =Cotação!AF22
A52: =Cotação!A23 -> 603531 | B52: =Cotação!B23 -> 7896033233729 | C52: =Cotação!C23 -> CANECA LILLO AP S 150ML MENINO | D52: =Cotação!D23 -> LILLO | E52: =Cotação!F23 -> C | F52: =Cotação!H23 -> 0.2 | G52: =Cotação!M23 -> 25.77 | H52: =Cotação!L23 -> 25.77 | I52: =Cotação!V23 -> 24.035 | J52: =Cotação!Y23 -> -0.067326348 | K52: =Cotação!AC23 -> 1 | L52: =Cotação!AD23 -> 24.035 | M52: =Cotação!AE23 -> 1.735 | N52: =Cotação!AB23 -> 3 | O52: =Cotação!AF23
A53: =Cotação!A181 -> 78101 | B53: =Cotação!B181 -> 7897848500907 | C53: =Cotação!C181 -> CARBOCISTEINA 20 MG/ML XPE INF 100 ML | D53: =Cotação!D181 -> NATIVITA IND | E53: =Cotação!F181 -> C | F53: =Cotação!H181 -> 0.4 | G53: =Cotação!M181 -> 8 | H53: =Cotação!L181 -> 0 | I53: =Cotação!V181 -> 6.517 | J53: =Cotação!Y181 -> -0.185375 | K53: =Cotação!AC181 -> 2 | L53: =Cotação!AD181 -> 13.034 | M53: =Cotação!AE181 -> 2.966 | N53: =Cotação!AB181 -> 135 | O53: =Cotação!AF181
